Workbook
Name OLE_LINK1: 'Annex 3 Preserved charges'!#REF!

Sheet Overview
A2: Company and Licence name, charging year, effective from, status
B3: Company and Licence name | C3: Year | D3: Effective From | E3: Status
A4: Company and Licence name, charging year, effective from, status | B4: London Power Networks | C4: 2027/28 | D4: 1 April 2027 | E4: Final
A6: List of data tables in this workbook
A7: Worksheet | B7: Information
A8: Annex 1 LV, HV and Unmetered Supplies charges | B8: Annex 1 contains the charges to LV and HV Designated Properties and Unmetered Supplies.
A9: Annex 2 Designated EHV charges | B9: ="Annex 2 contains the charges to Designated EHV Properties and charges applied to LDNOs with Designated EHV Properties/end-users embedded in networks within the " &B4 &" Licence area." -> Annex 2 contains the charges to Designated EHV Properties and charges applied to LDNOs with Designated EHV Properties/end-users embedded in networks within the London Power Networks Licence area.
A10: Annex 3 Preserved charges | B10: Annex 3 contains details of any preserved and additional charges that are valid at this time.
A11: Annex 4 LDNO charges | B11: ="Annex 4 contains charges that are levied on the owner of an embedded network within the "&B4&" Licence area. "&"Electricity suppliers and consumers who have properties connected to an embedded network should contact the embedded network owner to determine their distribution charges."&" The charges listed in this table are not payable by domestic consumers, business consumers or electricity suppliers." -> Annex 4 contains charges that are levied on the owner of an embedded network within the London Power Networks Licence area. Electricity suppliers and consumers who have properties connected to an embedded network should contact the embedded network owner to determine their distribution charges. The charges listed in this table are not payable by domestic consumers, business consumers or electricity suppliers.
A12: Annex 5 LLFs | B12: Annex 5 has been intentionally left blank as this charging statement is published a complete year before the LLFs have been audited. The line loss factors that are approved by the BSC Panel for the applicable year and consequently published on the Elexon website will take precedence and be used in Settlement. This annex will be re-published with these values once they are available.
A13: Annex 6 Charges for New or Amended Designated EHV Properties | B13: ="Annex 6 contains the charges for new or amended Designated EHV Properties and charges applied to LDNOs with new or amended Designated EHV Properties/end-users embedded in networks within the " &B4 &" Licence area." -> Annex 6 contains the charges for new or amended Designated EHV Properties and charges applied to LDNOs with new or amended Designated EHV Properties/end-users embedded in networks within the London Power Networks Licence area.
A14: Annex 7 Fixed adders for Supplier of Last Resort and Eligible Bad Debt pass-through costs | B14: Annex 7 contains the fixed adders to recover Supplier of Last Resort and Eligible Bad Debt pass-through costs. The Excess Supplier of Last Resort fixed adder relates to an increase to previously published charges only.
A15: Nodal prices | B15: Contains the underlying nodal costs used to calculate the current EDCM charges.
A16: SSC unit rate lookup | B16: Contains a mapping of Standard Settlement Configurations to common decodings
A17: Residual Charging Bandings | B17: Contains the four Residual charging band allocation for Customers
A18: TNUoS Mapping | B18: Contains a mapping of DUoS Tariffs to TNUoS Site Charging Bands
A19: Charge calculator | B19: Charge calculator is a tool to help you estimate your distribution charges using current consumption data and forecast consumption data.
A21: Notes to users of this spreadsheet
A23: Please use this spreadsheet with reference to the LC14 use of system charging statement.
A25: Notes to DNOs populating this spreadsheet
A27: DNOs must endeavour to maintain consistency in the structure of this spreadsheet. Any changes to the structure must be noted in the 'Notes to users of this spreadsheet'
A28: The drop down list on the charge calculator can be expanded by unprotecting the charge calculator sheet and selecting 'data', 'data validation...' and then expanding the 'source' data range. The sheet can then be protected.

Sheet Annex 1 LV, HV and UMS charges
A1: Back to Overview
A2: =Overview!B4& " - Effective from "&Overview!D4&" - "&Overview!E4&" LV and HV charges" -> London Power Networks - Effective from 1 April 2027 - Final LV and HV charges
A4: Time Bands for LV and HV Designated Properties | G4: Time Bands for Unmetered Properties
A5: Time periods | B5: Red Time Band | C5: Amber Time Band | E5: Green Time Band | I5: Black Time Band | J5: Yellow Time Band | K5: Green Time Band
A6: Monday to Friday (Including Bank Holidays) All Year | B6: 11:00 - 14:00 16:00 - 19:00 | C6: 07:00 - 11:00 14:00 - 16:00 19:00 - 23:00 | E6: 00:00 - 07:00 23:00 - 24:00 | G6: Monday to Friday (Including Bank Holidays) June to August Inclusive | I6: 11:00 - 14:00 | J6: 07:00 - 11:00 14:00 - 23:00 | K6: 00:00 - 07:00 23:00 - 24:00
A7: Saturday and Sunday All Year | E7: 00:00 - 24:00 | G7: Monday to Friday (Including Bank Holidays) November to February Inclusive | I7: 16:00 - 19:00 | J7: 07:00 - 16:00 19:00 - 23:00 | K7: 00:00 - 07:00 23:00 - 24:00
A8: Notes | B8: All the above times are in UK Clock time | G8: Monday to Friday (Including Bank Holidays) March, April, May and September, October | J8: 07:00 - 23:00 | K8: 00:00 - 07:00 23:00 - 24:00
G9: Saturday and Sunday All year | K9: 00:00 - 24:00
G10: Notes | I10: All the above times are in UK Clock time
A12: Tariff name | B12: Open LLFCs/ DUoS Tariff IDs | C12: PCs | D12: Red/black unit charge p/kWh | E12: Amber/yellow unit charge p/kWh | F12: Green unit charge p/kWh | G12: Fixed charge p/MPAN/day | H12: Capacity charge p/kVA/day | I12: Exceeded capacity charge p/kVA/day | J12: Reactive power charge p/kVArh | K12: Closed LLFCs/ DUoS Tariff IDs
A13: Domestic Aggregated or CT with Residual | B13: 1 | C13: 0, 1, 2 | D13: 12.197 | E13: 1.243 | F13: 0 | G13: 0 | K13: 902
A14: Domestic Aggregated (Related MPAN) | B14: 2 | C14: 2 | D14: 12.414 | E14: 1.46 | F14: 0.108
A15: Non-Domestic Aggregated or CT No Residual | B15: 199 | C15: 0, 3, 4, 5-8 | D15: 9.611 | E15: 1.13 | F15: 0.083 | G15: 5.91
A16: Non-Domestic Aggregated or CT Band 1 | B16: 201, N01 | C16: 0, 3, 4, 5-8 | D16: 9.491 | E16: 1.01 | F16: 0 | G16: 0
A17: Non-Domestic Aggregated or CT Band 2 | B17: 202, N02 | C17: 0, 3, 4, 5-8 | D17: 8.644 | E17: 0.164 | F17: 0 | G17: 0
A18: Non-Domestic Aggregated or CT Band 3 | B18: 203, N03 | C18: 0, 3, 4, 5-8 | D18: 8.334 | E18: 0 | F18: 0 | G18: 0
A19: Non-Domestic Aggregated or CT Band 4 | B19: 204, N04 | C19: 0, 3, 4, 5-8 | D19: 7.932 | E19: 0 | F19: 0 | G19: 0
A20: Non-Domestic Aggregated (Related MPAN) | B20: 200 | C20: 4 | D20: 9.611 | E20: 1.13 | F20: 0.083
A21: LV Site Specific No Residual | B21: 70 | C21: 0 | D21: 7.639 | E21: 0.922 | F21: 0.062 | G21: 14.51 | H21: 8.26 | I21: 8.26 | J21: 0.588
A22: LV Site Specific Band 1 | B22: 71 | C22: 0 | D22: 4.886 | E22: 0.322 | F22: 0.03 | G22: 2.3 | H22: 8.26 | I22: 8.26 | J22: 0.588
A23: LV Site Specific Band 2 | B23: 72 | C23: 0 | D23: 4.821 | E23: 0.322 | F23: 0.03 | G23: 2.3 | H23: 8.26 | I23: 8.26 | J23: 0.588
A24: LV Site Specific Band 3 | B24: 73 | C24: 0 | D24: 4.763 | E24: 0.322 | F24: 0.03 | G24: 2.3 | H24: 8.26 | I24: 8.26 | J24: 0.588
A25: LV Site Specific Band 4 | B25: 74 | C25: 0 | D25: 4.692 | E25: 0.322 | F25: 0.03 | G25: 2.3 | H25: 8.26 | I25: 8.26 | J25: 0.588
A26: LV Sub Site Specific No Residual | B26: 80 | C26: 0 | D26: 4.691 | E26: 0.599 | F26: 0.033 | G26: 12.21 | H26: 10.38 | I26: 10.38 | J26: 0.348
A27: LV Sub Site Specific Band 1 | B27: 81 | C27: 0 | D27: 1.938 | E27: 0 | F27: 0 | G27: 0 | H27: 10.38 | I27: 10.38 | J27: 0.348
A28: LV Sub Site Specific Band 2 | B28: 82 | C28: 0 | D28: 1.873 | E28: 0 | F28: 0 | G28: 0 | H28: 10.38 | I28: 10.38 | J28: 0.348
A29: LV Sub Site Specific Band 3 | B29: 83 | C29: 0 | D29: 1.815 | E29: 0 | F29: 0 | G29: 0 | H29: 10.38 | I29: 10.38 | J29: 0.348
A30: LV Sub Site Specific Band 4 | B30: 84 | C30: 0 | D30: 1.743 | E30: 0 | F30: 0 | G30: 0 | H30: 10.38 | I30: 10.38 | J30: 0.348
A31: HV Site Specific No Residual | B31: 90 | C31: 0 | D31: 3.488 | E31: 0.446 | F31: 0.026 | G31: 129.42 | H31: 10.65 | I31: 10.65 | J31: 0.271
A32: HV Site Specific Band 1 | B32: 91 | C32: 0 | D32: 0.42 | E32: 0 | F32: 0 | G32: 0 | H32: 10.65 | I32: 10.65 | J32: 0.271
... A35: HV Site Specific Band 4 | B35: 94 | C35: 0 | D35: 0.24 | E35: 0 | F35: 0 | G35: 0 | H35: 10.65 | I35: 10.65 | J35: 0.271
A36: Unmetered Supplies | B36: 350, 420, 421, 422, 423 | C36: 0, 1 or 8 | D36: 40.972 | E36: 3.346 | F36: 0.471 | K36: 424, 425, 426, 427, 428, 429, 430, 431, 432, 433, 434, 435
A37: LV Generation Aggregated | B37: 932 | C37: 0, 8 | D37: -7.828 | E37: -0.921 | F37: -0.068 | G37: 0
A38: LV Sub Generation Aggregated | C38: 0 | D38: -6.433 | E38: -0.769 | F38: -0.054 | G38: 0
A39: LV Generation Site Specific | B39: 980 | C39: 0 | D39: -7.828 | E39: -0.921 | F39: -0.068 | G39: 0 | J39: 0.55
A40: LV Generation Site Specific no RP Charge | B40: 981 | C40: 0 | D40: -7.828 | E40: -0.921 | F40: -0.068 | G40: 0
A41: LV Sub Generation Site Specific | B41: 984 | C41: 0 | D41: -6.433 | E41: -0.769 | F41: -0.054 | G41: 0 | J41: 0.433
A42: LV Sub Generation Site Specific no RP Charge | B42: 985 | C42: 0 | D42: -6.433 | E42: -0.769 | F42: -0.054 | G42: 0
A43: HV Generation Site Specific | B43: 988 | C43: 0 | D43: -4.179 | E43: -0.534 | F43: -0.029 | G43: 9.08 | J43: 0.382
A44: HV Generation Site Specific no RP Charge | B44: 989 | C44: 0 | D44: -4.179 | E44: -0.534 | F44: -0.029 | G44: 9.08

Sheet Annex 2 Designated EHV charges
A1: Back to Overview | C1: Note: The DNO reserves the right to apply the listed charges to any other MPANs/MSIDs associated with the site. This includes reallocating charges to a traded MPAN at the same site where another MPAN has been disconnected or de-energised.
A2: =Overview!B4& " - Effective from "&Overview!D4&" - "&Overview!E4&" Designated EHV charges" -> London Power Networks - Effective from 1 April 2027 - Final Designated EHV charges
A4: Time Periods for Designated EHV Properties
A5: Time periods | D5: Super Red Time Band
A6: Monday to Friday (Including Bank Holidays) June to August Inclusive | D6: 11:00 - 14:00
A7: Monday to Friday (Including Bank Holidays) November to February Inclusive | D7: 16:00 - 19:00
A8: Notes | D8: All the above times are in UK Clock time
A10: Import Unique Identifier | B10: LLFC/ DUoS Tariff ID | C10: Import MPANs/MSIDs | D10: Export Unique Identifier | E10: LLFC/ DUoS Tariff ID | F10: Export MPANs/MSIDs | G10: Name | H10: Residual Charging Band | I10: Import Super Red unit charge (p/kWh) | J10: Import fixed charge (p/day) | K10: Import capacity charge (p/kVA/day) | L10: Import exceeded capacity charge (p/kVA/day) | M10: Export Super Red unit charge (p/kWh) | N10: Export fixed charge (p/day) | O10: Export capacity charge (p/kVA/day) | P10: Export exceeded capacity charge (p/kVA/day)
A11: 21MOOR | B11: 854 | C11: 1200062747376;1200062747385 | G11: 21MOOR | H11: 2 | I11: 0.219 | J11: 11254.69 | K11: 2.68 | L11: 2.68
A12: 22BSHP | B12: 810 | C12: 1200062355497;1200062355502 | G12: 22BSHP | H12: 3 | I12: 0.208 | J12: 28784.81 | K12: 2.74 | L12: 2.74
A13: BISHPC | B13: 811 | C13: 1200061143976;1200061143985 | G13: BISHPC | H13: 3 | I13: 0.197 | J13: 28784.81 | K13: 2.74 | L13: 2.74
A14: BLMBGN | B14: 820 | C14: 1200061385700;1200061385710 | G14: BLMBGN | H14: 2 | I14: 0.216 | J14: 11254.69 | K14: 2.59 | L14: 2.59
A15: BLMBGS | B15: 821 | C15: 1200061385729;1200061385738 | G15: BLMBGS | H15: 2 | I15: 0.215 | J15: 11254.69 | K15: 1.96 | L15: 1.96
A16: BRDGTE | B16: 805 | C16: 1200061148014;1200061148023 | G16: BRDGTE | H16: 2 | I16: 0.207 | J16: 11254.69 | K16: 3.34 | L16: 3.34
A17: BRKFLD | B17: 829 | C17: 1200061148060;1200061148079 | G17: BRKFLD | H17: 2 | I17: 0.22 | J17: 11254.69 | K17: 2.62 | L17: 2.62
A18: BRMLEY | C18: MSID: 1630 | G18: BRMLEY | H18: 4 | I18: 0.212 | J18: 68626.32 | K18: 5.1 | L18: 5.1
A19: CRLIMM | B19: 812 | C19: 1200062090483;1200062090492 | G19: CRLIMM | H19: 4 | I19: 0.003 | J19: 82036.16 | K19: 1.5 | L19: 1.5
A20: DART11 | C20: MSID: 1032 | G20: DART11 | H20: 2 | I20: 0.285 | J20: 10677.01 | K20: 6.51 | L20: 6.51
A21: DART33 | C21: MSID: 1032 | G21: DART33 | H21: 3 | I21: 0.603 | J21: 28207.13 | K21: 7.02 | L21: 7.02
A22: EPNLEI | C22: MSID: 1628 | G22: EPNLEI | H22: 4 | I22: 0.024 | J22: 68626.32 | K22: 5.2 | L22: 5.2
A23: FENAVE | B23: 813 | C23: 1200062132159;1200062132168 | G23: FENAVE | H23: 2 | I23: 0.205 | J23: 11254.69 | K23: 2.13 | L23: 2.13
A24: FENCHS | B24: 800 | C24: 1200061144029;1200061144038 | G24: FENCHS | H24: 2 | I24: 0.26 | J24: 11254.69 | K24: 2.81 | L24: 2.81
A25: GBLSWI | B25: 843 | C25: 1200050913681;1200050913690;1200050913706;1200050913715 | G25: GBLSWI | H25: 4 | I25: 0.003 | J25: 80311.31 | K25: 2.44 | L25: 2.44
A26: KNGLPN | C26: MSID: 1027 | G26: KNGLPN | H26: 2 | I26: 0 | J26: 10677.01 | K26: 4.92 | L26: 4.92
A27: LEDNHS | B27: 808 | C27: 1200061144065;1200061144074 | G27: LEDNHS | H27: 2 | I27: 0.2 | J27: 11254.69 | K27: 2.65 | L27: 2.65
A28: LIMEST | B28: 814 | C28: 1200062132006;1200062132015 | G28: LIMEST | H28: 2 | I28: 0.209 | J28: 11254.69 | K28: 2.44 | L28: 2.44
A29: LNWAL1 | B29: 816 | C29: 1200061148194;1200061148200 | G29: LNWAL1 | H29: 1 | I29: 0.217 | J29: 1553.35 | K29: 3.41 | L29: 3.41
A30: LNWALL | B30: 816 | C30: 1200061953070;1200061953089 | G30: LNWALL | H30: 2 | I30: 0.217 | J30: 11254.69 | K30: 1.42 | L30: 1.42
A31: LU_ACT | C31: MSID: 1631 | G31: LU_ACT | H31: 3 | I31: 0 | J31: 28589.8 | K31: 2.51 | L31: 2.51
A32: LU_CAN | B32: 818 | C32: 1200060323207;1200060323216 | G32: LU_CAN | H32: 4 | I32: 0 | J32: 79377.14 | K32: 2.32 | L32: 2.32
A33: LU_CHA | B33: 801 | C33: 1200061231921;1200061231930;1200061231940;1200061231959 | G33: LU_CHA | H33: 4 | I33: 0 | J33: 79971.42 | K33: 1.74 | L33: 1.74
A34: LU_HOX | B34: 804 | C34: 1200060323191 | G34: LU_HOX | H34: 4 | I34: 0 | J34: 77804.46 | K34: 0.68 | L34: 0.68
A35: LU_LOT | B35: 838 | C35: 1200050376902;1200050376911 | G35: LU_LOT | H35: 4 | I35: 0.001 | J35: 111285.72 | K35: 2.81 | L35: 2.81
A36: LU_MAN | B36: 837 | C36: 1200010200926 | G36: LU_MAN | H36: 4 | I36: 0.002 | J36: 98926.85 | K36: 2.34 | L36: 2.34
A37: LU_STE | B37: 839 | C37: 1200010157225;1200010157234 | G37: LU_STE | H37: 4 | I37: 0 | J37: 78217.28 | K37: 3.81 | L37: 3.81
A38: MRKLNE | B38: 806 | C38: 1200061378624;1200061378633 | G38: MRKLNE | H38: 1 | I38: 0.237 | J38: 1553.35 | K38: 2.19 | L38: 2.19
A39: NGC_BA | B39: 817 | C39: 1200010151863;1200010151872 | G39: NGC_BA | H39: 1 | I39: 0 | J39: 975.67 | K39: 0.86 | L39: 0.86
A40: NR_BOW | B40: 807 | C40: 1200060280440;1200060280468 | D40: NR_BOW | E40: 707 | F40: 1200060280430;1200060280459 | G40: NR_BOW | H40: 3 | I40: 0.008 | J40: 36853.77 | K40: 4.32 | L40: 4.32
A41: NR_BRO | B41: 847 | C41: 1200010251559 | G41: NR_BRO | H41: 4 | I41: 0.13 | J41: 72138.7 | K41: 3.11 | L41: 3.11
A42: NR_CIT | B42: 846 | C42: 1200010251521 | G42: NR_CIT | H42: 1 | I42: 0.002 | J42: 1103.23 | K42: 1.61 | L42: 1.61
A43: NR_MAD | B43: 840 | C43: 1200010251540 | G43: NR_MAD | H43: 1 | I43: 0.03 | J43: 1230.79 | K43: 1.11 | L43: 1.11
A44: NR_W11 | B44: 841 | C44: 1200010251512 | G44: NR_W11 | H44: 3 | I44: 0 | J44: 37581.58 | K44: 2.81 | L44: 2.81
A45: NR_W25 | B45: 842 | C45: 1200010251498 | D45: NR_W25 | E45: 703 | F45: 1200052486866 | G45: NR_W25 | H45: 3 | I45: 0.016 | J45: 36223.61 | K45: 3.15 | L45: 3.15
A46: NR_WES | B46: 848 | C46: 1200010251568 | D46: NR_WES | E46: 716 | F46: 1200052486875 | G46: NR_WES | H46: 4 | I46: 0.214 | J46: 76588.56 | K46: 2.56 | L46: 2.56 | M46: 0 | N46: 631.92 | O46: 0.05 | P46: 0.05
A47: NR_WHI | B47: 849 | C47: 1200050493611 | G47: NR_WHI | H47: 1 | I47: 5.881 | J47: 1103.23 | K47: 2.68 | L47: 2.68
A48: NR_WIM | B48: 844 | C48: 1200010200874 | G48: NR_WIM | H48: 4 | I48: 0.197 | J48: 81222.03 | K48: 2.28 | L48: 2.28
A49: TELEHW | B49: 809 | C49: 1200060951114;1200060951123 | G49: TELEHW | H49: 4 | I49: 0.003 | J49: 70205.31 | K49: 2.96 | L49: 2.96
A50: THAMEB | B50: 828 | C50: 1200010146153;1200010146162;1200010146171;1200061197703 | D50: THAMEB | E50: 701 | F50: 1200050312030;1200050312040;1200061219394;1200050312059 | G50: THAMEB | H50: 4 | I50: 0 | J50: 72666.02 | K50: 0.78 | L50: 0.78 | M50: 0 | N50: 1529.31 | O50: 0.05 | P50: 0.05
A51: THAMEC | B51: 802 | C51: 1200061171324;1200061171333 | D51: THAMEC | E51: 702 | F51: 1200061171342;1200061171351 | G51: THAMEC | H51: 4 | I51: 0 | J51: 71987.77 | K51: 4.36 | L51: 4.36 | M51: -0.002 | N51: 2358.99 | O51: 0.05 | P51: 0.05
A52: TWKIRT | B52: 823 | C52: 1200061999491;1200061999507;1200062001242;1200062001251 | G52: TWKIRT | H52: 1 | I52: 1.454 | J52: 1230.79 | K52: 0.78 | L52: 0.78
A53: VOLTDC | B53: 803 | C53: 1200061148032;1200061148041 | G53: VOLTDC | H53: 2 | I53: 0.207 | J53: 12519.87 | K53: 2.92 | L53: 2.92
A54: BELVE2 | B54: 865 | C54: 1200063126740 | G54: BELVE2 | H54: 0 | I54: 0 | J54: 29394.67 | K54: 1.06 | L54: 1.06
A55: BELVED | B55: 815 | C55: 1200060787109 | D55: BELVED | E55: 711 | F55: 1200060787118 | G55: BELVED | H55: 0 | I55: 0 | J55: 545.58 | K55: 0.68 | L55: 0.68 | M55: 0 | N55: 1033.4 | O55: 0.05 | P55: 0.05
A56: SELCHP | B56: 827 | C56: 1200010175650 | D56: SELCHP | E56: 730 | F56: 1200010258304 | G56: SELCHP | H56: 1 | I56: 0.304 | J56: 1458.55 | K56: 1.11 | L56: 1.11 | M56: -0.304 | N56: 5121.4 | O56: 0.05 | P56: 0.05
A57: TLRSLN | C57: MSID: 5538 | D57: TLRSLN | F57: MSID: 5538 | G57: TLRSLN | H57: 1 | I57: 0.014 | J57: 975.67 | K57: 0.99 | L57: 0.99 | M57: -0.014 | N57: 0 | O57: 0.05 | P57: 0.05

Sheet Annex 2a Import
A1: Note: The list of MPANs / MSIDs provided may be incomplete; the DNO reserves the right to apply the listed charges to any other MPANs / MSIDs associated with the site. Note: This table is automatically populated based on the content of the tab entitled 'Annex 2 Designated EHV charges'. The timebands are as shown in Annex 2.
A2: =Overview!B4& " - Effective from "&Overview!D4&" - "&Overview!E4&" Designated EHV import charges" -> London Power Networks - Effective from 1 April 2027 - Final Designated EHV import charges
A4: Import Unique Identifier | B4: LLFC/ DUoS Tariff ID | C4: Import MPANs/MSIDs | D4: Name | E4: ='Annex 2 Designated EHV charges'!I10 -> Import Super Red unit charge (p/kWh) | F4: ='Annex 2 Designated EHV charges'!J10 -> Import fixed charge (p/day) | G4: ='Annex 2 Designated EHV charges'!K10 -> Import capacity charge (p/kVA/day) | H4: ='Annex 2 Designated EHV charges'!L10 -> Import exceeded capacity charge (p/kVA/day)
A5: {=IFERROR(INDEX('Annex 2 Designated EHV charges'!$A$11:$A$58, MATCH(0, IF(ISBLANK('Annex 2 Designated EHV charges'!$A$11:$A$58),1, COUNTIF(A$4:$A4, 'Annex 2 Designated EHV charges'!$A$11:$A$58)), 0)),"")} -> 21MOOR | B5: =IF($A5="","",VLOOKUP($A5,'Annex 2 Designated EHV charges'!$A:$O,2,0)) -> 854 | C5: =IF($A5="","",VLOOKUP($A5,'Annex 2 Designated EHV charges'!$A:$O,3,0)) -> 1200062747376;1200062747385 | D5: =IF($A5="","",VLOOKUP($A5,'Annex 2 Designated EHV charges'!$A:$O,7,0)) -> 21MOOR | E5: =IFERROR(IF(VLOOKUP($A5,'Annex 2 Designated EHV charges'!$A:$P,9,FALSE)=0,"",VLOOKUP($A5,'Annex 2 Designated EHV charges'!$A:$P,9,FALSE)),"") -> 0.219 | F5: =IFERROR(IF(VLOOKUP($A5,'Annex 2 Designated EHV charges'!$A:$P,10,FALSE)=0,"",VLOOKUP($A5,'Annex 2 Designated EHV charges'!$A:$P,10,FALSE)),"") -> 11254.69 | G5: =IFERROR(IF(VLOOKUP($A5,'Annex 2 Designated EHV charges'!$A:$P,11,FALSE)=0,"",VLOOKUP($A5,'Annex 2 Designated EHV charges'!$A:$P,11,FALSE)),"") -> 2.68 | H5: =IFERROR(IF(VLOOKUP($A5,'Annex 2 Designated EHV charges'!$A:$P,12,FALSE)=0,"",VLOOKUP($A5,'Annex 2 Designated EHV charges'!$A:$P,12,FALSE)),"") -> 2.68
A6: {=IFERROR(INDEX('Annex 2 Designated EHV charges'!$A$11:$A$58, MATCH(0, IF(ISBLANK('Annex 2 Designated EHV charges'!$A$11:$A$58),1, COUNTIF(A$4:$A5, 'Annex 2 Designated EHV charges'!$A$11:$A$58)), 0)),"")} -> 22BSHP | B6: =IF($A6="","",VLOOKUP($A6,'Annex 2 Designated EHV charges'!$A:$O,2,0)) -> 810 | C6: =IF($A6="","",VLOOKUP($A6,'Annex 2 Designated EHV charges'!$A:$O,3,0)) -> 1200062355497;1200062355502 | D6: =IF($A6="","",VLOOKUP($A6,'Annex 2 Designated EHV charges'!$A:$O,7,0)) -> 22BSHP | E6: =IFERROR(IF(VLOOKUP($A6,'Annex 2 Designated EHV charges'!$A:$P,9,FALSE)=0,"",VLOOKUP($A6,'Annex 2 Designated EHV charges'!$A:$P,9,FALSE)),"") -> 0.208 | F6: =IFERROR(IF(VLOOKUP($A6,'Annex 2 Designated EHV charges'!$A:$P,10,FALSE)=0,"",VLOOKUP($A6,'Annex 2 Designated EHV charges'!$A:$P,10,FALSE)),"") -> 28784.81 | G6: =IFERROR(IF(VLOOKUP($A6,'Annex 2 Designated EHV charges'!$A:$P,11,FALSE)=0,"",VLOOKUP($A6,'Annex 2 Designated EHV charges'!$A:$P,11,FALSE)),"") -> 2.74 | H6: =IFERROR(IF(VLOOKUP($A6,'Annex 2 Designated EHV charges'!$A:$P,12,FALSE)=0,"",VLOOKUP($A6,'Annex 2 Designated EHV charges'!$A:$P,12,FALSE)),"") -> 2.74
A7: {=IFERROR(INDEX('Annex 2 Designated EHV charges'!$A$11:$A$58, MATCH(0, IF(ISBLANK('Annex 2 Designated EHV charges'!$A$11:$A$58),1, COUNTIF(A$4:$A6, 'Annex 2 Designated EHV charges'!$A$11:$A$58)), 0)),"")} -> BISHPC | B7: =IF($A7="","",VLOOKUP($A7,'Annex 2 Designated EHV charges'!$A:$O,2,0)) -> 811 | C7: =IF($A7="","",VLOOKUP($A7,'Annex 2 Designated EHV charges'!$A:$O,3,0)) -> 1200061143976;1200061143985 | D7: =IF($A7="","",VLOOKUP($A7,'Annex 2 Designated EHV charges'!$A:$O,7,0)) -> BISHPC | E7: =IFERROR(IF(VLOOKUP($A7,'Annex 2 Designated EHV charges'!$A:$P,9,FALSE)=0,"",VLOOKUP($A7,'Annex 2 Designated EHV charges'!$A:$P,9,FALSE)),"") -> 0.197 | F7: =IFERROR(IF(VLOOKUP($A7,'Annex 2 Designated EHV charges'!$A:$P,10,FALSE)=0,"",VLOOKUP($A7,'Annex 2 Designated EHV charges'!$A:$P,10,FALSE)),"") -> 28784.81 | G7: =IFERROR(IF(VLOOKUP($A7,'Annex 2 Designated EHV charges'!$A:$P,11,FALSE)=0,"",VLOOKUP($A7,'Annex 2 Designated EHV charges'!$A:$P,11,FALSE)),"") -> 2.74 | H7: =IFERROR(IF(VLOOKUP($A7,'Annex 2 Designated EHV charges'!$A:$P,12,FALSE)=0,"",VLOOKUP($A7,'Annex 2 Designated EHV charges'!$A:$P,12,FALSE)),"") -> 2.74
A8: {=IFERROR(INDEX('Annex 2 Designated EHV charges'!$A$11:$A$58, MATCH(0, IF(ISBLANK('Annex 2 Designated EHV charges'!$A$11:$A$58),1, COUNTIF(A$4:$A7, 'Annex 2 Designated EHV charges'!$A$11:$A$58)), 0)),"")} -> BLMBGN | B8: =IF($A8="","",VLOOKUP($A8,'Annex 2 Designated EHV charges'!$A:$O,2,0)) -> 820 | C8: =IF($A8="","",VLOOKUP($A8,'Annex 2 Designated EHV charges'!$A:$O,3,0)) -> 1200061385700;1200061385710 | D8: =IF($A8="","",VLOOKUP($A8,'Annex 2 Designated EHV charges'!$A:$O,7,0)) -> BLMBGN | E8: =IFERROR(IF(VLOOKUP($A8,'Annex 2 Designated EHV charges'!$A:$P,9,FALSE)=0,"",VLOOKUP($A8,'Annex 2 Designated EHV charges'!$A:$P,9,FALSE)),"") -> 0.216 | F8: =IFERROR(IF(VLOOKUP($A8,'Annex 2 Designated EHV charges'!$A:$P,10,FALSE)=0,"",VLOOKUP($A8,'Annex 2 Designated EHV charges'!$A:$P,10,FALSE)),"") -> 11254.69 | G8: =IFERROR(IF(VLOOKUP($A8,'Annex 2 Designated EHV charges'!$A:$P,11,FALSE)=0,"",VLOOKUP($A8,'Annex 2 Designated EHV charges'!$A:$P,11,FALSE)),"") -> 2.59 | H8: =IFERROR(IF(VLOOKUP($A8,'Annex 2 Designated EHV charges'!$A:$P,12,FALSE)=0,"",VLOOKUP($A8,'Annex 2 Designated EHV charges'!$A:$P,12,FALSE)),"") -> 2.59
A9: {=IFERROR(INDEX('Annex 2 Designated EHV charges'!$A$11:$A$58, MATCH(0, IF(ISBLANK('Annex 2 Designated EHV charges'!$A$11:$A$58),1, COUNTIF(A$4:$A8, 'Annex 2 Designated EHV charges'!$A$11:$A$58)), 0)),"")} -> BLMBGS | B9: =IF($A9="","",VLOOKUP($A9,'Annex 2 Designated EHV charges'!$A:$O,2,0)) -> 821 | C9: =IF($A9="","",VLOOKUP($A9,'Annex 2 Designated EHV charges'!$A:$O,3,0)) -> 1200061385729;1200061385738 | D9: =IF($A9="","",VLOOKUP($A9,'Annex 2 Designated EHV charges'!$A:$O,7,0)) -> BLMBGS | E9: =IFERROR(IF(VLOOKUP($A9,'Annex 2 Designated EHV charges'!$A:$P,9,FALSE)=0,"",VLOOKUP($A9,'Annex 2 Designated EHV charges'!$A:$P,9,FALSE)),"") -> 0.215 | F9: =IFERROR(IF(VLOOKUP($A9,'Annex 2 Designated EHV charges'!$A:$P,10,FALSE)=0,"",VLOOKUP($A9,'Annex 2 Designated EHV charges'!$A:$P,10,FALSE)),"") -> 11254.69 | G9: =IFERROR(IF(VLOOKUP($A9,'Annex 2 Designated EHV charges'!$A:$P,11,FALSE)=0,"",VLOOKUP($A9,'Annex 2 Designated EHV charges'!$A:$P,11,FALSE)),"") -> 1.96 | H9: =IFERROR(IF(VLOOKUP($A9,'Annex 2 Designated EHV charges'!$A:$P,12,FALSE)=0,"",VLOOKUP($A9,'Annex 2 Designated EHV charges'!$A:$P,12,FALSE)),"") -> 1.96
A10: {=IFERROR(INDEX('Annex 2 Designated EHV charges'!$A$11:$A$58, MATCH(0, IF(ISBLANK('Annex 2 Designated EHV charges'!$A$11:$A$58),1, COUNTIF(A$4:$A9, 'Annex 2 Designated EHV charges'!$A$11:$A$58)), 0)),"")} -> BRDGTE | B10: =IF($A10="","",VLOOKUP($A10,'Annex 2 Designated EHV charges'!$A:$O,2,0)) -> 805 | C10: =IF($A10="","",VLOOKUP($A10,'Annex 2 Designated EHV charges'!$A:$O,3,0)) -> 1200061148014;1200061148023 | D10: =IF($A10="","",VLOOKUP($A10,'Annex 2 Designated EHV charges'!$A:$O,7,0)) -> BRDGTE | E10: =IFERROR(IF(VLOOKUP($A10,'Annex 2 Designated EHV charges'!$A:$P,9,FALSE)=0,"",VLOOKUP($A10,'Annex 2 Designated EHV charges'!$A:$P,9,FALSE)),"") -> 0.207 | F10: =IFERROR(IF(VLOOKUP($A10,'Annex 2 Designated EHV charges'!$A:$P,10,FALSE)=0,"",VLOOKUP($A10,'Annex 2 Designated EHV charges'!$A:$P,10,FALSE)),"") -> 11254.69 | G10: =IFERROR(IF(VLOOKUP($A10,'Annex 2 Designated EHV charges'!$A:$P,11,FALSE)=0,"",VLOOKUP($A10,'Annex 2 Designated EHV charges'!$A:$P,11,FALSE)),"") -> 3.34 | H10: =IFERROR(IF(VLOOKUP($A10,'Annex 2 Designated EHV charges'!$A:$P,12,FALSE)=0,"",VLOOKUP($A10,'Annex 2 Designated EHV charges'!$A:$P,12,FALSE)),"") -> 3.34
A11: {=IFERROR(INDEX('Annex 2 Designated EHV charges'!$A$11:$A$58, MATCH(0, IF(ISBLANK('Annex 2 Designated EHV charges'!$A$11:$A$58),1, COUNTIF(A$4:$A10, 'Annex 2 Designated EHV charges'!$A$11:$A$58)), 0)),"")} -> BRKFLD | B11: =IF($A11="","",VLOOKUP($A11,'Annex 2 Designated EHV charges'!$A:$O,2,0)) -> 829 | C11: =IF($A11="","",VLOOKUP($A11,'Annex 2 Designated EHV charges'!$A:$O,3,0)) -> 1200061148060;1200061148079 | D11: =IF($A11="","",VLOOKUP($A11,'Annex 2 Designated EHV charges'!$A:$O,7,0)) -> BRKFLD | E11: =IFERROR(IF(VLOOKUP($A11,'Annex 2 Designated EHV charges'!$A:$P,9,FALSE)=0,"",VLOOKUP($A11,'Annex 2 Designated EHV charges'!$A:$P,9,FALSE)),"") -> 0.22 | F11: =IFERROR(IF(VLOOKUP($A11,'Annex 2 Designated EHV charges'!$A:$P,10,FALSE)=0,"",VLOOKUP($A11,'Annex 2 Designated EHV charges'!$A:$P,10,FALSE)),"") -> 11254.69 | G11: =IFERROR(IF(VLOOKUP($A11,'Annex 2 Designated EHV charges'!$A:$P,11,FALSE)=0,"",VLOOKUP($A11,'Annex 2 Designated EHV charges'!$A:$P,11,FALSE)),"") -> 2.62 | H11: =IFERROR(IF(VLOOKUP($A11,'Annex 2 Designated EHV charges'!$A:$P,12,FALSE)=0,"",VLOOKUP($A11,'Annex 2 Designated EHV charges'!$A:$P,12,FALSE)),"") -> 2.62
A12: {=IFERROR(INDEX('Annex 2 Designated EHV charges'!$A$11:$A$58, MATCH(0, IF(ISBLANK('Annex 2 Designated EHV charges'!$A$11:$A$58),1, COUNTIF(A$4:$A11, 'Annex 2 Designated EHV charges'!$A$11:$A$58)), 0)),"")} -> BRMLEY | B12: =IF($A12="","",VLOOKUP($A12,'Annex 2 Designated EHV charges'!$A:$O,2,0)) -> 0 | C12: =IF($A12="","",VLOOKUP($A12,'Annex 2 Designated EHV charges'!$A:$O,3,0)) -> MSID: 1630 | D12: =IF($A12="","",VLOOKUP($A12,'Annex 2 Designated EHV charges'!$A:$O,7,0)) -> BRMLEY | E12: =IFERROR(IF(VLOOKUP($A12,'Annex 2 Designated EHV charges'!$A:$P,9,FALSE)=0,"",VLOOKUP($A12,'Annex 2 Designated EHV charges'!$A:$P,9,FALSE)),"") -> 0.212 | F12: =IFERROR(IF(VLOOKUP($A12,'Annex 2 Designated EHV charges'!$A:$P,10,FALSE)=0,"",VLOOKUP($A12,'Annex 2 Designated EHV charges'!$A:$P,10,FALSE)),"") -> 68626.32 | G12: =IFERROR(IF(VLOOKUP($A12,'Annex 2 Designated EHV charges'!$A:$P,11,FALSE)=0,"",VLOOKUP($A12,'Annex 2 Designated EHV charges'!$A:$P,11,FALSE)),"") -> 5.1 | H12: =IFERROR(IF(VLOOKUP($A12,'Annex 2 Designated EHV charges'!$A:$P,12,FALSE)=0,"",VLOOKUP($A12,'Annex 2 Designated EHV charges'!$A:$P,12,FALSE)),"") -> 5.1
A13: {=IFERROR(INDEX('Annex 2 Designated EHV charges'!$A$11:$A$58, MATCH(0, IF(ISBLANK('Annex 2 Designated EHV charges'!$A$11:$A$58),1, COUNTIF(A$4:$A12, 'Annex 2 Designated EHV charges'!$A$11:$A$58)), 0)),"")} -> CRLIMM | B13: =IF($A13="","",VLOOKUP($A13,'Annex 2 Designated EHV charges'!$A:$O,2,0)) -> 812 | C13: =IF($A13="","",VLOOKUP($A13,'Annex 2 Designated EHV charges'!$A:$O,3,0)) -> 1200062090483;1200062090492 | D13: =IF($A13="","",VLOOKUP($A13,'Annex 2 Designated EHV charges'!$A:$O,7,0)) -> CRLIMM | E13: =IFERROR(IF(VLOOKUP($A13,'Annex 2 Designated EHV charges'!$A:$P,9,FALSE)=0,"",VLOOKUP($A13,'Annex 2 Designated EHV charges'!$A:$P,9,FALSE)),"") -> 0.003 | F13: =IFERROR(IF(VLOOKUP($A13,'Annex 2 Designated EHV charges'!$A:$P,10,FALSE)=0,"",VLOOKUP($A13,'Annex 2 Designated EHV charges'!$A:$P,10,FALSE)),"") -> 82036.16 | G13: =IFERROR(IF(VLOOKUP($A13,'Annex 2 Designated EHV charges'!$A:$P,11,FALSE)=0,"",VLOOKUP($A13,'Annex 2 Designated EHV charges'!$A:$P,11,FALSE)),"") -> 1.5 | H13: =IFERROR(IF(VLOOKUP($A13,'Annex 2 Designated EHV charges'!$A:$P,12,FALSE)=0,"",VLOOKUP($A13,'Annex 2 Designated EHV charges'!$A:$P,12,FALSE)),"") -> 1.5
A14: {=IFERROR(INDEX('Annex 2 Designated EHV charges'!$A$11:$A$58, MATCH(0, IF(ISBLANK('Annex 2 Designated EHV charges'!$A$11:$A$58),1, COUNTIF(A$4:$A13, 'Annex 2 Designated EHV charges'!$A$11:$A$58)), 0)),"")} -> DART11 | B14: =IF($A14="","",VLOOKUP($A14,'Annex 2 Designated EHV charges'!$A:$O,2,0)) -> 0 | C14: =IF($A14="","",VLOOKUP($A14,'Annex 2 Designated EHV charges'!$A:$O,3,0)) -> MSID: 1032 | D14: =IF($A14="","",VLOOKUP($A14,'Annex 2 Designated EHV charges'!$A:$O,7,0)) -> DART11 | E14: =IFERROR(IF(VLOOKUP($A14,'Annex 2 Designated EHV charges'!$A:$P,9,FALSE)=0,"",VLOOKUP($A14,'Annex 2 Designated EHV charges'!$A:$P,9,FALSE)),"") -> 0.285 | F14: =IFERROR(IF(VLOOKUP($A14,'Annex 2 Designated EHV charges'!$A:$P,10,FALSE)=0,"",VLOOKUP($A14,'Annex 2 Designated EHV charges'!$A:$P,10,FALSE)),"") -> 10677.01 | G14: =IFERROR(IF(VLOOKUP($A14,'Annex 2 Designated EHV charges'!$A:$P,11,FALSE)=0,"",VLOOKUP($A14,'Annex 2 Designated EHV charges'!$A:$P,11,FALSE)),"") -> 6.51 | H14: =IFERROR(IF(VLOOKUP($A14,'Annex 2 Designated EHV charges'!$A:$P,12,FALSE)=0,"",VLOOKUP($A14,'Annex 2 Designated EHV charges'!$A:$P,12,FALSE)),"") -> 6.51
A15: {=IFERROR(INDEX('Annex 2 Designated EHV charges'!$A$11:$A$58, MATCH(0, IF(ISBLANK('Annex 2 Designated EHV charges'!$A$11:$A$58),1, COUNTIF(A$4:$A14, 'Annex 2 Designated EHV charges'!$A$11:$A$58)), 0)),"")} -> DART33 | B15: =IF($A15="","",VLOOKUP($A15,'Annex 2 Designated EHV charges'!$A:$O,2,0)) -> 0 | C15: =IF($A15="","",VLOOKUP($A15,'Annex 2 Designated EHV charges'!$A:$O,3,0)) -> MSID: 1032 | D15: =IF($A15="","",VLOOKUP($A15,'Annex 2 Designated EHV charges'!$A:$O,7,0)) -> DART33 | E15: =IFERROR(IF(VLOOKUP($A15,'Annex 2 Designated EHV charges'!$A:$P,9,FALSE)=0,"",VLOOKUP($A15,'Annex 2 Designated EHV charges'!$A:$P,9,FALSE)),"") -> 0.603 | F15: =IFERROR(IF(VLOOKUP($A15,'Annex 2 Designated EHV charges'!$A:$P,10,FALSE)=0,"",VLOOKUP($A15,'Annex 2 Designated EHV charges'!$A:$P,10,FALSE)),"") -> 28207.13 | G15: =IFERROR(IF(VLOOKUP($A15,'Annex 2 Designated EHV charges'!$A:$P,11,FALSE)=0,"",VLOOKUP($A15,'Annex 2 Designated EHV charges'!$A:$P,11,FALSE)),"") -> 7.02 | H15: =IFERROR(IF(VLOOKUP($A15,'Annex 2 Designated EHV charges'!$A:$P,12,FALSE)=0,"",VLOOKUP($A15,'Annex 2 Designated EHV charges'!$A:$P,12,FALSE)),"") -> 7.02
A16: {=IFERROR(INDEX('Annex 2 Designated EHV charges'!$A$11:$A$58, MATCH(0, IF(ISBLANK('Annex 2 Designated EHV charges'!$A$11:$A$58),1, COUNTIF(A$4:$A15, 'Annex 2 Designated EHV charges'!$A$11:$A$58)), 0)),"")} -> EPNLEI | B16: =IF($A16="","",VLOOKUP($A16,'Annex 2 Designated EHV charges'!$A:$O,2,0)) -> 0 | C16: =IF($A16="","",VLOOKUP($A16,'Annex 2 Designated EHV charges'!$A:$O,3,0)) -> MSID: 1628 | D16: =IF($A16="","",VLOOKUP($A16,'Annex 2 Designated EHV charges'!$A:$O,7,0)) -> EPNLEI | E16: =IFERROR(IF(VLOOKUP($A16,'Annex 2 Designated EHV charges'!$A:$P,9,FALSE)=0,"",VLOOKUP($A16,'Annex 2 Designated EHV charges'!$A:$P,9,FALSE)),"") -> 0.024 | F16: =IFERROR(IF(VLOOKUP($A16,'Annex 2 Designated EHV charges'!$A:$P,10,FALSE)=0,"",VLOOKUP($A16,'Annex 2 Designated EHV charges'!$A:$P,10,FALSE)),"") -> 68626.32 | G16: =IFERROR(IF(VLOOKUP($A16,'Annex 2 Designated EHV charges'!$A:$P,11,FALSE)=0,"",VLOOKUP($A16,'Annex 2 Designated EHV charges'!$A:$P,11,FALSE)),"") -> 5.2 | H16: =IFERROR(IF(VLOOKUP($A16,'Annex 2 Designated EHV charges'!$A:$P,12,FALSE)=0,"",VLOOKUP($A16,'Annex 2 Designated EHV charges'!$A:$P,12,FALSE)),"") -> 5.2
... A254: {=IFERROR(INDEX('Annex 2 Designated EHV charges'!$A$11:$A$58, MATCH(0, IF(ISBLANK('Annex 2 Designated EHV charges'!$A$11:$A$58),1, COUNTIF(A$4:$A253, 'Annex 2 Designated EHV charges'!$A$11:$A$58)), 0)),"")} | B254: =IF($A254="","",VLOOKUP($A254,'Annex 2 Designated EHV charges'!$A:$O,2,0)) | C254: =IF($A254="","",VLOOKUP($A254,'Annex 2 Designated EHV charges'!$A:$O,3,0)) | D254: =IF($A254="","",VLOOKUP($A254,'Annex 2 Designated EHV charges'!$A:$O,7,0)) | E254: =IFERROR(IF(VLOOKUP($A254,'Annex 2 Designated EHV charges'!$A:$P,9,FALSE)=0,"",VLOOKUP($A254,'Annex 2 Designated EHV charges'!$A:$P,9,FALSE)),"") | F254: =IFERROR(IF(VLOOKUP($A254,'Annex 2 Designated EHV charges'!$A:$P,10,FALSE)=0,"",VLOOKUP($A254,'Annex 2 Designated EHV charges'!$A:$P,10,FALSE)),"") | G254: =IFERROR(IF(VLOOKUP($A254,'Annex 2 Designated EHV charges'!$A:$P,11,FALSE)=0,"",VLOOKUP($A254,'Annex 2 Designated EHV charges'!$A:$P,11,FALSE)),"") | H254: =IFERROR(IF(VLOOKUP($A254,'Annex 2 Designated EHV charges'!$A:$P,12,FALSE)=0,"",VLOOKUP($A254,'Annex 2 Designated EHV charges'!$A:$P,12,FALSE)),"")

Sheet Annex 2b Export
A1: Note: The list of MPANs / MSIDs provided may be incomplete; the DNO reserves the right to apply the listed charges to any other MPANs / MSIDs associated with the site. Note: This table is automatically populated based on the content of the tab entitled 'Annex 2 Designated EHV charges'. The timebands are as shown in Annex 2.
A2: =Overview!B4& " - Effective from "&Overview!D4&" - "&Overview!E4&" Designated EHV export charges" -> London Power Networks - Effective from 1 April 2027 - Final Designated EHV export charges
A4: Export Unique Identifier | B4: LLFC/ DUoS Tariff ID | C4: Export MPANs/MSIDs | D4: Name | E4: ='Annex 2 Designated EHV charges'!M10 -> Export Super Red unit charge (p/kWh) | F4: ='Annex 2 Designated EHV charges'!N10 -> Export fixed charge (p/day) | G4: ='Annex 2 Designated EHV charges'!O10 -> Export capacity charge (p/kVA/day) | H4: ='Annex 2 Designated EHV charges'!P10 -> Export exceeded capacity charge (p/kVA/day)
A5: {=IFERROR(INDEX('Annex 2 Designated EHV charges'!$D$11:$D$58, MATCH(0, IF(ISBLANK('Annex 2 Designated EHV charges'!$D$11:$D$58),1, COUNTIF(A$4:$A4, 'Annex 2 Designated EHV charges'!$D$11:$D$58)), 0)),"")} -> NR_BOW | B5: =IF($A5="","",VLOOKUP($A5,'Annex 2 Designated EHV charges'!$D:$O,2,0)) -> 707 | C5: =IF($A5="","",VLOOKUP($A5,'Annex 2 Designated EHV charges'!$D:$O,3,0)) -> 1200060280430;1200060280459 | D5: =IF($A5="","",VLOOKUP($A5,'Annex 2 Designated EHV charges'!$D:$O,4,0)) -> NR_BOW | E5: =IFERROR(IF(VLOOKUP($A5,'Annex 2 Designated EHV charges'!$D:$P,10,FALSE)=0,"",VLOOKUP($A5,'Annex 2 Designated EHV charges'!$D:$P,10,FALSE)),"") | F5: =IFERROR(IF(VLOOKUP($A5,'Annex 2 Designated EHV charges'!$D:$P,11,FALSE)=0,"",VLOOKUP($A5,'Annex 2 Designated EHV charges'!$D:$P,11,FALSE)),"") | G5: =IFERROR(IF(VLOOKUP($A5,'Annex 2 Designated EHV charges'!$D:$P,12,FALSE)=0,"",VLOOKUP($A5,'Annex 2 Designated EHV charges'!$D:$P,12,FALSE)),"") | H5: =IFERROR(IF(VLOOKUP($A5,'Annex 2 Designated EHV charges'!$D:$P,13,FALSE)=0,"",VLOOKUP($A5,'Annex 2 Designated EHV charges'!$D:$P,13,FALSE)),"")
A6: {=IFERROR(INDEX('Annex 2 Designated EHV charges'!$D$11:$D$58, MATCH(0, IF(ISBLANK('Annex 2 Designated EHV charges'!$D$11:$D$58),1, COUNTIF(A$4:$A5, 'Annex 2 Designated EHV charges'!$D$11:$D$58)), 0)),"")} -> NR_W25 | B6: =IF($A6="","",VLOOKUP($A6,'Annex 2 Designated EHV charges'!$D:$O,2,0)) -> 703 | C6: =IF($A6="","",VLOOKUP($A6,'Annex 2 Designated EHV charges'!$D:$O,3,0)) -> 1200052486866 | D6: =IF($A6="","",VLOOKUP($A6,'Annex 2 Designated EHV charges'!$D:$O,4,0)) -> NR_W25 | E6: =IFERROR(IF(VLOOKUP($A6,'Annex 2 Designated EHV charges'!$D:$P,10,FALSE)=0,"",VLOOKUP($A6,'Annex 2 Designated EHV charges'!$D:$P,10,FALSE)),"") | F6: =IFERROR(IF(VLOOKUP($A6,'Annex 2 Designated EHV charges'!$D:$P,11,FALSE)=0,"",VLOOKUP($A6,'Annex 2 Designated EHV charges'!$D:$P,11,FALSE)),"") | G6: =IFERROR(IF(VLOOKUP($A6,'Annex 2 Designated EHV charges'!$D:$P,12,FALSE)=0,"",VLOOKUP($A6,'Annex 2 Designated EHV charges'!$D:$P,12,FALSE)),"") | H6: =IFERROR(IF(VLOOKUP($A6,'Annex 2 Designated EHV charges'!$D:$P,13,FALSE)=0,"",VLOOKUP($A6,'Annex 2 Designated EHV charges'!$D:$P,13,FALSE)),"")
A7: {=IFERROR(INDEX('Annex 2 Designated EHV charges'!$D$11:$D$58, MATCH(0, IF(ISBLANK('Annex 2 Designated EHV charges'!$D$11:$D$58),1, COUNTIF(A$4:$A6, 'Annex 2 Designated EHV charges'!$D$11:$D$58)), 0)),"")} -> NR_WES | B7: =IF($A7="","",VLOOKUP($A7,'Annex 2 Designated EHV charges'!$D:$O,2,0)) -> 716 | C7: =IF($A7="","",VLOOKUP($A7,'Annex 2 Designated EHV charges'!$D:$O,3,0)) -> 1200052486875 | D7: =IF($A7="","",VLOOKUP($A7,'Annex 2 Designated EHV charges'!$D:$O,4,0)) -> NR_WES | E7: =IFERROR(IF(VLOOKUP($A7,'Annex 2 Designated EHV charges'!$D:$P,10,FALSE)=0,"",VLOOKUP($A7,'Annex 2 Designated EHV charges'!$D:$P,10,FALSE)),"") | F7: =IFERROR(IF(VLOOKUP($A7,'Annex 2 Designated EHV charges'!$D:$P,11,FALSE)=0,"",VLOOKUP($A7,'Annex 2 Designated EHV charges'!$D:$P,11,FALSE)),"") -> 631.92 | G7: =IFERROR(IF(VLOOKUP($A7,'Annex 2 Designated EHV charges'!$D:$P,12,FALSE)=0,"",VLOOKUP($A7,'Annex 2 Designated EHV charges'!$D:$P,12,FALSE)),"") -> 0.05 | H7: =IFERROR(IF(VLOOKUP($A7,'Annex 2 Designated EHV charges'!$D:$P,13,FALSE)=0,"",VLOOKUP($A7,'Annex 2 Designated EHV charges'!$D:$P,13,FALSE)),"") -> 0.05
A8: {=IFERROR(INDEX('Annex 2 Designated EHV charges'!$D$11:$D$58, MATCH(0, IF(ISBLANK('Annex 2 Designated EHV charges'!$D$11:$D$58),1, COUNTIF(A$4:$A7, 'Annex 2 Designated EHV charges'!$D$11:$D$58)), 0)),"")} -> THAMEB | B8: =IF($A8="","",VLOOKUP($A8,'Annex 2 Designated EHV charges'!$D:$O,2,0)) -> 701 | C8: =IF($A8="","",VLOOKUP($A8,'Annex 2 Designated EHV charges'!$D:$O,3,0)) -> 1200050312030;1200050312040;1200061219394;1200050312059 | D8: =IF($A8="","",VLOOKUP($A8,'Annex 2 Designated EHV charges'!$D:$O,4,0)) -> THAMEB | E8: =IFERROR(IF(VLOOKUP($A8,'Annex 2 Designated EHV charges'!$D:$P,10,FALSE)=0,"",VLOOKUP($A8,'Annex 2 Designated EHV charges'!$D:$P,10,FALSE)),"") | F8: =IFERROR(IF(VLOOKUP($A8,'Annex 2 Designated EHV charges'!$D:$P,11,FALSE)=0,"",VLOOKUP($A8,'Annex 2 Designated EHV charges'!$D:$P,11,FALSE)),"") -> 1529.31 | G8: =IFERROR(IF(VLOOKUP($A8,'Annex 2 Designated EHV charges'!$D:$P,12,FALSE)=0,"",VLOOKUP($A8,'Annex 2 Designated EHV charges'!$D:$P,12,FALSE)),"") -> 0.05 | H8: =IFERROR(IF(VLOOKUP($A8,'Annex 2 Designated EHV charges'!$D:$P,13,FALSE)=0,"",VLOOKUP($A8,'Annex 2 Designated EHV charges'!$D:$P,13,FALSE)),"") -> 0.05
A9: {=IFERROR(INDEX('Annex 2 Designated EHV charges'!$D$11:$D$58, MATCH(0, IF(ISBLANK('Annex 2 Designated EHV charges'!$D$11:$D$58),1, COUNTIF(A$4:$A8, 'Annex 2 Designated EHV charges'!$D$11:$D$58)), 0)),"")} -> THAMEC | B9: =IF($A9="","",VLOOKUP($A9,'Annex 2 Designated EHV charges'!$D:$O,2,0)) -> 702 | C9: =IF($A9="","",VLOOKUP($A9,'Annex 2 Designated EHV charges'!$D:$O,3,0)) -> 1200061171342;1200061171351 | D9: =IF($A9="","",VLOOKUP($A9,'Annex 2 Designated EHV charges'!$D:$O,4,0)) -> THAMEC | E9: =IFERROR(IF(VLOOKUP($A9,'Annex 2 Designated EHV charges'!$D:$P,10,FALSE)=0,"",VLOOKUP($A9,'Annex 2 Designated EHV charges'!$D:$P,10,FALSE)),"") -> -0.002 | F9: =IFERROR(IF(VLOOKUP($A9,'Annex 2 Designated EHV charges'!$D:$P,11,FALSE)=0,"",VLOOKUP($A9,'Annex 2 Designated EHV charges'!$D:$P,11,FALSE)),"") -> 2358.99 | G9: =IFERROR(IF(VLOOKUP($A9,'Annex 2 Designated EHV charges'!$D:$P,12,FALSE)=0,"",VLOOKUP($A9,'Annex 2 Designated EHV charges'!$D:$P,12,FALSE)),"") -> 0.05 | H9: =IFERROR(IF(VLOOKUP($A9,'Annex 2 Designated EHV charges'!$D:$P,13,FALSE)=0,"",VLOOKUP($A9,'Annex 2 Designated EHV charges'!$D:$P,13,FALSE)),"") -> 0.05
A10: {=IFERROR(INDEX('Annex 2 Designated EHV charges'!$D$11:$D$58, MATCH(0, IF(ISBLANK('Annex 2 Designated EHV charges'!$D$11:$D$58),1, COUNTIF(A$4:$A9, 'Annex 2 Designated EHV charges'!$D$11:$D$58)), 0)),"")} -> BELVED | B10: =IF($A10="","",VLOOKUP($A10,'Annex 2 Designated EHV charges'!$D:$O,2,0)) -> 711 | C10: =IF($A10="","",VLOOKUP($A10,'Annex 2 Designated EHV charges'!$D:$O,3,0)) -> 1200060787118 | D10: =IF($A10="","",VLOOKUP($A10,'Annex 2 Designated EHV charges'!$D:$O,4,0)) -> BELVED | E10: =IFERROR(IF(VLOOKUP($A10,'Annex 2 Designated EHV charges'!$D:$P,10,FALSE)=0,"",VLOOKUP($A10,'Annex 2 Designated EHV charges'!$D:$P,10,FALSE)),"") | F10: =IFERROR(IF(VLOOKUP($A10,'Annex 2 Designated EHV charges'!$D:$P,11,FALSE)=0,"",VLOOKUP($A10,'Annex 2 Designated EHV charges'!$D:$P,11,FALSE)),"") -> 1033.4 | G10: =IFERROR(IF(VLOOKUP($A10,'Annex 2 Designated EHV charges'!$D:$P,12,FALSE)=0,"",VLOOKUP($A10,'Annex 2 Designated EHV charges'!$D:$P,12,FALSE)),"") -> 0.05 | H10: =IFERROR(IF(VLOOKUP($A10,'Annex 2 Designated EHV charges'!$D:$P,13,FALSE)=0,"",VLOOKUP($A10,'Annex 2 Designated EHV charges'!$D:$P,13,FALSE)),"") -> 0.05
A11: {=IFERROR(INDEX('Annex 2 Designated EHV charges'!$D$11:$D$58, MATCH(0, IF(ISBLANK('Annex 2 Designated EHV charges'!$D$11:$D$58),1, COUNTIF(A$4:$A10, 'Annex 2 Designated EHV charges'!$D$11:$D$58)), 0)),"")} -> SELCHP | B11: =IF($A11="","",VLOOKUP($A11,'Annex 2 Designated EHV charges'!$D:$O,2,0)) -> 730 | C11: =IF($A11="","",VLOOKUP($A11,'Annex 2 Designated EHV charges'!$D:$O,3,0)) -> 1200010258304 | D11: =IF($A11="","",VLOOKUP($A11,'Annex 2 Designated EHV charges'!$D:$O,4,0)) -> SELCHP | E11: =IFERROR(IF(VLOOKUP($A11,'Annex 2 Designated EHV charges'!$D:$P,10,FALSE)=0,"",VLOOKUP($A11,'Annex 2 Designated EHV charges'!$D:$P,10,FALSE)),"") -> -0.304 | F11: =IFERROR(IF(VLOOKUP($A11,'Annex 2 Designated EHV charges'!$D:$P,11,FALSE)=0,"",VLOOKUP($A11,'Annex 2 Designated EHV charges'!$D:$P,11,FALSE)),"") -> 5121.4 | G11: =IFERROR(IF(VLOOKUP($A11,'Annex 2 Designated EHV charges'!$D:$P,12,FALSE)=0,"",VLOOKUP($A11,'Annex 2 Designated EHV charges'!$D:$P,12,FALSE)),"") -> 0.05 | H11: =IFERROR(IF(VLOOKUP($A11,'Annex 2 Designated EHV charges'!$D:$P,13,FALSE)=0,"",VLOOKUP($A11,'Annex 2 Designated EHV charges'!$D:$P,13,FALSE)),"") -> 0.05
A12: {=IFERROR(INDEX('Annex 2 Designated EHV charges'!$D$11:$D$58, MATCH(0, IF(ISBLANK('Annex 2 Designated EHV charges'!$D$11:$D$58),1, COUNTIF(A$4:$A11, 'Annex 2 Designated EHV charges'!$D$11:$D$58)), 0)),"")} -> TLRSLN | B12: =IF($A12="","",VLOOKUP($A12,'Annex 2 Designated EHV charges'!$D:$O,2,0)) -> 0 | C12: =IF($A12="","",VLOOKUP($A12,'Annex 2 Designated EHV charges'!$D:$O,3,0)) -> MSID: 5538 | D12: =IF($A12="","",VLOOKUP($A12,'Annex 2 Designated EHV charges'!$D:$O,4,0)) -> TLRSLN | E12: =IFERROR(IF(VLOOKUP($A12,'Annex 2 Designated EHV charges'!$D:$P,10,FALSE)=0,"",VLOOKUP($A12,'Annex 2 Designated EHV charges'!$D:$P,10,FALSE)),"") -> -0.014 | F12: =IFERROR(IF(VLOOKUP($A12,'Annex 2 Designated EHV charges'!$D:$P,11,FALSE)=0,"",VLOOKUP($A12,'Annex 2 Designated EHV charges'!$D:$P,11,FALSE)),"") | G12: =IFERROR(IF(VLOOKUP($A12,'Annex 2 Designated EHV charges'!$D:$P,12,FALSE)=0,"",VLOOKUP($A12,'Annex 2 Designated EHV charges'!$D:$P,12,FALSE)),"") -> 0.05 | H12: =IFERROR(IF(VLOOKUP($A12,'Annex 2 Designated EHV charges'!$D:$P,13,FALSE)=0,"",VLOOKUP($A12,'Annex 2 Designated EHV charges'!$D:$P,13,FALSE)),"") -> 0.05
A13: {=IFERROR(INDEX('Annex 2 Designated EHV charges'!$D$11:$D$58, MATCH(0, IF(ISBLANK('Annex 2 Designated EHV charges'!$D$11:$D$58),1, COUNTIF(A$4:$A12, 'Annex 2 Designated EHV charges'!$D$11:$D$58)), 0)),"")} | B13: =IF($A13="","",VLOOKUP($A13,'Annex 2 Designated EHV charges'!$D:$O,2,0)) | C13: =IF($A13="","",VLOOKUP($A13,'Annex 2 Designated EHV charges'!$D:$O,3,0)) | D13: =IF($A13="","",VLOOKUP($A13,'Annex 2 Designated EHV charges'!$D:$O,4,0)) | E13: =IFERROR(IF(VLOOKUP($A13,'Annex 2 Designated EHV charges'!$D:$P,10,FALSE)=0,"",VLOOKUP($A13,'Annex 2 Designated EHV charges'!$D:$P,10,FALSE)),"") | F13: =IFERROR(IF(VLOOKUP($A13,'Annex 2 Designated EHV charges'!$D:$P,11,FALSE)=0,"",VLOOKUP($A13,'Annex 2 Designated EHV charges'!$D:$P,11,FALSE)),"") | G13: =IFERROR(IF(VLOOKUP($A13,'Annex 2 Designated EHV charges'!$D:$P,12,FALSE)=0,"",VLOOKUP($A13,'Annex 2 Designated EHV charges'!$D:$P,12,FALSE)),"") | H13: =IFERROR(IF(VLOOKUP($A13,'Annex 2 Designated EHV charges'!$D:$P,13,FALSE)=0,"",VLOOKUP($A13,'Annex 2 Designated EHV charges'!$D:$P,13,FALSE)),"")
A14: {=IFERROR(INDEX('Annex 2 Designated EHV charges'!$D$11:$D$58, MATCH(0, IF(ISBLANK('Annex 2 Designated EHV charges'!$D$11:$D$58),1, COUNTIF(A$4:$A13, 'Annex 2 Designated EHV charges'!$D$11:$D$58)), 0)),"")} | B14: =IF($A14="","",VLOOKUP($A14,'Annex 2 Designated EHV charges'!$D:$O,2,0)) | C14: =IF($A14="","",VLOOKUP($A14,'Annex 2 Designated EHV charges'!$D:$O,3,0)) | D14: =IF($A14="","",VLOOKUP($A14,'Annex 2 Designated EHV charges'!$D:$O,4,0)) | E14: =IFERROR(IF(VLOOKUP($A14,'Annex 2 Designated EHV charges'!$D:$P,10,FALSE)=0,"",VLOOKUP($A14,'Annex 2 Designated EHV charges'!$D:$P,10,FALSE)),"") | F14: =IFERROR(IF(VLOOKUP($A14,'Annex 2 Designated EHV charges'!$D:$P,11,FALSE)=0,"",VLOOKUP($A14,'Annex 2 Designated EHV charges'!$D:$P,11,FALSE)),"") | G14: =IFERROR(IF(VLOOKUP($A14,'Annex 2 Designated EHV charges'!$D:$P,12,FALSE)=0,"",VLOOKUP($A14,'Annex 2 Designated EHV charges'!$D:$P,12,FALSE)),"") | H14: =IFERROR(IF(VLOOKUP($A14,'Annex 2 Designated EHV charges'!$D:$P,13,FALSE)=0,"",VLOOKUP($A14,'Annex 2 Designated EHV charges'!$D:$P,13,FALSE)),"")
A15: {=IFERROR(INDEX('Annex 2 Designated EHV charges'!$D$11:$D$58, MATCH(0, IF(ISBLANK('Annex 2 Designated EHV charges'!$D$11:$D$58),1, COUNTIF(A$4:$A14, 'Annex 2 Designated EHV charges'!$D$11:$D$58)), 0)),"")} | B15: =IF($A15="","",VLOOKUP($A15,'Annex 2 Designated EHV charges'!$D:$O,2,0)) | C15: =IF($A15="","",VLOOKUP($A15,'Annex 2 Designated EHV charges'!$D:$O,3,0)) | D15: =IF($A15="","",VLOOKUP($A15,'Annex 2 Designated EHV charges'!$D:$O,4,0)) | E15: =IFERROR(IF(VLOOKUP($A15,'Annex 2 Designated EHV charges'!$D:$P,10,FALSE)=0,"",VLOOKUP($A15,'Annex 2 Designated EHV charges'!$D:$P,10,FALSE)),"") | F15: =IFERROR(IF(VLOOKUP($A15,'Annex 2 Designated EHV charges'!$D:$P,11,FALSE)=0,"",VLOOKUP($A15,'Annex 2 Designated EHV charges'!$D:$P,11,FALSE)),"") | G15: =IFERROR(IF(VLOOKUP($A15,'Annex 2 Designated EHV charges'!$D:$P,12,FALSE)=0,"",VLOOKUP($A15,'Annex 2 Designated EHV charges'!$D:$P,12,FALSE)),"") | H15: =IFERROR(IF(VLOOKUP($A15,'Annex 2 Designated EHV charges'!$D:$P,13,FALSE)=0,"",VLOOKUP($A15,'Annex 2 Designated EHV charges'!$D:$P,13,FALSE)),"")
A16: {=IFERROR(INDEX('Annex 2 Designated EHV charges'!$D$11:$D$58, MATCH(0, IF(ISBLANK('Annex 2 Designated EHV charges'!$D$11:$D$58),1, COUNTIF(A$4:$A15, 'Annex 2 Designated EHV charges'!$D$11:$D$58)), 0)),"")} | B16: =IF($A16="","",VLOOKUP($A16,'Annex 2 Designated EHV charges'!$D:$O,2,0)) | C16: =IF($A16="","",VLOOKUP($A16,'Annex 2 Designated EHV charges'!$D:$O,3,0)) | D16: =IF($A16="","",VLOOKUP($A16,'Annex 2 Designated EHV charges'!$D:$O,4,0)) | E16: =IFERROR(IF(VLOOKUP($A16,'Annex 2 Designated EHV charges'!$D:$P,10,FALSE)=0,"",VLOOKUP($A16,'Annex 2 Designated EHV charges'!$D:$P,10,FALSE)),"") | F16: =IFERROR(IF(VLOOKUP($A16,'Annex 2 Designated EHV charges'!$D:$P,11,FALSE)=0,"",VLOOKUP($A16,'Annex 2 Designated EHV charges'!$D:$P,11,FALSE)),"") | G16: =IFERROR(IF(VLOOKUP($A16,'Annex 2 Designated EHV charges'!$D:$P,12,FALSE)=0,"",VLOOKUP($A16,'Annex 2 Designated EHV charges'!$D:$P,12,FALSE)),"") | H16: =IFERROR(IF(VLOOKUP($A16,'Annex 2 Designated EHV charges'!$D:$P,13,FALSE)=0,"",VLOOKUP($A16,'Annex 2 Designated EHV charges'!$D:$P,13,FALSE)),"")
... A254: {=IFERROR(INDEX('Annex 2 Designated EHV charges'!$D$11:$D$58, MATCH(0, IF(ISBLANK('Annex 2 Designated EHV charges'!$D$11:$D$58),1, COUNTIF(A$4:$A253, 'Annex 2 Designated EHV charges'!$D$11:$D$58)), 0)),"")} | B254: =IF($A254="","",VLOOKUP($A254,'Annex 2 Designated EHV charges'!$D:$O,2,0)) | C254: =IF($A254="","",VLOOKUP($A254,'Annex 2 Designated EHV charges'!$D:$O,3,0)) | D254: =IF($A254="","",VLOOKUP($A254,'Annex 2 Designated EHV charges'!$D:$O,4,0)) | E254: =IFERROR(IF(VLOOKUP($A254,'Annex 2 Designated EHV charges'!$D:$P,10,FALSE)=0,"",VLOOKUP($A254,'Annex 2 Designated EHV charges'!$D:$P,10,FALSE)),"") | F254: =IFERROR(IF(VLOOKUP($A254,'Annex 2 Designated EHV charges'!$D:$P,11,FALSE)=0,"",VLOOKUP($A254,'Annex 2 Designated EHV charges'!$D:$P,11,FALSE)),"") | G254: =IFERROR(IF(VLOOKUP($A254,'Annex 2 Designated EHV charges'!$D:$P,12,FALSE)=0,"",VLOOKUP($A254,'Annex 2 Designated EHV charges'!$D:$P,12,FALSE)),"") | H254: =IFERROR(IF(VLOOKUP($A254,'Annex 2 Designated EHV charges'!$D:$P,13,FALSE)=0,"",VLOOKUP($A254,'Annex 2 Designated EHV charges'!$D:$P,13,FALSE)),"")

Sheet Annex 3 Preserved charges
A1: Back to Overview
A2: =Overview!B4& " - Effective from "&Overview!D4&" - "&Overview!E4&" LV and HV tariffs" -> London Power Networks - Effective from 1 April 2027 - Final LV and HV tariffs
A4: Supercustomer preserved charges/additional LLFCs/ DUoS Tariff IDs
B5: Closed LLFCs/ DUoS Tariff IDs | C5: PCs | D5: Red/black unit charge p/kWh | E5: Amber/yellow unit charge p/kWh | F5: Green unit charge p/kWh | G5: Fixed charge p/MPAN/day
A7: Notes: | B7: London Power Networks has no Preserved NHH Tariffs/Additional LLFCs/DUoS Tariff IDs
A12: Site Specific preserved charges/additional LLFCs/ DUoS Tariff IDs
B13: Closed LLFCs/ DUoS Tariff IDs | C13: PCs | D13: Red/black unit charge p/kWh | E13: Amber/yellow unit charge p/kWh | F13: Green unit charge p/kWh | G13: Fixed charge p/MPAN/day | H13: Capacity charge p/kVA/day | I13: Exceeded capacity charge p/kVA/day | J13: Reactive power charge p/kVArh
A15: Notes: | B15: London Power Networks has no Preserved HH Tariffs/Additional LLFCs/DUoS Tariff IDs

Sheet Annex 4 LDNO charges
A1: Back to Overview
A2: =Overview!B4& " - Effective from "&Overview!D4&" - "&Overview!E4&" LDNO tariffs" -> London Power Networks - Effective from 1 April 2027 - Final LDNO tariffs
A4: Time Bands for LV and HV Designated Properties | F4: Time Bands for Unmetered Properties
A5: Time periods | B5: Red Time Band | C5: Amber Time Band | D5: Green Time Band | H5: Black Time Band | I5: Yellow Time Band | J5: Green Time Band
A6: Monday to Friday (Including Bank Holidays) All Year | B6: 11:00 - 14:00 16:00 - 19:00 | C6: 07:00 - 11:00 14:00 - 16:00 19:00 - 23:00 | D6: 00:00 - 07:00 23:00 - 24:00 | F6: Monday to Friday (Including Bank Holidays) June to August Inclusive | H6: 11:00 - 14:00 | I6: 07:00 - 11:00 14:00 - 23:00 | J6: 00:00 - 07:00 23:00 - 24:00
A7: Saturday and Sunday All Year | D7: 00:00 - 24:00 | F7: Monday to Friday (Including Bank Holidays) November to February Inclusive | H7: 16:00 - 19:00 | I7: 07:00 - 16:00 19:00 - 23:00 | J7: 00:00 - 07:00 23:00 - 24:00
A8: Notes | B8: All the above times are in UK Clock time | F8: Monday to Friday (Including Bank Holidays) March, April, May and September, October | I8: 07:00 - 23:00 | J8: 00:00 - 07:00 23:00 - 24:00
F9: Saturday and Sunday All year | J9: 00:00 - 24:00
F10: Notes | H10: All the above times are in UK Clock time
A13: Tariff name | B13: Unique billing identifier | C13: PCs | D13: Red/black unit charge p/kWh | E13: Amber/yellow unit charge p/kWh | F13: Green unit charge p/kWh | G13: Fixed charge p/MPAN/day | H13: Capacity charge p/kVA/day | I13: Exceeded capacity charge p/kVA/day | J13: Reactive power charge p/kVArh
A14: LDNO LV: Domestic Aggregated or CT with Residual | B14: A00 | C14: 0, 1, 2 | D14: 8.454 | E14: 0.861 | F14: 0 | G14: 0
A15: LDNO LV: Domestic Aggregated (Related MPAN) | B15: B00 | C15: 2 | D15: 8.604 | E15: 1.012 | F15: 0.075
A16: LDNO LV: Non-Domestic Aggregated or CT No Residual | B16: C00 | C16: 0, 3, 4, 5-8 | D16: 6.661 | E16: 0.784 | F16: 0.058 | G16: 4.1
A17: LDNO LV: Non-Domestic Aggregated or CT Band 1 | B17: C01 | C17: 0, 3, 4, 5-8 | D17: 6.578 | E17: 0.7 | F17: 0 | G17: 0
A18: LDNO LV: Non-Domestic Aggregated or CT Band 2 | B18: C02 | C18: 0, 3, 4, 5-8 | D18: 5.991 | E18: 0.114 | F18: 0 | G18: 0
A19: LDNO LV: Non-Domestic Aggregated or CT Band 3 | B19: C03 | C19: 0, 3, 4, 5-8 | D19: 5.776 | E19: 0 | F19: 0 | G19: 0
A20: LDNO LV: Non-Domestic Aggregated or CT Band 4 | B20: C04 | C20: 0, 3, 4, 5-8 | D20: 5.498 | E20: 0 | F20: 0 | G20: 0
A21: LDNO LV: Non-Domestic Aggregated (Related MPAN) | B21: D00 | C21: 4 | D21: 6.661 | E21: 0.784 | F21: 0.058
A22: LDNO LV: LV Site Specific No Residual | B22: E00 | C22: 0 | D22: 5.295 | E22: 0.639 | F22: 0.043 | G22: 10.05 | H22: 5.73 | I22: 5.73 | J22: 0.407
A23: LDNO LV: LV Site Specific Band 1 | B23: E01 | C23: 0 | D23: 3.387 | E23: 0.223 | F23: 0.021 | G23: 1.59 | H23: 5.73 | I23: 5.73 | J23: 0.407
A24: LDNO LV: LV Site Specific Band 2 | B24: E02 | C24: 0 | D24: 3.342 | E24: 0.223 | F24: 0.021 | G24: 1.59 | H24: 5.73 | I24: 5.73 | J24: 0.407
A25: LDNO LV: LV Site Specific Band 3 | B25: E03 | C25: 0 | D25: 3.301 | E25: 0.223 | F25: 0.021 | G25: 1.59 | H25: 5.73 | I25: 5.73 | J25: 0.407
A26: LDNO LV: LV Site Specific Band 4 | B26: E04 | C26: 0 | D26: 3.252 | E26: 0.223 | F26: 0.021 | G26: 1.59 | H26: 5.73 | I26: 5.73 | J26: 0.407
A27: LDNO LV: Unmetered Supplies | B27: U00 | C27: 0, 1 or 8 | D27: 28.398 | E27: 2.319 | F27: 0.326
A28: LDNO LV: LV Generation Aggregated | B28: F00 | C28: 0, 8 | D28: -7.828 | E28: -0.921 | F28: -0.068 | G28: 0
A29: LDNO LV: LV Generation Site Specific | B29: G00 | C29: 0 | D29: -7.828 | E29: -0.921 | F29: -0.068 | G29: 0 | J29: 0.55
A30: LDNO HV: Domestic Aggregated or CT with Residual | B30: A10 | C30: 0, 1, 2 | D30: 6.533 | E30: 0.666 | F30: 0 | G30: 0
A31: LDNO HV: Domestic Aggregated (Related MPAN) | B31: B10 | C31: 2 | D31: 6.65 | E31: 0.782 | F31: 0.058
A32: LDNO HV: Non-Domestic Aggregated or CT No Residual | B32: C10 | C32: 0, 3, 4, 5-8 | D32: 5.148 | E32: 0.606 | F32: 0.045 | G32: 3.17
A33: LDNO HV: Non-Domestic Aggregated or CT Band 1 | B33: C11 | C33: 0, 3, 4, 5-8 | D33: 5.084 | E33: 0.541 | F33: 0 | G33: 0
A34: LDNO HV: Non-Domestic Aggregated or CT Band 2 | B34: C12 | C34: 0, 3, 4, 5-8 | D34: 4.63 | E34: 0.088 | F34: 0 | G34: 0
A35: LDNO HV: Non-Domestic Aggregated or CT Band 3 | B35: C13 | C35: 0, 3, 4, 5-8 | D35: 4.464 | E35: 0 | F35: 0 | G35: 0
A36: LDNO HV: Non-Domestic Aggregated or CT Band 4 | B36: C14 | C36: 0, 3, 4, 5-8 | D36: 4.249 | E36: 0 | F36: 0 | G36: 0
A37: LDNO HV: Non-Domestic Aggregated (Related MPAN) | B37: D10 | C37: 4 | D37: 5.148 | E37: 0.606 | F37: 0.045
A38: LDNO HV: LV Site Specific No Residual | B38: E10 | C38: 0 | D38: 4.092 | E38: 0.494 | F38: 0.033 | G38: 7.77 | H38: 4.43 | I38: 4.43 | J38: 0.315
A39: LDNO HV: LV Site Specific Band 1 | B39: E11 | C39: 0 | D39: 2.617 | E39: 0.173 | F39: 0.016 | G39: 1.23 | H39: 4.43 | I39: 4.43 | J39: 0.315
A40: LDNO HV: LV Site Specific Band 2 | B40: E12 | C40: 0 | D40: 2.583 | E40: 0.173 | F40: 0.016 | G40: 1.23 | H40: 4.43 | I40: 4.43 | J40: 0.315
A41: LDNO HV: LV Site Specific Band 3 | B41: E13 | C41: 0 | D41: 2.551 | E41: 0.173 | F41: 0.016 | G41: 1.23 | H41: 4.43 | I41: 4.43 | J41: 0.315
A42: LDNO HV: LV Site Specific Band 4 | B42: E14 | C42: 0 | D42: 2.513 | E42: 0.173 | F42: 0.016 | G42: 1.23 | H42: 4.43 | I42: 4.43 | J42: 0.315
A43: LDNO HV: LV Sub Site Specific No Residual | B43: J10 | C43: 0 | D43: 3.668 | E43: 0.469 | F43: 0.025 | G43: 9.55 | H43: 8.12 | I43: 8.12 | J43: 0.272
A44: LDNO HV: LV Sub Site Specific Band 1 | B44: J11 | C44: 0 | D44: 1.515 | E44: 0 | F44: 0 | G44: 0 | H44: 8.12 | I44: 8.12 | J44: 0.272
A45: LDNO HV: LV Sub Site Specific Band 2 | B45: J12 | C45: 0 | D45: 1.465 | E45: 0 | F45: 0 | G45: 0 | H45: 8.12 | I45: 8.12 | J45: 0.272
A46: LDNO HV: LV Sub Site Specific Band 3 | B46: J13 | C46: 0 | D46: 1.419 | E46: 0 | F46: 0 | G46: 0 | H46: 8.12 | I46: 8.12 | J46: 0.272
A47: LDNO HV: LV Sub Site Specific Band 4 | B47: J14 | C47: 0 | D47: 1.363 | E47: 0 | F47: 0 | G47: 0 | H47: 8.12 | I47: 8.12 | J47: 0.272
A48: LDNO HV: HV Site Specific No Residual | B48: K10 | C48: 0 | D48: 3.031 | E48: 0.387 | F48: 0.022 | G48: 112.49 | H48: 9.25 | I48: 9.25 | J48: 0.236
A49: LDNO HV: HV Site Specific Band 1 | B49: K11 | C49: 0 | D49: 0.365 | E49: 0 | F49: 0 | G49: 0 | H49: 9.25 | I49: 9.25 | J49: 0.236
... A52: LDNO HV: HV Site Specific Band 4 | B52: K14 | C52: 0 | D52: 0.209 | E52: 0 | F52: 0 | G52: 0 | H52: 9.25 | I52: 9.25 | J52: 0.236
A53: LDNO HV: Unmetered Supplies | B53: U10 | C53: 0, 1 or 8 | D53: 21.946 | E53: 1.793 | F53: 0.252
A54: LDNO HV: LV Generation Aggregated | B54: F10 | C54: 0, 8 | D54: -7.828 | E54: -0.921 | F54: -0.068 | G54: 0
A55: LDNO HV: LV Sub Generation Aggregated | B55: H10 | C55: 0 | D55: -6.433 | E55: -0.769 | F55: -0.054 | G55: 0
A56: LDNO HV: LV Generation Site Specific | B56: G10 | C56: 0 | D56: -7.828 | E56: -0.921 | F56: -0.068 | G56: 0 | J56: 0.55
A57: LDNO HV: LV Sub Generation Site Specific | B57: L10 | C57: 0 | D57: -6.433 | E57: -0.769 | F57: -0.054 | G57: 0 | J57: 0.433
A58: LDNO HV: HV Generation Site Specific | B58: M10 | C58: 0 | D58: -4.179 | E58: -0.534 | F58: -0.029 | G58: 0 | J58: 0.382
A59: LDNO HVplus: Domestic Aggregated or CT with Residual | B59: A20 | C59: 0, 1, 2 | D59: 5.826 | E59: 0.594 | F59: 0 | G59: 0
A60: LDNO HVplus: Domestic Aggregated (Related MPAN) | B60: B20 | C60: 2 | D60: 5.93 | E60: 0.698 | F60: 0.051
A61: LDNO HVplus: Non-Domestic Aggregated or CT No Residual | B61: C20 | C61: 0, 3, 4, 5-8 | D61: 4.591 | E61: 0.54 | F61: 0.04 | G61: 2.82
A62: LDNO HVplus: Non-Domestic Aggregated or CT Band 1 | B62: C21 | C62: 0, 3, 4, 5-8 | D62: 4.533 | E62: 0.483 | F62: 0 | G62: 0
A63: LDNO HVplus: Non-Domestic Aggregated or CT Band 2 | B63: C22 | C63: 0, 3, 4, 5-8 | D63: 4.129 | E63: 0.078 | F63: 0 | G63: 0
A64: LDNO HVplus: Non-Domestic Aggregated or CT Band 3 | B64: C23 | C64: 0, 3, 4, 5-8 | D64: 3.981 | E64: 0 | F64: 0 | G64: 0
A65: LDNO HVplus: Non-Domestic Aggregated or CT Band 4 | B65: C24 | C65: 0, 3, 4, 5-8 | D65: 3.789 | E65: 0 | F65: 0 | G65: 0
A66: LDNO HVplus: Non-Domestic Aggregated (Related MPAN) | B66: D20 | C66: 4 | D66: 4.591 | E66: 0.54 | F66: 0.04
A67: LDNO HVplus: LV Site Specific No Residual | B67: E20 | C67: 0 | D67: 3.649 | E67: 0.44 | F67: 0.03 | G67: 6.93 | H67: 3.95 | I67: 3.95 | J67: 0.281
A68: LDNO HVplus: LV Site Specific Band 1 | B68: E21 | C68: 0 | D68: 2.334 | E68: 0.154 | F68: 0.014 | G68: 1.1 | H68: 3.95 | I68: 3.95 | J68: 0.281
A69: LDNO HVplus: LV Site Specific Band 2 | B69: E22 | C69: 0 | D69: 2.303 | E69: 0.154 | F69: 0.014 | G69: 1.1 | H69: 3.95 | I69: 3.95 | J69: 0.281
A70: LDNO HVplus: LV Site Specific Band 3 | B70: E23 | C70: 0 | D70: 2.275 | E70: 0.154 | F70: 0.014 | G70: 1.1 | H70: 3.95 | I70: 3.95 | J70: 0.281
A71: LDNO HVplus: LV Site Specific Band 4 | B71: E24 | C71: 0 | D71: 2.241 | E71: 0.154 | F71: 0.014 | G71: 1.1 | H71: 3.95 | I71: 3.95 | J71: 0.281
A72: LDNO HVplus: LV Sub Site Specific No Residual | B72: J20 | C72: 0 | D72: 3.244 | E72: 0.414 | F72: 0.023 | G72: 8.44 | H72: 7.18 | I72: 7.18 | J72: 0.241
A73: LDNO HVplus: LV Sub Site Specific Band 1 | B73: J21 | C73: 0 | D73: 1.34 | E73: 0 | F73: 0 | G73: 0 | H73: 7.18 | I73: 7.18 | J73: 0.241
A74: LDNO HVplus: LV Sub Site Specific Band 2 | B74: J22 | C74: 0 | D74: 1.295 | E74: 0 | F74: 0 | G74: 0 | H74: 7.18 | I74: 7.18 | J74: 0.241
A75: LDNO HVplus: LV Sub Site Specific Band 3 | B75: J23 | C75: 0 | D75: 1.255 | E75: 0 | F75: 0 | G75: 0 | H75: 7.18 | I75: 7.18 | J75: 0.241
A76: LDNO HVplus: LV Sub Site Specific Band 4 | B76: J24 | C76: 0 | D76: 1.205 | E76: 0 | F76: 0 | G76: 0 | H76: 7.18 | I76: 7.18 | J76: 0.241
A77: LDNO HVplus: HV Site Specific No Residual | B77: K20 | C77: 0 | D77: 2.668 | E77: 0.341 | F77: 0.02 | G77: 99 | H77: 8.14 | I77: 8.14 | J77: 0.208
A78: LDNO HVplus: HV Site Specific Band 1 | B78: K21 | C78: 0 | D78: 0.322 | E78: 0 | F78: 0 | G78: 0 | H78: 8.14 | I78: 8.14 | J78: 0.208
... A81: LDNO HVplus: HV Site Specific Band 4 | B81: K24 | C81: 0 | D81: 0.184 | E81: 0 | F81: 0 | G81: 0 | H81: 8.14 | I81: 8.14 | J81: 0.208
A82: LDNO HVplus: Unmetered Supplies | B82: U20 | C82: 0, 1 or 8 | D82: 19.571 | E82: 1.599 | F82: 0.225
A83: LDNO HVplus: LV Generation Aggregated | B83: F20 | C83: 0, 8 | D83: -5.414 | E83: -0.637 | F83: -0.047 | G83: 0
A84: LDNO HVplus: LV Sub Generation Aggregated | B84: H20 | C84: 0 | D84: -4.921 | E84: -0.588 | F84: -0.041 | G84: 0
A85: LDNO HVplus: LV Generation Site Specific | B85: G20 | C85: 0 | D85: -5.414 | E85: -0.637 | F85: -0.047 | G85: 0 | J85: 0.38
A86: LDNO HVplus: LV Sub Generation Site Specific | B86: L20 | C86: 0 | D86: -4.921 | E86: -0.588 | F86: -0.041 | G86: 0 | J86: 0.331
A87: LDNO HVplus: HV Generation Site Specific | B87: M20 | C87: 0 | D87: -4.179 | E87: -0.534 | F87: -0.029 | G87: 9.08 | J87: 0.382
A88: LDNO EHV: Domestic Aggregated or CT with Residual | B88: A30 | C88: 0, 1, 2 | D88: 4.473 | E88: 0.456 | F88: 0 | G88: 0
A89: LDNO EHV: Domestic Aggregated (Related MPAN) | B89: B30 | C89: 2 | D89: 4.552 | E89: 0.535 | F89: 0.04
A90: LDNO EHV: Non-Domestic Aggregated or CT No Residual | B90: C30 | C90: 0, 3, 4, 5-8 | D90: 3.524 | E90: 0.415 | F90: 0.031 | G90: 2.17
A91: LDNO EHV: Non-Domestic Aggregated or CT Band 1 | B91: C31 | C91: 0, 3, 4, 5-8 | D91: 3.48 | E91: 0.371 | F91: 0 | G91: 0
A92: LDNO EHV: Non-Domestic Aggregated or CT Band 2 | B92: C32 | C92: 0, 3, 4, 5-8 | D92: 3.17 | E92: 0.06 | F92: 0 | G92: 0
A93: LDNO EHV: Non-Domestic Aggregated or CT Band 3 | B93: C33 | C93: 0, 3, 4, 5-8 | D93: 3.056 | E93: 0 | F93: 0 | G93: 0
A94: LDNO EHV: Non-Domestic Aggregated or CT Band 4 | B94: C34 | C94: 0, 3, 4, 5-8 | D94: 2.909 | E94: 0 | F94: 0 | G94: 0
A95: LDNO EHV: Non-Domestic Aggregated (Related MPAN) | B95: D30 | C95: 4 | D95: 3.524 | E95: 0.415 | F95: 0.031
A96: LDNO EHV: LV Site Specific No Residual | B96: E30 | C96: 0 | D96: 2.801 | E96: 0.338 | F96: 0.023 | G96: 5.32 | H96: 3.03 | I96: 3.03 | J96: 0.215
A97: LDNO EHV: LV Site Specific Band 1 | B97: E31 | C97: 0 | D97: 1.792 | E97: 0.118 | F97: 0.011 | G97: 0.84 | H97: 3.03 | I97: 3.03 | J97: 0.215
A98: LDNO EHV: LV Site Specific Band 2 | B98: E32 | C98: 0 | D98: 1.768 | E98: 0.118 | F98: 0.011 | G98: 0.84 | H98: 3.03 | I98: 3.03 | J98: 0.215
A99: LDNO EHV: LV Site Specific Band 3 | B99: E33 | C99: 0 | D99: 1.747 | E99: 0.118 | F99: 0.011 | G99: 0.84 | H99: 3.03 | I99: 3.03 | J99: 0.215
A100: LDNO EHV: LV Site Specific Band 4 | B100: E34 | C100: 0 | D100: 1.72 | E100: 0.118 | F100: 0.011 | G100: 0.84 | H100: 3.03 | I100: 3.03 | J100: 0.215
A101: LDNO EHV: LV Sub Site Specific No Residual | B101: J30 | C101: 0 | D101: 2.49 | E101: 0.318 | F101: 0.017 | G101: 6.48 | H101: 5.51 | I101: 5.51 | J101: 0.185
A102: LDNO EHV: LV Sub Site Specific Band 1 | B102: J31 | C102: 0 | D102: 1.029 | E102: 0 | F102: 0 | G102: 0 | H102: 5.51 | I102: 5.51 | J102: 0.185
A103: LDNO EHV: LV Sub Site Specific Band 2 | B103: J32 | C103: 0 | D103: 0.994 | E103: 0 | F103: 0 | G103: 0 | H103: 5.51 | I103: 5.51 | J103: 0.185
A104: LDNO EHV: LV Sub Site Specific Band 3 | B104: J33 | C104: 0 | D104: 0.964 | E104: 0 | F104: 0 | G104: 0 | H104: 5.51 | I104: 5.51 | J104: 0.185
A105: LDNO EHV: LV Sub Site Specific Band 4 | B105: J34 | C105: 0 | D105: 0.925 | E105: 0 | F105: 0 | G105: 0 | H105: 5.51 | I105: 5.51 | J105: 0.185
A106: LDNO EHV: HV Site Specific No Residual | B106: K30 | C106: 0 | D106: 2.048 | E106: 0.262 | F106: 0.015 | G106: 76 | H106: 6.25 | I106: 6.25 | J106: 0.159
A107: LDNO EHV: HV Site Specific Band 1 | B107: K31 | C107: 0 | D107: 0.247 | E107: 0 | F107: 0 | G107: 0 | H107: 6.25 | I107: 6.25 | J107: 0.159
...

Sheet Annex 5 LLFs
A1: Back to Overview
A2: This table has intentionally been left blank. The line loss factors that are approved by the BSC Panel for the applicable year and consequently published on the Elexon website will take precedence and be used in Settlement. This annex will be re-published once these values are available.
A3: =Overview!B4& " - Illustrative LLFs for year beginning "&Overview!D4 -> London Power Networks - Illustrative LLFs for year beginning 1 April 2027
A5: Time periods | C5: Period 1 | D5: Period 2 | E5: Period 3 | F5: Period 4 | G5: Period 5
C6: Winter Peak | D6: Summer Peak | E6: Winter Shoulder | F6: Night | G6: Other
A7: Monday to Friday November to February | C7: 16:00 - 20:00 | E7: 07:00 - 16:00
A8: Monday to Friday June to August | D8: 07:00 - 20:00
A9: Monday to Friday March | E9: 07:00 - 20:00
A10: All Year | F10: 00:00 - 07:00 | G10: All Other Times
A11: Notes | C11: All the above times are in UK Clock time
A13: Generic demand and generation LLFs
A14: Metered voltage, respective periods and associated LLFCs/DUoS Tariff IDs
A15: Metered voltage | B15: Period 1 | C15: Period 2 | D15: Period 3 | E15: Period 4 | F15: Period 5 | G15: Associated LLFC/DUoS Tariff ID
A16: Low-voltage network
A17: Low-voltage substation
A18: High-voltage network
A19: High-voltage substation
A20: 33kV generic
A21: 132kV generic
A23: EHV site specific LLFs
A24: Demand
A25: Site | B25: Period 1 | C25: Period 2 | D25: Period 3 | E25: Period 4 | F25: Period 5 | G25: Associated LLFC/DUoS Tariff ID
A26: Site 1
A27: Site 2
A28: Site 3
A29: Site 4
A30: Site 5
A32: EHV site specific LLFs
A33: Generation
A34: Site | B34: Period 1 | C34: Period 2 | D34: Period 3 | E34: Period 4 | F34: Period 5 | G34: Associated LLFC/DUoS Tariff ID
A35: Site 1
A36: Site 2
A37: Site 3
A38: Site 4
A39: Site 5
A41: CVA site specific LLFs
A42: Site | B42: Period 1 | C42: Period 2 | D42: Period 3 | E42: Period 4 | F42: Period 5 | G42: MSID
A43: Site 1
A44: Site 2
A45: Site 3
A46: Site 4
A47: Site 5

Sheet Annex 6 New or Amended EHV
A1: Back to Overview | D1: Note: The DNO reserves the right to apply the listed charges to any other MPANs/MSIDs associated with the site. This includes reallocating charges to a traded MPAN at the same site where another MPAN has been disconnected or de-energised. If sites appear in both Annex 2 and Annex 6, the charges in Annex 6 take precedence. Where an existing Designated EHV Property is modified and energised in the charging year, we may revise the EDCM charges for the modified Designated EHV Property.
A2: Annex 6 - Charges for New or Amended Designated EHV Properties
A4: =Overview!B4& " - Effective from "&Overview!D4&" - "&Overview!E4&" new designated EHV charges" -> London Power Networks - Effective from 1 April 2027 - Final new designated EHV charges
A5: Effective from date | B5: Import Unique Identifier | C5: LLFC/ DUoS Tariff ID | D5: Import MPANs/MSIDs | E5: Export Unique Identifier | F5: LLFC/ DUoS Tariff ID | G5: Export MPANs/MSIDs | H5: Name | I5: Residual Charging Band | J5: ='Annex 2 Designated EHV charges'!I10 -> Import Super Red unit charge (p/kWh) | K5: ='Annex 2 Designated EHV charges'!J10 -> Import fixed charge (p/day) | L5: ='Annex 2 Designated EHV charges'!K10 -> Import capacity charge (p/kVA/day) | M5: ='Annex 2 Designated EHV charges'!L10 -> Import exceeded capacity charge (p/kVA/day) | N5: ='Annex 2 Designated EHV charges'!M10 -> Export Super Red unit charge (p/kWh) | O5: ='Annex 2 Designated EHV charges'!N10 -> Export fixed charge (p/day) | P5: ='Annex 2 Designated EHV charges'!O10 -> Export capacity charge (p/kVA/day) | Q5: ='Annex 2 Designated EHV charges'!P10 -> Export exceeded capacity charge (p/kVA/day)
A6: 01/04/2027 | B6: THAMEC | C6: 802 | D6: 1200061171324;1200061171333 | E6: THAMEC | F6: 702 | G6: 1200061171342;1200061171351 | H6: THAMEC | I6: 4 | J6: 0 | K6: 73260.99 | L6: 1.9 | M6: 1.9 | N6: -0.002 | O6: 1084.47 | P6: 0.05 | Q6: 0.05
A17: =Overview!B4& " - Effective from "&Overview!D4&" - "&Overview!E4&" new designated EHV line loss factors" -> London Power Networks - Effective from 1 April 2027 - Final new designated EHV line loss factors
A18: Effective from date | B18: Import Unique Identifier | C18: LLFC/ DUoS Tariff ID | D18: Import MPANs/MSIDs | E18: Export Unique Identifier | F18: LLFC/ DUoS Tariff ID | G18: Export MPANs/MSIDs | H18: Name | I18: Residual Charging Band | J18: Import LLF period 1 | K18: Import LLF period 2 | L18: Import LLF period 3 | M18: Import LLF period 4 | N18: Import LLF period 5 | O18: Export LLF period 1 | P18: Export LLF period 2 | Q18: Export LLF period 3 | R18: Export LLF period 4 | S18: Export LLF period 5

Sheet Annex 7 Pass-Through Costs
A1: Back to Overview
A2: =""&Overview!B4& " - Effective from "&Overview!D4&" - "&Overview!E4&" Supplier of Last Resort and Eligible Bad Debt Pass-Through Costs" -> London Power Networks - Effective from 1 April 2027 - Final Supplier of Last Resort and Eligible Bad Debt Pass-Through Costs
A4: Tariff name | B4: Open LLFCs/ DUoS Tariff IDs / LDNO unique billing identifier | C4: PCs | D4: Supplier of Last Resort Fixed charge adder* p/MPAN/day | E4: Eligible Bad Debt Fixed charge adder** p/MPAN/day
A5: Domestic Aggregated or CT with Residual | B5: =IFERROR(INDEX('Annex 1 LV, HV and UMS charges'!$B$13:$B$44,MATCH($A5,'Annex 1 LV, HV and UMS charges'!$A$13:$A$44,0)),IF(INDEX('Annex 4 LDNO charges'!$B$12:$B$202,MATCH($A5,'Annex 4 LDNO charges'!$A$12:$A$202,0))=0,"",INDEX('Annex 4 LDNO charges'!$B$12:$B$202,MATCH($A5,'Annex 4 LDNO charges'!$A$12:$A$202,0)))) -> 1 | C5: =IFERROR(INDEX('Annex 1 LV, HV and UMS charges'!$C$13:$C$44,MATCH($A5,'Annex 1 LV, HV and UMS charges'!$A$13:$A$44,0)),INDEX('Annex 4 LDNO charges'!$C$12:$C$202,MATCH($A5,'Annex 4 LDNO charges'!$A$12:$A$202,0))) -> 0, 1, 2 | D5: 0 | E5: 0
A6: Non-Domestic Aggregated or CT No Residual | B6: =IFERROR(INDEX('Annex 1 LV, HV and UMS charges'!$B$13:$B$44,MATCH($A6,'Annex 1 LV, HV and UMS charges'!$A$13:$A$44,0)),IF(INDEX('Annex 4 LDNO charges'!$B$12:$B$202,MATCH($A6,'Annex 4 LDNO charges'!$A$12:$A$202,0))=0,"",INDEX('Annex 4 LDNO charges'!$B$12:$B$202,MATCH($A6,'Annex 4 LDNO charges'!$A$12:$A$202,0)))) -> 199 | C6: =IFERROR(INDEX('Annex 1 LV, HV and UMS charges'!$C$13:$C$44,MATCH($A6,'Annex 1 LV, HV and UMS charges'!$A$13:$A$44,0)),INDEX('Annex 4 LDNO charges'!$C$12:$C$202,MATCH($A6,'Annex 4 LDNO charges'!$A$12:$A$202,0))) -> 0, 3, 4, 5-8 | E6: 0
A7: Non-Domestic Aggregated or CT Band 1 | B7: =IFERROR(INDEX('Annex 1 LV, HV and UMS charges'!$B$13:$B$44,MATCH($A7,'Annex 1 LV, HV and UMS charges'!$A$13:$A$44,0)),IF(INDEX('Annex 4 LDNO charges'!$B$12:$B$202,MATCH($A7,'Annex 4 LDNO charges'!$A$12:$A$202,0))=0,"",INDEX('Annex 4 LDNO charges'!$B$12:$B$202,MATCH($A7,'Annex 4 LDNO charges'!$A$12:$A$202,0)))) -> 201, N01 | C7: =IFERROR(INDEX('Annex 1 LV, HV and UMS charges'!$C$13:$C$44,MATCH($A7,'Annex 1 LV, HV and UMS charges'!$A$13:$A$44,0)),INDEX('Annex 4 LDNO charges'!$C$12:$C$202,MATCH($A7,'Annex 4 LDNO charges'!$A$12:$A$202,0))) -> 0, 3, 4, 5-8 | E7: 0
A8: Non-Domestic Aggregated or CT Band 2 | B8: =IFERROR(INDEX('Annex 1 LV, HV and UMS charges'!$B$13:$B$44,MATCH($A8,'Annex 1 LV, HV and UMS charges'!$A$13:$A$44,0)),IF(INDEX('Annex 4 LDNO charges'!$B$12:$B$202,MATCH($A8,'Annex 4 LDNO charges'!$A$12:$A$202,0))=0,"",INDEX('Annex 4 LDNO charges'!$B$12:$B$202,MATCH($A8,'Annex 4 LDNO charges'!$A$12:$A$202,0)))) -> 202, N02 | C8: =IFERROR(INDEX('Annex 1 LV, HV and UMS charges'!$C$13:$C$44,MATCH($A8,'Annex 1 LV, HV and UMS charges'!$A$13:$A$44,0)),INDEX('Annex 4 LDNO charges'!$C$12:$C$202,MATCH($A8,'Annex 4 LDNO charges'!$A$12:$A$202,0))) -> 0, 3, 4, 5-8 | E8: 0
A9: Non-Domestic Aggregated or CT Band 3 | B9: =IFERROR(INDEX('Annex 1 LV, HV and UMS charges'!$B$13:$B$44,MATCH($A9,'Annex 1 LV, HV and UMS charges'!$A$13:$A$44,0)),IF(INDEX('Annex 4 LDNO charges'!$B$12:$B$202,MATCH($A9,'Annex 4 LDNO charges'!$A$12:$A$202,0))=0,"",INDEX('Annex 4 LDNO charges'!$B$12:$B$202,MATCH($A9,'Annex 4 LDNO charges'!$A$12:$A$202,0)))) -> 203, N03 | C9: =IFERROR(INDEX('Annex 1 LV, HV and UMS charges'!$C$13:$C$44,MATCH($A9,'Annex 1 LV, HV and UMS charges'!$A$13:$A$44,0)),INDEX('Annex 4 LDNO charges'!$C$12:$C$202,MATCH($A9,'Annex 4 LDNO charges'!$A$12:$A$202,0))) -> 0, 3, 4, 5-8 | E9: 0
A10: Non-Domestic Aggregated or CT Band 4 | B10: =IFERROR(INDEX('Annex 1 LV, HV and UMS charges'!$B$13:$B$44,MATCH($A10,'Annex 1 LV, HV and UMS charges'!$A$13:$A$44,0)),IF(INDEX('Annex 4 LDNO charges'!$B$12:$B$202,MATCH($A10,'Annex 4 LDNO charges'!$A$12:$A$202,0))=0,"",INDEX('Annex 4 LDNO charges'!$B$12:$B$202,MATCH($A10,'Annex 4 LDNO charges'!$A$12:$A$202,0)))) -> 204, N04 | C10: =IFERROR(INDEX('Annex 1 LV, HV and UMS charges'!$C$13:$C$44,MATCH($A10,'Annex 1 LV, HV and UMS charges'!$A$13:$A$44,0)),INDEX('Annex 4 LDNO charges'!$C$12:$C$202,MATCH($A10,'Annex 4 LDNO charges'!$A$12:$A$202,0))) -> 0, 3, 4, 5-8 | E10: 0
A11: LV Site Specific No Residual | B11: =IFERROR(INDEX('Annex 1 LV, HV and UMS charges'!$B$13:$B$44,MATCH($A11,'Annex 1 LV, HV and UMS charges'!$A$13:$A$44,0)),IF(INDEX('Annex 4 LDNO charges'!$B$12:$B$202,MATCH($A11,'Annex 4 LDNO charges'!$A$12:$A$202,0))=0,"",INDEX('Annex 4 LDNO charges'!$B$12:$B$202,MATCH($A11,'Annex 4 LDNO charges'!$A$12:$A$202,0)))) -> 70 | C11: =IFERROR(INDEX('Annex 1 LV, HV and UMS charges'!$C$13:$C$44,MATCH($A11,'Annex 1 LV, HV and UMS charges'!$A$13:$A$44,0)),INDEX('Annex 4 LDNO charges'!$C$12:$C$202,MATCH($A11,'Annex 4 LDNO charges'!$A$12:$A$202,0))) -> 0 | E11: 0
A12: LV Site Specific Band 1 | B12: =IFERROR(INDEX('Annex 1 LV, HV and UMS charges'!$B$13:$B$44,MATCH($A12,'Annex 1 LV, HV and UMS charges'!$A$13:$A$44,0)),IF(INDEX('Annex 4 LDNO charges'!$B$12:$B$202,MATCH($A12,'Annex 4 LDNO charges'!$A$12:$A$202,0))=0,"",INDEX('Annex 4 LDNO charges'!$B$12:$B$202,MATCH($A12,'Annex 4 LDNO charges'!$A$12:$A$202,0)))) -> 71 | C12: =IFERROR(INDEX('Annex 1 LV, HV and UMS charges'!$C$13:$C$44,MATCH($A12,'Annex 1 LV, HV and UMS charges'!$A$13:$A$44,0)),INDEX('Annex 4 LDNO charges'!$C$12:$C$202,MATCH($A12,'Annex 4 LDNO charges'!$A$12:$A$202,0))) -> 0 | E12: 0
A13: LV Site Specific Band 2 | B13: =IFERROR(INDEX('Annex 1 LV, HV and UMS charges'!$B$13:$B$44,MATCH($A13,'Annex 1 LV, HV and UMS charges'!$A$13:$A$44,0)),IF(INDEX('Annex 4 LDNO charges'!$B$12:$B$202,MATCH($A13,'Annex 4 LDNO charges'!$A$12:$A$202,0))=0,"",INDEX('Annex 4 LDNO charges'!$B$12:$B$202,MATCH($A13,'Annex 4 LDNO charges'!$A$12:$A$202,0)))) -> 72 | C13: =IFERROR(INDEX('Annex 1 LV, HV and UMS charges'!$C$13:$C$44,MATCH($A13,'Annex 1 LV, HV and UMS charges'!$A$13:$A$44,0)),INDEX('Annex 4 LDNO charges'!$C$12:$C$202,MATCH($A13,'Annex 4 LDNO charges'!$A$12:$A$202,0))) -> 0 | E13: 0
A14: LV Site Specific Band 3 | B14: =IFERROR(INDEX('Annex 1 LV, HV and UMS charges'!$B$13:$B$44,MATCH($A14,'Annex 1 LV, HV and UMS charges'!$A$13:$A$44,0)),IF(INDEX('Annex 4 LDNO charges'!$B$12:$B$202,MATCH($A14,'Annex 4 LDNO charges'!$A$12:$A$202,0))=0,"",INDEX('Annex 4 LDNO charges'!$B$12:$B$202,MATCH($A14,'Annex 4 LDNO charges'!$A$12:$A$202,0)))) -> 73 | C14: =IFERROR(INDEX('Annex 1 LV, HV and UMS charges'!$C$13:$C$44,MATCH($A14,'Annex 1 LV, HV and UMS charges'!$A$13:$A$44,0)),INDEX('Annex 4 LDNO charges'!$C$12:$C$202,MATCH($A14,'Annex 4 LDNO charges'!$A$12:$A$202,0))) -> 0 | E14: 0
A15: LV Site Specific Band 4 | B15: =IFERROR(INDEX('Annex 1 LV, HV and UMS charges'!$B$13:$B$44,MATCH($A15,'Annex 1 LV, HV and UMS charges'!$A$13:$A$44,0)),IF(INDEX('Annex 4 LDNO charges'!$B$12:$B$202,MATCH($A15,'Annex 4 LDNO charges'!$A$12:$A$202,0))=0,"",INDEX('Annex 4 LDNO charges'!$B$12:$B$202,MATCH($A15,'Annex 4 LDNO charges'!$A$12:$A$202,0)))) -> 74 | C15: =IFERROR(INDEX('Annex 1 LV, HV and UMS charges'!$C$13:$C$44,MATCH($A15,'Annex 1 LV, HV and UMS charges'!$A$13:$A$44,0)),INDEX('Annex 4 LDNO charges'!$C$12:$C$202,MATCH($A15,'Annex 4 LDNO charges'!$A$12:$A$202,0))) -> 0 | E15: 0
A16: LV Sub Site Specific No Residual | B16: =IFERROR(INDEX('Annex 1 LV, HV and UMS charges'!$B$13:$B$44,MATCH($A16,'Annex 1 LV, HV and UMS charges'!$A$13:$A$44,0)),IF(INDEX('Annex 4 LDNO charges'!$B$12:$B$202,MATCH($A16,'Annex 4 LDNO charges'!$A$12:$A$202,0))=0,"",INDEX('Annex 4 LDNO charges'!$B$12:$B$202,MATCH($A16,'Annex 4 LDNO charges'!$A$12:$A$202,0)))) -> 80 | C16: =IFERROR(INDEX('Annex 1 LV, HV and UMS charges'!$C$13:$C$44,MATCH($A16,'Annex 1 LV, HV and UMS charges'!$A$13:$A$44,0)),INDEX('Annex 4 LDNO charges'!$C$12:$C$202,MATCH($A16,'Annex 4 LDNO charges'!$A$12:$A$202,0))) -> 0 | E16: 0
A17: LV Sub Site Specific Band 1 | B17: =IFERROR(INDEX('Annex 1 LV, HV and UMS charges'!$B$13:$B$44,MATCH($A17,'Annex 1 LV, HV and UMS charges'!$A$13:$A$44,0)),IF(INDEX('Annex 4 LDNO charges'!$B$12:$B$202,MATCH($A17,'Annex 4 LDNO charges'!$A$12:$A$202,0))=0,"",INDEX('Annex 4 LDNO charges'!$B$12:$B$202,MATCH($A17,'Annex 4 LDNO charges'!$A$12:$A$202,0)))) -> 81 | C17: =IFERROR(INDEX('Annex 1 LV, HV and UMS charges'!$C$13:$C$44,MATCH($A17,'Annex 1 LV, HV and UMS charges'!$A$13:$A$44,0)),INDEX('Annex 4 LDNO charges'!$C$12:$C$202,MATCH($A17,'Annex 4 LDNO charges'!$A$12:$A$202,0))) -> 0 | E17: 0
... A25: HV Site Specific Band 4 | B25: =IFERROR(INDEX('Annex 1 LV, HV and UMS charges'!$B$13:$B$44,MATCH($A25,'Annex 1 LV, HV and UMS charges'!$A$13:$A$44,0)),IF(INDEX('Annex 4 LDNO charges'!$B$12:$B$202,MATCH($A25,'Annex 4 LDNO charges'!$A$12:$A$202,0))=0,"",INDEX('Annex 4 LDNO charges'!$B$12:$B$202,MATCH($A25,'Annex 4 LDNO charges'!$A$12:$A$202,0)))) -> 94 | C25: =IFERROR(INDEX('Annex 1 LV, HV and UMS charges'!$C$13:$C$44,MATCH($A25,'Annex 1 LV, HV and UMS charges'!$A$13:$A$44,0)),INDEX('Annex 4 LDNO charges'!$C$12:$C$202,MATCH($A25,'Annex 4 LDNO charges'!$A$12:$A$202,0))) -> 0 | E25: 0
A26: LDNO LV: Domestic Aggregated or CT with Residual | B26: =IFERROR(INDEX('Annex 1 LV, HV and UMS charges'!$B$13:$B$44,MATCH($A26,'Annex 1 LV, HV and UMS charges'!$A$13:$A$44,0)),IF(INDEX('Annex 4 LDNO charges'!$B$12:$B$202,MATCH($A26,'Annex 4 LDNO charges'!$A$12:$A$202,0))=0,"",INDEX('Annex 4 LDNO charges'!$B$12:$B$202,MATCH($A26,'Annex 4 LDNO charges'!$A$12:$A$202,0)))) -> A00 | C26: =IFERROR(INDEX('Annex 1 LV, HV and UMS charges'!$C$13:$C$44,MATCH($A26,'Annex 1 LV, HV and UMS charges'!$A$13:$A$44,0)),INDEX('Annex 4 LDNO charges'!$C$12:$C$202,MATCH($A26,'Annex 4 LDNO charges'!$A$12:$A$202,0))) -> 0, 1, 2 | D26: 0 | E26: 0
A27: LDNO LV: Non-Domestic Aggregated or CT No Residual | B27: =IFERROR(INDEX('Annex 1 LV, HV and UMS charges'!$B$13:$B$44,MATCH($A27,'Annex 1 LV, HV and UMS charges'!$A$13:$A$44,0)),IF(INDEX('Annex 4 LDNO charges'!$B$12:$B$202,MATCH($A27,'Annex 4 LDNO charges'!$A$12:$A$202,0))=0,"",INDEX('Annex 4 LDNO charges'!$B$12:$B$202,MATCH($A27,'Annex 4 LDNO charges'!$A$12:$A$202,0)))) -> C00 | C27: =IFERROR(INDEX('Annex 1 LV, HV and UMS charges'!$C$13:$C$44,MATCH($A27,'Annex 1 LV, HV and UMS charges'!$A$13:$A$44,0)),INDEX('Annex 4 LDNO charges'!$C$12:$C$202,MATCH($A27,'Annex 4 LDNO charges'!$A$12:$A$202,0))) -> 0, 3, 4, 5-8 | E27: 0
A28: LDNO LV: Non-Domestic Aggregated or CT Band 1 | B28: =IFERROR(INDEX('Annex 1 LV, HV and UMS charges'!$B$13:$B$44,MATCH($A28,'Annex 1 LV, HV and UMS charges'!$A$13:$A$44,0)),IF(INDEX('Annex 4 LDNO charges'!$B$12:$B$202,MATCH($A28,'Annex 4 LDNO charges'!$A$12:$A$202,0))=0,"",INDEX('Annex 4 LDNO charges'!$B$12:$B$202,MATCH($A28,'Annex 4 LDNO charges'!$A$12:$A$202,0)))) -> C01 | C28: =IFERROR(INDEX('Annex 1 LV, HV and UMS charges'!$C$13:$C$44,MATCH($A28,'Annex 1 LV, HV and UMS charges'!$A$13:$A$44,0)),INDEX('Annex 4 LDNO charges'!$C$12:$C$202,MATCH($A28,'Annex 4 LDNO charges'!$A$12:$A$202,0))) -> 0, 3, 4, 5-8 | E28: 0
A29: LDNO LV: Non-Domestic Aggregated or CT Band 2 | B29: =IFERROR(INDEX('Annex 1 LV, HV and UMS charges'!$B$13:$B$44,MATCH($A29,'Annex 1 LV, HV and UMS charges'!$A$13:$A$44,0)),IF(INDEX('Annex 4 LDNO charges'!$B$12:$B$202,MATCH($A29,'Annex 4 LDNO charges'!$A$12:$A$202,0))=0,"",INDEX('Annex 4 LDNO charges'!$B$12:$B$202,MATCH($A29,'Annex 4 LDNO charges'!$A$12:$A$202,0)))) -> C02 | C29: =IFERROR(INDEX('Annex 1 LV, HV and UMS charges'!$C$13:$C$44,MATCH($A29,'Annex 1 LV, HV and UMS charges'!$A$13:$A$44,0)),INDEX('Annex 4 LDNO charges'!$C$12:$C$202,MATCH($A29,'Annex 4 LDNO charges'!$A$12:$A$202,0))) -> 0, 3, 4, 5-8 | E29: 0
A30: LDNO LV: Non-Domestic Aggregated or CT Band 3 | B30: =IFERROR(INDEX('Annex 1 LV, HV and UMS charges'!$B$13:$B$44,MATCH($A30,'Annex 1 LV, HV and UMS charges'!$A$13:$A$44,0)),IF(INDEX('Annex 4 LDNO charges'!$B$12:$B$202,MATCH($A30,'Annex 4 LDNO charges'!$A$12:$A$202,0))=0,"",INDEX('Annex 4 LDNO charges'!$B$12:$B$202,MATCH($A30,'Annex 4 LDNO charges'!$A$12:$A$202,0)))) -> C03 | C30: =IFERROR(INDEX('Annex 1 LV, HV and UMS charges'!$C$13:$C$44,MATCH($A30,'Annex 1 LV, HV and UMS charges'!$A$13:$A$44,0)),INDEX('Annex 4 LDNO charges'!$C$12:$C$202,MATCH($A30,'Annex 4 LDNO charges'!$A$12:$A$202,0))) -> 0, 3, 4, 5-8 | E30: 0
A31: LDNO LV: Non-Domestic Aggregated or CT Band 4 | B31: =IFERROR(INDEX('Annex 1 LV, HV and UMS charges'!$B$13:$B$44,MATCH($A31,'Annex 1 LV, HV and UMS charges'!$A$13:$A$44,0)),IF(INDEX('Annex 4 LDNO charges'!$B$12:$B$202,MATCH($A31,'Annex 4 LDNO charges'!$A$12:$A$202,0))=0,"",INDEX('Annex 4 LDNO charges'!$B$12:$B$202,MATCH($A31,'Annex 4 LDNO charges'!$A$12:$A$202,0)))) -> C04 | C31: =IFERROR(INDEX('Annex 1 LV, HV and UMS charges'!$C$13:$C$44,MATCH($A31,'Annex 1 LV, HV and UMS charges'!$A$13:$A$44,0)),INDEX('Annex 4 LDNO charges'!$C$12:$C$202,MATCH($A31,'Annex 4 LDNO charges'!$A$12:$A$202,0))) -> 0, 3, 4, 5-8 | E31: 0
A32: LDNO LV: LV Site Specific No Residual | B32: =IFERROR(INDEX('Annex 1 LV, HV and UMS charges'!$B$13:$B$44,MATCH($A32,'Annex 1 LV, HV and UMS charges'!$A$13:$A$44,0)),IF(INDEX('Annex 4 LDNO charges'!$B$12:$B$202,MATCH($A32,'Annex 4 LDNO charges'!$A$12:$A$202,0))=0,"",INDEX('Annex 4 LDNO charges'!$B$12:$B$202,MATCH($A32,'Annex 4 LDNO charges'!$A$12:$A$202,0)))) -> E00 | C32: =IFERROR(INDEX('Annex 1 LV, HV and UMS charges'!$C$13:$C$44,MATCH($A32,'Annex 1 LV, HV and UMS charges'!$A$13:$A$44,0)),INDEX('Annex 4 LDNO charges'!$C$12:$C$202,MATCH($A32,'Annex 4 LDNO charges'!$A$12:$A$202,0))) -> 0 | E32: 0
A33: LDNO LV: LV Site Specific Band 1 | B33: =IFERROR(INDEX('Annex 1 LV, HV and UMS charges'!$B$13:$B$44,MATCH($A33,'Annex 1 LV, HV and UMS charges'!$A$13:$A$44,0)),IF(INDEX('Annex 4 LDNO charges'!$B$12:$B$202,MATCH($A33,'Annex 4 LDNO charges'!$A$12:$A$202,0))=0,"",INDEX('Annex 4 LDNO charges'!$B$12:$B$202,MATCH($A33,'Annex 4 LDNO charges'!$A$12:$A$202,0)))) -> E01 | C33: =IFERROR(INDEX('Annex 1 LV, HV and UMS charges'!$C$13:$C$44,MATCH($A33,'Annex 1 LV, HV and UMS charges'!$A$13:$A$44,0)),INDEX('Annex 4 LDNO charges'!$C$12:$C$202,MATCH($A33,'Annex 4 LDNO charges'!$A$12:$A$202,0))) -> 0 | E33: 0
A34: LDNO LV: LV Site Specific Band 2 | B34: =IFERROR(INDEX('Annex 1 LV, HV and UMS charges'!$B$13:$B$44,MATCH($A34,'Annex 1 LV, HV and UMS charges'!$A$13:$A$44,0)),IF(INDEX('Annex 4 LDNO charges'!$B$12:$B$202,MATCH($A34,'Annex 4 LDNO charges'!$A$12:$A$202,0))=0,"",INDEX('Annex 4 LDNO charges'!$B$12:$B$202,MATCH($A34,'Annex 4 LDNO charges'!$A$12:$A$202,0)))) -> E02 | C34: =IFERROR(INDEX('Annex 1 LV, HV and UMS charges'!$C$13:$C$44,MATCH($A34,'Annex 1 LV, HV and UMS charges'!$A$13:$A$44,0)),INDEX('Annex 4 LDNO charges'!$C$12:$C$202,MATCH($A34,'Annex 4 LDNO charges'!$A$12:$A$202,0))) -> 0 | E34: 0
A35: LDNO LV: LV Site Specific Band 3 | B35: =IFERROR(INDEX('Annex 1 LV, HV and UMS charges'!$B$13:$B$44,MATCH($A35,'Annex 1 LV, HV and UMS charges'!$A$13:$A$44,0)),IF(INDEX('Annex 4 LDNO charges'!$B$12:$B$202,MATCH($A35,'Annex 4 LDNO charges'!$A$12:$A$202,0))=0,"",INDEX('Annex 4 LDNO charges'!$B$12:$B$202,MATCH($A35,'Annex 4 LDNO charges'!$A$12:$A$202,0)))) -> E03 | C35: =IFERROR(INDEX('Annex 1 LV, HV and UMS charges'!$C$13:$C$44,MATCH($A35,'Annex 1 LV, HV and UMS charges'!$A$13:$A$44,0)),INDEX('Annex 4 LDNO charges'!$C$12:$C$202,MATCH($A35,'Annex 4 LDNO charges'!$A$12:$A$202,0))) -> 0 | E35: 0
A36: LDNO LV: LV Site Specific Band 4 | B36: =IFERROR(INDEX('Annex 1 LV, HV and UMS charges'!$B$13:$B$44,MATCH($A36,'Annex 1 LV, HV and UMS charges'!$A$13:$A$44,0)),IF(INDEX('Annex 4 LDNO charges'!$B$12:$B$202,MATCH($A36,'Annex 4 LDNO charges'!$A$12:$A$202,0))=0,"",INDEX('Annex 4 LDNO charges'!$B$12:$B$202,MATCH($A36,'Annex 4 LDNO charges'!$A$12:$A$202,0)))) -> E04 | C36: =IFERROR(INDEX('Annex 1 LV, HV and UMS charges'!$C$13:$C$44,MATCH($A36,'Annex 1 LV, HV and UMS charges'!$A$13:$A$44,0)),INDEX('Annex 4 LDNO charges'!$C$12:$C$202,MATCH($A36,'Annex 4 LDNO charges'!$A$12:$A$202,0))) -> 0 | E36: 0
A37: LDNO HV: Domestic Aggregated or CT with Residual | B37: =IFERROR(INDEX('Annex 1 LV, HV and UMS charges'!$B$13:$B$44,MATCH($A37,'Annex 1 LV, HV and UMS charges'!$A$13:$A$44,0)),IF(INDEX('Annex 4 LDNO charges'!$B$12:$B$202,MATCH($A37,'Annex 4 LDNO charges'!$A$12:$A$202,0))=0,"",INDEX('Annex 4 LDNO charges'!$B$12:$B$202,MATCH($A37,'Annex 4 LDNO charges'!$A$12:$A$202,0)))) -> A10 | C37: =IFERROR(INDEX('Annex 1 LV, HV and UMS charges'!$C$13:$C$44,MATCH($A37,'Annex 1 LV, HV and UMS charges'!$A$13:$A$44,0)),INDEX('Annex 4 LDNO charges'!$C$12:$C$202,MATCH($A37,'Annex 4 LDNO charges'!$A$12:$A$202,0))) -> 0, 1, 2 | D37: 0 | E37: 0
A38: LDNO HV: Non-Domestic Aggregated or CT No Residual | B38: =IFERROR(INDEX('Annex 1 LV, HV and UMS charges'!$B$13:$B$44,MATCH($A38,'Annex 1 LV, HV and UMS charges'!$A$13:$A$44,0)),IF(INDEX('Annex 4 LDNO charges'!$B$12:$B$202,MATCH($A38,'Annex 4 LDNO charges'!$A$12:$A$202,0))=0,"",INDEX('Annex 4 LDNO charges'!$B$12:$B$202,MATCH($A38,'Annex 4 LDNO charges'!$A$12:$A$202,0)))) -> C10 | C38: =IFERROR(INDEX('Annex 1 LV, HV and UMS charges'!$C$13:$C$44,MATCH($A38,'Annex 1 LV, HV and UMS charges'!$A$13:$A$44,0)),INDEX('Annex 4 LDNO charges'!$C$12:$C$202,MATCH($A38,'Annex 4 LDNO charges'!$A$12:$A$202,0))) -> 0, 3, 4, 5-8 | E38: 0
A39: LDNO HV: Non-Domestic Aggregated or CT Band 1 | B39: =IFERROR(INDEX('Annex 1 LV, HV and UMS charges'!$B$13:$B$44,MATCH($A39,'Annex 1 LV, HV and UMS charges'!$A$13:$A$44,0)),IF(INDEX('Annex 4 LDNO charges'!$B$12:$B$202,MATCH($A39,'Annex 4 LDNO charges'!$A$12:$A$202,0))=0,"",INDEX('Annex 4 LDNO charges'!$B$12:$B$202,MATCH($A39,'Annex 4 LDNO charges'!$A$12:$A$202,0)))) -> C11 | C39: =IFERROR(INDEX('Annex 1 LV, HV and UMS charges'!$C$13:$C$44,MATCH($A39,'Annex 1 LV, HV and UMS charges'!$A$13:$A$44,0)),INDEX('Annex 4 LDNO charges'!$C$12:$C$202,MATCH($A39,'Annex 4 LDNO charges'!$A$12:$A$202,0))) -> 0, 3, 4, 5-8 | E39: 0
A40: LDNO HV: Non-Domestic Aggregated or CT Band 2 | B40: =IFERROR(INDEX('Annex 1 LV, HV and UMS charges'!$B$13:$B$44,MATCH($A40,'Annex 1 LV, HV and UMS charges'!$A$13:$A$44,0)),IF(INDEX('Annex 4 LDNO charges'!$B$12:$B$202,MATCH($A40,'Annex 4 LDNO charges'!$A$12:$A$202,0))=0,"",INDEX('Annex 4 LDNO charges'!$B$12:$B$202,MATCH($A40,'Annex 4 LDNO charges'!$A$12:$A$202,0)))) -> C12 | C40: =IFERROR(INDEX('Annex 1 LV, HV and UMS charges'!$C$13:$C$44,MATCH($A40,'Annex 1 LV, HV and UMS charges'!$A$13:$A$44,0)),INDEX('Annex 4 LDNO charges'!$C$12:$C$202,MATCH($A40,'Annex 4 LDNO charges'!$A$12:$A$202,0))) -> 0, 3, 4, 5-8 | E40: 0
A41: LDNO HV: Non-Domestic Aggregated or CT Band 3 | B41: =IFERROR(INDEX('Annex 1 LV, HV and UMS charges'!$B$13:$B$44,MATCH($A41,'Annex 1 LV, HV and UMS charges'!$A$13:$A$44,0)),IF(INDEX('Annex 4 LDNO charges'!$B$12:$B$202,MATCH($A41,'Annex 4 LDNO charges'!$A$12:$A$202,0))=0,"",INDEX('Annex 4 LDNO charges'!$B$12:$B$202,MATCH($A41,'Annex 4 LDNO charges'!$A$12:$A$202,0)))) -> C13 | C41: =IFERROR(INDEX('Annex 1 LV, HV and UMS charges'!$C$13:$C$44,MATCH($A41,'Annex 1 LV, HV and UMS charges'!$A$13:$A$44,0)),INDEX('Annex 4 LDNO charges'!$C$12:$C$202,MATCH($A41,'Annex 4 LDNO charges'!$A$12:$A$202,0))) -> 0, 3, 4, 5-8 | E41: 0
A42: LDNO HV: Non-Domestic Aggregated or CT Band 4 | B42: =IFERROR(INDEX('Annex 1 LV, HV and UMS charges'!$B$13:$B$44,MATCH($A42,'Annex 1 LV, HV and UMS charges'!$A$13:$A$44,0)),IF(INDEX('Annex 4 LDNO charges'!$B$12:$B$202,MATCH($A42,'Annex 4 LDNO charges'!$A$12:$A$202,0))=0,"",INDEX('Annex 4 LDNO charges'!$B$12:$B$202,MATCH($A42,'Annex 4 LDNO charges'!$A$12:$A$202,0)))) -> C14 | C42: =IFERROR(INDEX('Annex 1 LV, HV and UMS charges'!$C$13:$C$44,MATCH($A42,'Annex 1 LV, HV and UMS charges'!$A$13:$A$44,0)),INDEX('Annex 4 LDNO charges'!$C$12:$C$202,MATCH($A42,'Annex 4 LDNO charges'!$A$12:$A$202,0))) -> 0, 3, 4, 5-8 | E42: 0
A43: LDNO HV: LV Site Specific No Residual | B43: =IFERROR(INDEX('Annex 1 LV, HV and UMS charges'!$B$13:$B$44,MATCH($A43,'Annex 1 LV, HV and UMS charges'!$A$13:$A$44,0)),IF(INDEX('Annex 4 LDNO charges'!$B$12:$B$202,MATCH($A43,'Annex 4 LDNO charges'!$A$12:$A$202,0))=0,"",INDEX('Annex 4 LDNO charges'!$B$12:$B$202,MATCH($A43,'Annex 4 LDNO charges'!$A$12:$A$202,0)))) -> E10 | C43: =IFERROR(INDEX('Annex 1 LV, HV and UMS charges'!$C$13:$C$44,MATCH($A43,'Annex 1 LV, HV and UMS charges'!$A$13:$A$44,0)),INDEX('Annex 4 LDNO charges'!$C$12:$C$202,MATCH($A43,'Annex 4 LDNO charges'!$A$12:$A$202,0))) -> 0 | E43: 0
A44: LDNO HV: LV Site Specific Band 1 | B44: =IFERROR(INDEX('Annex 1 LV, HV and UMS charges'!$B$13:$B$44,MATCH($A44,'Annex 1 LV, HV and UMS charges'!$A$13:$A$44,0)),IF(INDEX('Annex 4 LDNO charges'!$B$12:$B$202,MATCH($A44,'Annex 4 LDNO charges'!$A$12:$A$202,0))=0,"",INDEX('Annex 4 LDNO charges'!$B$12:$B$202,MATCH($A44,'Annex 4 LDNO charges'!$A$12:$A$202,0)))) -> E11 | C44: =IFERROR(INDEX('Annex 1 LV, HV and UMS charges'!$C$13:$C$44,MATCH($A44,'Annex 1 LV, HV and UMS charges'!$A$13:$A$44,0)),INDEX('Annex 4 LDNO charges'!$C$12:$C$202,MATCH($A44,'Annex 4 LDNO charges'!$A$12:$A$202,0))) -> 0 | E44: 0
A45: LDNO HV: LV Site Specific Band 2 | B45: =IFERROR(INDEX('Annex 1 LV, HV and UMS charges'!$B$13:$B$44,MATCH($A45,'Annex 1 LV, HV and UMS charges'!$A$13:$A$44,0)),IF(INDEX('Annex 4 LDNO charges'!$B$12:$B$202,MATCH($A45,'Annex 4 LDNO charges'!$A$12:$A$202,0))=0,"",INDEX('Annex 4 LDNO charges'!$B$12:$B$202,MATCH($A45,'Annex 4 LDNO charges'!$A$12:$A$202,0)))) -> E12 | C45: =IFERROR(INDEX('Annex 1 LV, HV and UMS charges'!$C$13:$C$44,MATCH($A45,'Annex 1 LV, HV and UMS charges'!$A$13:$A$44,0)),INDEX('Annex 4 LDNO charges'!$C$12:$C$202,MATCH($A45,'Annex 4 LDNO charges'!$A$12:$A$202,0))) -> 0 | E45: 0
A46: LDNO HV: LV Site Specific Band 3 | B46: =IFERROR(INDEX('Annex 1 LV, HV and UMS charges'!$B$13:$B$44,MATCH($A46,'Annex 1 LV, HV and UMS charges'!$A$13:$A$44,0)),IF(INDEX('Annex 4 LDNO charges'!$B$12:$B$202,MATCH($A46,'Annex 4 LDNO charges'!$A$12:$A$202,0))=0,"",INDEX('Annex 4 LDNO charges'!$B$12:$B$202,MATCH($A46,'Annex 4 LDNO charges'!$A$12:$A$202,0)))) -> E13 | C46: =IFERROR(INDEX('Annex 1 LV, HV and UMS charges'!$C$13:$C$44,MATCH($A46,'Annex 1 LV, HV and UMS charges'!$A$13:$A$44,0)),INDEX('Annex 4 LDNO charges'!$C$12:$C$202,MATCH($A46,'Annex 4 LDNO charges'!$A$12:$A$202,0))) -> 0 | E46: 0
A47: LDNO HV: LV Site Specific Band 4 | B47: =IFERROR(INDEX('Annex 1 LV, HV and UMS charges'!$B$13:$B$44,MATCH($A47,'Annex 1 LV, HV and UMS charges'!$A$13:$A$44,0)),IF(INDEX('Annex 4 LDNO charges'!$B$12:$B$202,MATCH($A47,'Annex 4 LDNO charges'!$A$12:$A$202,0))=0,"",INDEX('Annex 4 LDNO charges'!$B$12:$B$202,MATCH($A47,'Annex 4 LDNO charges'!$A$12:$A$202,0)))) -> E14 | C47: =IFERROR(INDEX('Annex 1 LV, HV and UMS charges'!$C$13:$C$44,MATCH($A47,'Annex 1 LV, HV and UMS charges'!$A$13:$A$44,0)),INDEX('Annex 4 LDNO charges'!$C$12:$C$202,MATCH($A47,'Annex 4 LDNO charges'!$A$12:$A$202,0))) -> 0 | E47: 0
A48: LDNO HV: LV Sub Site Specific No Residual | B48: =IFERROR(INDEX('Annex 1 LV, HV and UMS charges'!$B$13:$B$44,MATCH($A48,'Annex 1 LV, HV and UMS charges'!$A$13:$A$44,0)),IF(INDEX('Annex 4 LDNO charges'!$B$12:$B$202,MATCH($A48,'Annex 4 LDNO charges'!$A$12:$A$202,0))=0,"",INDEX('Annex 4 LDNO charges'!$B$12:$B$202,MATCH($A48,'Annex 4 LDNO charges'!$A$12:$A$202,0)))) -> J10 | C48: =IFERROR(INDEX('Annex 1 LV, HV and UMS charges'!$C$13:$C$44,MATCH($A48,'Annex 1 LV, HV and UMS charges'!$A$13:$A$44,0)),INDEX('Annex 4 LDNO charges'!$C$12:$C$202,MATCH($A48,'Annex 4 LDNO charges'!$A$12:$A$202,0))) -> 0 | E48: 0
A49: LDNO HV: LV Sub Site Specific Band 1 | B49: =IFERROR(INDEX('Annex 1 LV, HV and UMS charges'!$B$13:$B$44,MATCH($A49,'Annex 1 LV, HV and UMS charges'!$A$13:$A$44,0)),IF(INDEX('Annex 4 LDNO charges'!$B$12:$B$202,MATCH($A49,'Annex 4 LDNO charges'!$A$12:$A$202,0))=0,"",INDEX('Annex 4 LDNO charges'!$B$12:$B$202,MATCH($A49,'Annex 4 LDNO charges'!$A$12:$A$202,0)))) -> J11 | C49: =IFERROR(INDEX('Annex 1 LV, HV and UMS charges'!$C$13:$C$44,MATCH($A49,'Annex 1 LV, HV and UMS charges'!$A$13:$A$44,0)),INDEX('Annex 4 LDNO charges'!$C$12:$C$202,MATCH($A49,'Annex 4 LDNO charges'!$A$12:$A$202,0))) -> 0 | E49: 0
... A57: LDNO HV: HV Site Specific Band 4 | B57: =IFERROR(INDEX('Annex 1 LV, HV and UMS charges'!$B$13:$B$44,MATCH($A57,'Annex 1 LV, HV and UMS charges'!$A$13:$A$44,0)),IF(INDEX('Annex 4 LDNO charges'!$B$12:$B$202,MATCH($A57,'Annex 4 LDNO charges'!$A$12:$A$202,0))=0,"",INDEX('Annex 4 LDNO charges'!$B$12:$B$202,MATCH($A57,'Annex 4 LDNO charges'!$A$12:$A$202,0)))) -> K14 | C57: =IFERROR(INDEX('Annex 1 LV, HV and UMS charges'!$C$13:$C$44,MATCH($A57,'Annex 1 LV, HV and UMS charges'!$A$13:$A$44,0)),INDEX('Annex 4 LDNO charges'!$C$12:$C$202,MATCH($A57,'Annex 4 LDNO charges'!$A$12:$A$202,0))) -> 0 | E57: 0
A58: LDNO HVplus: Domestic Aggregated or CT with Residual | B58: =IFERROR(INDEX('Annex 1 LV, HV and UMS charges'!$B$13:$B$44,MATCH($A58,'Annex 1 LV, HV and UMS charges'!$A$13:$A$44,0)),IF(INDEX('Annex 4 LDNO charges'!$B$12:$B$202,MATCH($A58,'Annex 4 LDNO charges'!$A$12:$A$202,0))=0,"",INDEX('Annex 4 LDNO charges'!$B$12:$B$202,MATCH($A58,'Annex 4 LDNO charges'!$A$12:$A$202,0)))) -> A20 | C58: =IFERROR(INDEX('Annex 1 LV, HV and UMS charges'!$C$13:$C$44,MATCH($A58,'Annex 1 LV, HV and UMS charges'!$A$13:$A$44,0)),INDEX('Annex 4 LDNO charges'!$C$12:$C$202,MATCH($A58,'Annex 4 LDNO charges'!$A$12:$A$202,0))) -> 0, 1, 2 | D58: 0 | E58: 0
A59: LDNO HVplus: Non-Domestic Aggregated or CT No Residual | B59: =IFERROR(INDEX('Annex 1 LV, HV and UMS charges'!$B$13:$B$44,MATCH($A59,'Annex 1 LV, HV and UMS charges'!$A$13:$A$44,0)),IF(INDEX('Annex 4 LDNO charges'!$B$12:$B$202,MATCH($A59,'Annex 4 LDNO charges'!$A$12:$A$202,0))=0,"",INDEX('Annex 4 LDNO charges'!$B$12:$B$202,MATCH($A59,'Annex 4 LDNO charges'!$A$12:$A$202,0)))) -> C20 | C59: =IFERROR(INDEX('Annex 1 LV, HV and UMS charges'!$C$13:$C$44,MATCH($A59,'Annex 1 LV, HV and UMS charges'!$A$13:$A$44,0)),INDEX('Annex 4 LDNO charges'!$C$12:$C$202,MATCH($A59,'Annex 4 LDNO charges'!$A$12:$A$202,0))) -> 0, 3, 4, 5-8 | E59: 0
A60: LDNO HVplus: Non-Domestic Aggregated or CT Band 1 | B60: =IFERROR(INDEX('Annex 1 LV, HV and UMS charges'!$B$13:$B$44,MATCH($A60,'Annex 1 LV, HV and UMS charges'!$A$13:$A$44,0)),IF(INDEX('Annex 4 LDNO charges'!$B$12:$B$202,MATCH($A60,'Annex 4 LDNO charges'!$A$12:$A$202,0))=0,"",INDEX('Annex 4 LDNO charges'!$B$12:$B$202,MATCH($A60,'Annex 4 LDNO charges'!$A$12:$A$202,0)))) -> C21 | C60: =IFERROR(INDEX('Annex 1 LV, HV and UMS charges'!$C$13:$C$44,MATCH($A60,'Annex 1 LV, HV and UMS charges'!$A$13:$A$44,0)),INDEX('Annex 4 LDNO charges'!$C$12:$C$202,MATCH($A60,'Annex 4 LDNO charges'!$A$12:$A$202,0))) -> 0, 3, 4, 5-8 | E60: 0
A61: LDNO HVplus: Non-Domestic Aggregated or CT Band 2 | B61: =IFERROR(INDEX('Annex 1 LV, HV and UMS charges'!$B$13:$B$44,MATCH($A61,'Annex 1 LV, HV and UMS charges'!$A$13:$A$44,0)),IF(INDEX('Annex 4 LDNO charges'!$B$12:$B$202,MATCH($A61,'Annex 4 LDNO charges'!$A$12:$A$202,0))=0,"",INDEX('Annex 4 LDNO charges'!$B$12:$B$202,MATCH($A61,'Annex 4 LDNO charges'!$A$12:$A$202,0)))) -> C22 | C61: =IFERROR(INDEX('Annex 1 LV, HV and UMS charges'!$C$13:$C$44,MATCH($A61,'Annex 1 LV, HV and UMS charges'!$A$13:$A$44,0)),INDEX('Annex 4 LDNO charges'!$C$12:$C$202,MATCH($A61,'Annex 4 LDNO charges'!$A$12:$A$202,0))) -> 0, 3, 4, 5-8 | E61: 0
A62: LDNO HVplus: Non-Domestic Aggregated or CT Band 3 | B62: =IFERROR(INDEX('Annex 1 LV, HV and UMS charges'!$B$13:$B$44,MATCH($A62,'Annex 1 LV, HV and UMS charges'!$A$13:$A$44,0)),IF(INDEX('Annex 4 LDNO charges'!$B$12:$B$202,MATCH($A62,'Annex 4 LDNO charges'!$A$12:$A$202,0))=0,"",INDEX('Annex 4 LDNO charges'!$B$12:$B$202,MATCH($A62,'Annex 4 LDNO charges'!$A$12:$A$202,0)))) -> C23 | C62: =IFERROR(INDEX('Annex 1 LV, HV and UMS charges'!$C$13:$C$44,MATCH($A62,'Annex 1 LV, HV and UMS charges'!$A$13:$A$44,0)),INDEX('Annex 4 LDNO charges'!$C$12:$C$202,MATCH($A62,'Annex 4 LDNO charges'!$A$12:$A$202,0))) -> 0, 3, 4, 5-8 | E62: 0
A63: LDNO HVplus: Non-Domestic Aggregated or CT Band 4 | B63: =IFERROR(INDEX('Annex 1 LV, HV and UMS charges'!$B$13:$B$44,MATCH($A63,'Annex 1 LV, HV and UMS charges'!$A$13:$A$44,0)),IF(INDEX('Annex 4 LDNO charges'!$B$12:$B$202,MATCH($A63,'Annex 4 LDNO charges'!$A$12:$A$202,0))=0,"",INDEX('Annex 4 LDNO charges'!$B$12:$B$202,MATCH($A63,'Annex 4 LDNO charges'!$A$12:$A$202,0)))) -> C24 | C63: =IFERROR(INDEX('Annex 1 LV, HV and UMS charges'!$C$13:$C$44,MATCH($A63,'Annex 1 LV, HV and UMS charges'!$A$13:$A$44,0)),INDEX('Annex 4 LDNO charges'!$C$12:$C$202,MATCH($A63,'Annex 4 LDNO charges'!$A$12:$A$202,0))) -> 0, 3, 4, 5-8 | E63: 0
A64: LDNO HVplus: LV Site Specific No Residual | B64: =IFERROR(INDEX('Annex 1 LV, HV and UMS charges'!$B$13:$B$44,MATCH($A64,'Annex 1 LV, HV and UMS charges'!$A$13:$A$44,0)),IF(INDEX('Annex 4 LDNO charges'!$B$12:$B$202,MATCH($A64,'Annex 4 LDNO charges'!$A$12:$A$202,0))=0,"",INDEX('Annex 4 LDNO charges'!$B$12:$B$202,MATCH($A64,'Annex 4 LDNO charges'!$A$12:$A$202,0)))) -> E20 | C64: =IFERROR(INDEX('Annex 1 LV, HV and UMS charges'!$C$13:$C$44,MATCH($A64,'Annex 1 LV, HV and UMS charges'!$A$13:$A$44,0)),INDEX('Annex 4 LDNO charges'!$C$12:$C$202,MATCH($A64,'Annex 4 LDNO charges'!$A$12:$A$202,0))) -> 0 | E64: 0
A65: LDNO HVplus: LV Site Specific Band 1 | B65: =IFERROR(INDEX('Annex 1 LV, HV and UMS charges'!$B$13:$B$44,MATCH($A65,'Annex 1 LV, HV and UMS charges'!$A$13:$A$44,0)),IF(INDEX('Annex 4 LDNO charges'!$B$12:$B$202,MATCH($A65,'Annex 4 LDNO charges'!$A$12:$A$202,0))=0,"",INDEX('Annex 4 LDNO charges'!$B$12:$B$202,MATCH($A65,'Annex 4 LDNO charges'!$A$12:$A$202,0)))) -> E21 | C65: =IFERROR(INDEX('Annex 1 LV, HV and UMS charges'!$C$13:$C$44,MATCH($A65,'Annex 1 LV, HV and UMS charges'!$A$13:$A$44,0)),INDEX('Annex 4 LDNO charges'!$C$12:$C$202,MATCH($A65,'Annex 4 LDNO charges'!$A$12:$A$202,0))) -> 0 | E65: 0
A66: LDNO HVplus: LV Site Specific Band 2 | B66: =IFERROR(INDEX('Annex 1 LV, HV and UMS charges'!$B$13:$B$44,MATCH($A66,'Annex 1 LV, HV and UMS charges'!$A$13:$A$44,0)),IF(INDEX('Annex 4 LDNO charges'!$B$12:$B$202,MATCH($A66,'Annex 4 LDNO charges'!$A$12:$A$202,0))=0,"",INDEX('Annex 4 LDNO charges'!$B$12:$B$202,MATCH($A66,'Annex 4 LDNO charges'!$A$12:$A$202,0)))) -> E22 | C66: =IFERROR(INDEX('Annex 1 LV, HV and UMS charges'!$C$13:$C$44,MATCH($A66,'Annex 1 LV, HV and UMS charges'!$A$13:$A$44,0)),INDEX('Annex 4 LDNO charges'!$C$12:$C$202,MATCH($A66,'Annex 4 LDNO charges'!$A$12:$A$202,0))) -> 0 | E66: 0
A67: LDNO HVplus: LV Site Specific Band 3 | B67: =IFERROR(INDEX('Annex 1 LV, HV and UMS charges'!$B$13:$B$44,MATCH($A67,'Annex 1 LV, HV and UMS charges'!$A$13:$A$44,0)),IF(INDEX('Annex 4 LDNO charges'!$B$12:$B$202,MATCH($A67,'Annex 4 LDNO charges'!$A$12:$A$202,0))=0,"",INDEX('Annex 4 LDNO charges'!$B$12:$B$202,MATCH($A67,'Annex 4 LDNO charges'!$A$12:$A$202,0)))) -> E23 | C67: =IFERROR(INDEX('Annex 1 LV, HV and UMS charges'!$C$13:$C$44,MATCH($A67,'Annex 1 LV, HV and UMS charges'!$A$13:$A$44,0)),INDEX('Annex 4 LDNO charges'!$C$12:$C$202,MATCH($A67,'Annex 4 LDNO charges'!$A$12:$A$202,0))) -> 0 | E67: 0
A68: LDNO HVplus: LV Site Specific Band 4 | B68: =IFERROR(INDEX('Annex 1 LV, HV and UMS charges'!$B$13:$B$44,MATCH($A68,'Annex 1 LV, HV and UMS charges'!$A$13:$A$44,0)),IF(INDEX('Annex 4 LDNO charges'!$B$12:$B$202,MATCH($A68,'Annex 4 LDNO charges'!$A$12:$A$202,0))=0,"",INDEX('Annex 4 LDNO charges'!$B$12:$B$202,MATCH($A68,'Annex 4 LDNO charges'!$A$12:$A$202,0)))) -> E24 | C68: =IFERROR(INDEX('Annex 1 LV, HV and UMS charges'!$C$13:$C$44,MATCH($A68,'Annex 1 LV, HV and UMS charges'!$A$13:$A$44,0)),INDEX('Annex 4 LDNO charges'!$C$12:$C$202,MATCH($A68,'Annex 4 LDNO charges'!$A$12:$A$202,0))) -> 0 | E68: 0
A69: LDNO HVplus: LV Sub Site Specific No Residual | B69: =IFERROR(INDEX('Annex 1 LV, HV and UMS charges'!$B$13:$B$44,MATCH($A69,'Annex 1 LV, HV and UMS charges'!$A$13:$A$44,0)),IF(INDEX('Annex 4 LDNO charges'!$B$12:$B$202,MATCH($A69,'Annex 4 LDNO charges'!$A$12:$A$202,0))=0,"",INDEX('Annex 4 LDNO charges'!$B$12:$B$202,MATCH($A69,'Annex 4 LDNO charges'!$A$12:$A$202,0)))) -> J20 | C69: =IFERROR(INDEX('Annex 1 LV, HV and UMS charges'!$C$13:$C$44,MATCH($A69,'Annex 1 LV, HV and UMS charges'!$A$13:$A$44,0)),INDEX('Annex 4 LDNO charges'!$C$12:$C$202,MATCH($A69,'Annex 4 LDNO charges'!$A$12:$A$202,0))) -> 0 | E69: 0
A70: LDNO HVplus: LV Sub Site Specific Band 1 | B70: =IFERROR(INDEX('Annex 1 LV, HV and UMS charges'!$B$13:$B$44,MATCH($A70,'Annex 1 LV, HV and UMS charges'!$A$13:$A$44,0)),IF(INDEX('Annex 4 LDNO charges'!$B$12:$B$202,MATCH($A70,'Annex 4 LDNO charges'!$A$12:$A$202,0))=0,"",INDEX('Annex 4 LDNO charges'!$B$12:$B$202,MATCH($A70,'Annex 4 LDNO charges'!$A$12:$A$202,0)))) -> J21 | C70: =IFERROR(INDEX('Annex 1 LV, HV and UMS charges'!$C$13:$C$44,MATCH($A70,'Annex 1 LV, HV and UMS charges'!$A$13:$A$44,0)),INDEX('Annex 4 LDNO charges'!$C$12:$C$202,MATCH($A70,'Annex 4 LDNO charges'!$A$12:$A$202,0))) -> 0 | E70: 0
... A78: LDNO HVplus: HV Site Specific Band 4 | B78: =IFERROR(INDEX('Annex 1 LV, HV and UMS charges'!$B$13:$B$44,MATCH($A78,'Annex 1 LV, HV and UMS charges'!$A$13:$A$44,0)),IF(INDEX('Annex 4 LDNO charges'!$B$12:$B$202,MATCH($A78,'Annex 4 LDNO charges'!$A$12:$A$202,0))=0,"",INDEX('Annex 4 LDNO charges'!$B$12:$B$202,MATCH($A78,'Annex 4 LDNO charges'!$A$12:$A$202,0)))) -> K24 | C78: =IFERROR(INDEX('Annex 1 LV, HV and UMS charges'!$C$13:$C$44,MATCH($A78,'Annex 1 LV, HV and UMS charges'!$A$13:$A$44,0)),INDEX('Annex 4 LDNO charges'!$C$12:$C$202,MATCH($A78,'Annex 4 LDNO charges'!$A$12:$A$202,0))) -> 0 | E78: 0
A79: LDNO EHV: Domestic Aggregated or CT with Residual | B79: =IFERROR(INDEX('Annex 1 LV, HV and UMS charges'!$B$13:$B$44,MATCH($A79,'Annex 1 LV, HV and UMS charges'!$A$13:$A$44,0)),IF(INDEX('Annex 4 LDNO charges'!$B$12:$B$202,MATCH($A79,'Annex 4 LDNO charges'!$A$12:$A$202,0))=0,"",INDEX('Annex 4 LDNO charges'!$B$12:$B$202,MATCH($A79,'Annex 4 LDNO charges'!$A$12:$A$202,0)))) -> A30 | C79: =IFERROR(INDEX('Annex 1 LV, HV and UMS charges'!$C$13:$C$44,MATCH($A79,'Annex 1 LV, HV and UMS charges'!$A$13:$A$44,0)),INDEX('Annex 4 LDNO charges'!$C$12:$C$202,MATCH($A79,'Annex 4 LDNO charges'!$A$12:$A$202,0))) -> 0, 1, 2 | D79: 0 | E79: 0
A80: LDNO EHV: Non-Domestic Aggregated or CT No Residual | B80: =IFERROR(INDEX('Annex 1 LV, HV and UMS charges'!$B$13:$B$44,MATCH($A80,'Annex 1 LV, HV and UMS charges'!$A$13:$A$44,0)),IF(INDEX('Annex 4 LDNO charges'!$B$12:$B$202,MATCH($A80,'Annex 4 LDNO charges'!$A$12:$A$202,0))=0,"",INDEX('Annex 4 LDNO charges'!$B$12:$B$202,MATCH($A80,'Annex 4 LDNO charges'!$A$12:$A$202,0)))) -> C30 | C80: =IFERROR(INDEX('Annex 1 LV, HV and UMS charges'!$C$13:$C$44,MATCH($A80,'Annex 1 LV, HV and UMS charges'!$A$13:$A$44,0)),INDEX('Annex 4 LDNO charges'!$C$12:$C$202,MATCH($A80,'Annex 4 LDNO charges'!$A$12:$A$202,0))) -> 0, 3, 4, 5-8 | E80: 0
A81: LDNO EHV: Non-Domestic Aggregated or CT Band 1 | B81: =IFERROR(INDEX('Annex 1 LV, HV and UMS charges'!$B$13:$B$44,MATCH($A81,'Annex 1 LV, HV and UMS charges'!$A$13:$A$44,0)),IF(INDEX('Annex 4 LDNO charges'!$B$12:$B$202,MATCH($A81,'Annex 4 LDNO charges'!$A$12:$A$202,0))=0,"",INDEX('Annex 4 LDNO charges'!$B$12:$B$202,MATCH($A81,'Annex 4 LDNO charges'!$A$12:$A$202,0)))) -> C31 | C81: =IFERROR(INDEX('Annex 1 LV, HV and UMS charges'!$C$13:$C$44,MATCH($A81,'Annex 1 LV, HV and UMS charges'!$A$13:$A$44,0)),INDEX('Annex 4 LDNO charges'!$C$12:$C$202,MATCH($A81,'Annex 4 LDNO charges'!$A$12:$A$202,0))) -> 0, 3, 4, 5-8 | E81: 0
A82: LDNO EHV: Non-Domestic Aggregated or CT Band 2 | B82: =IFERROR(INDEX('Annex 1 LV, HV and UMS charges'!$B$13:$B$44,MATCH($A82,'Annex 1 LV, HV and UMS charges'!$A$13:$A$44,0)),IF(INDEX('Annex 4 LDNO charges'!$B$12:$B$202,MATCH($A82,'Annex 4 LDNO charges'!$A$12:$A$202,0))=0,"",INDEX('Annex 4 LDNO charges'!$B$12:$B$202,MATCH($A82,'Annex 4 LDNO charges'!$A$12:$A$202,0)))) -> C32 | C82: =IFERROR(INDEX('Annex 1 LV, HV and UMS charges'!$C$13:$C$44,MATCH($A82,'Annex 1 LV, HV and UMS charges'!$A$13:$A$44,0)),INDEX('Annex 4 LDNO charges'!$C$12:$C$202,MATCH($A82,'Annex 4 LDNO charges'!$A$12:$A$202,0))) -> 0, 3, 4, 5-8 | E82: 0
A83: LDNO EHV: Non-Domestic Aggregated or CT Band 3 | B83: =IFERROR(INDEX('Annex 1 LV, HV and UMS charges'!$B$13:$B$44,MATCH($A83,'Annex 1 LV, HV and UMS charges'!$A$13:$A$44,0)),IF(INDEX('Annex 4 LDNO charges'!$B$12:$B$202,MATCH($A83,'Annex 4 LDNO charges'!$A$12:$A$202,0))=0,"",INDEX('Annex 4 LDNO charges'!$B$12:$B$202,MATCH($A83,'Annex 4 LDNO charges'!$A$12:$A$202,0)))) -> C33 | C83: =IFERROR(INDEX('Annex 1 LV, HV and UMS charges'!$C$13:$C$44,MATCH($A83,'Annex 1 LV, HV and UMS charges'!$A$13:$A$44,0)),INDEX('Annex 4 LDNO charges'!$C$12:$C$202,MATCH($A83,'Annex 4 LDNO charges'!$A$12:$A$202,0))) -> 0, 3, 4, 5-8 | E83: 0
A84: LDNO EHV: Non-Domestic Aggregated or CT Band 4 | B84: =IFERROR(INDEX('Annex 1 LV, HV and UMS charges'!$B$13:$B$44,MATCH($A84,'Annex 1 LV, HV and UMS charges'!$A$13:$A$44,0)),IF(INDEX('Annex 4 LDNO charges'!$B$12:$B$202,MATCH($A84,'Annex 4 LDNO charges'!$A$12:$A$202,0))=0,"",INDEX('Annex 4 LDNO charges'!$B$12:$B$202,MATCH($A84,'Annex 4 LDNO charges'!$A$12:$A$202,0)))) -> C34 | C84: =IFERROR(INDEX('Annex 1 LV, HV and UMS charges'!$C$13:$C$44,MATCH($A84,'Annex 1 LV, HV and UMS charges'!$A$13:$A$44,0)),INDEX('Annex 4 LDNO charges'!$C$12:$C$202,MATCH($A84,'Annex 4 LDNO charges'!$A$12:$A$202,0))) -> 0, 3, 4, 5-8 | E84: 0
A85: LDNO EHV: LV Site Specific No Residual | B85: =IFERROR(INDEX('Annex 1 LV, HV and UMS charges'!$B$13:$B$44,MATCH($A85,'Annex 1 LV, HV and UMS charges'!$A$13:$A$44,0)),IF(INDEX('Annex 4 LDNO charges'!$B$12:$B$202,MATCH($A85,'Annex 4 LDNO charges'!$A$12:$A$202,0))=0,"",INDEX('Annex 4 LDNO charges'!$B$12:$B$202,MATCH($A85,'Annex 4 LDNO charges'!$A$12:$A$202,0)))) -> E30 | C85: =IFERROR(INDEX('Annex 1 LV, HV and UMS charges'!$C$13:$C$44,MATCH($A85,'Annex 1 LV, HV and UMS charges'!$A$13:$A$44,0)),INDEX('Annex 4 LDNO charges'!$C$12:$C$202,MATCH($A85,'Annex 4 LDNO charges'!$A$12:$A$202,0))) -> 0 | E85: 0
A86: LDNO EHV: LV Site Specific Band 1 | B86: =IFERROR(INDEX('Annex 1 LV, HV and UMS charges'!$B$13:$B$44,MATCH($A86,'Annex 1 LV, HV and UMS charges'!$A$13:$A$44,0)),IF(INDEX('Annex 4 LDNO charges'!$B$12:$B$202,MATCH($A86,'Annex 4 LDNO charges'!$A$12:$A$202,0))=0,"",INDEX('Annex 4 LDNO charges'!$B$12:$B$202,MATCH($A86,'Annex 4 LDNO charges'!$A$12:$A$202,0)))) -> E31 | C86: =IFERROR(INDEX('Annex 1 LV, HV and UMS charges'!$C$13:$C$44,MATCH($A86,'Annex 1 LV, HV and UMS charges'!$A$13:$A$44,0)),INDEX('Annex 4 LDNO charges'!$C$12:$C$202,MATCH($A86,'Annex 4 LDNO charges'!$A$12:$A$202,0))) -> 0 | E86: 0
A87: LDNO EHV: LV Site Specific Band 2 | B87: =IFERROR(INDEX('Annex 1 LV, HV and UMS charges'!$B$13:$B$44,MATCH($A87,'Annex 1 LV, HV and UMS charges'!$A$13:$A$44,0)),IF(INDEX('Annex 4 LDNO charges'!$B$12:$B$202,MATCH($A87,'Annex 4 LDNO charges'!$A$12:$A$202,0))=0,"",INDEX('Annex 4 LDNO charges'!$B$12:$B$202,MATCH($A87,'Annex 4 LDNO charges'!$A$12:$A$202,0)))) -> E32 | C87: =IFERROR(INDEX('Annex 1 LV, HV and UMS charges'!$C$13:$C$44,MATCH($A87,'Annex 1 LV, HV and UMS charges'!$A$13:$A$44,0)),INDEX('Annex 4 LDNO charges'!$C$12:$C$202,MATCH($A87,'Annex 4 LDNO charges'!$A$12:$A$202,0))) -> 0 | E87: 0
A88: LDNO EHV: LV Site Specific Band 3 | B88: =IFERROR(INDEX('Annex 1 LV, HV and UMS charges'!$B$13:$B$44,MATCH($A88,'Annex 1 LV, HV and UMS charges'!$A$13:$A$44,0)),IF(INDEX('Annex 4 LDNO charges'!$B$12:$B$202,MATCH($A88,'Annex 4 LDNO charges'!$A$12:$A$202,0))=0,"",INDEX('Annex 4 LDNO charges'!$B$12:$B$202,MATCH($A88,'Annex 4 LDNO charges'!$A$12:$A$202,0)))) -> E33 | C88: =IFERROR(INDEX('Annex 1 LV, HV and UMS charges'!$C$13:$C$44,MATCH($A88,'Annex 1 LV, HV and UMS charges'!$A$13:$A$44,0)),INDEX('Annex 4 LDNO charges'!$C$12:$C$202,MATCH($A88,'Annex 4 LDNO charges'!$A$12:$A$202,0))) -> 0 | E88: 0
A89: LDNO EHV: LV Site Specific Band 4 | B89: =IFERROR(INDEX('Annex 1 LV, HV and UMS charges'!$B$13:$B$44,MATCH($A89,'Annex 1 LV, HV and UMS charges'!$A$13:$A$44,0)),IF(INDEX('Annex 4 LDNO charges'!$B$12:$B$202,MATCH($A89,'Annex 4 LDNO charges'!$A$12:$A$202,0))=0,"",INDEX('Annex 4 LDNO charges'!$B$12:$B$202,MATCH($A89,'Annex 4 LDNO charges'!$A$12:$A$202,0)))) -> E34 | C89: =IFERROR(INDEX('Annex 1 LV, HV and UMS charges'!$C$13:$C$44,MATCH($A89,'Annex 1 LV, HV and UMS charges'!$A$13:$A$44,0)),INDEX('Annex 4 LDNO charges'!$C$12:$C$202,MATCH($A89,'Annex 4 LDNO charges'!$A$12:$A$202,0))) -> 0 | E89: 0
A90: LDNO EHV: LV Sub Site Specific No Residual | B90: =IFERROR(INDEX('Annex 1 LV, HV and UMS charges'!$B$13:$B$44,MATCH($A90,'Annex 1 LV, HV and UMS charges'!$A$13:$A$44,0)),IF(INDEX('Annex 4 LDNO charges'!$B$12:$B$202,MATCH($A90,'Annex 4 LDNO charges'!$A$12:$A$202,0))=0,"",INDEX('Annex 4 LDNO charges'!$B$12:$B$202,MATCH($A90,'Annex 4 LDNO charges'!$A$12:$A$202,0)))) -> J30 | C90: =IFERROR(INDEX('Annex 1 LV, HV and UMS charges'!$C$13:$C$44,MATCH($A90,'Annex 1 LV, HV and UMS charges'!$A$13:$A$44,0)),INDEX('Annex 4 LDNO charges'!$C$12:$C$202,MATCH($A90,'Annex 4 LDNO charges'!$A$12:$A$202,0))) -> 0 | E90: 0
A91: LDNO EHV: LV Sub Site Specific Band 1 | B91: =IFERROR(INDEX('Annex 1 LV, HV and UMS charges'!$B$13:$B$44,MATCH($A91,'Annex 1 LV, HV and UMS charges'!$A$13:$A$44,0)),IF(INDEX('Annex 4 LDNO charges'!$B$12:$B$202,MATCH($A91,'Annex 4 LDNO charges'!$A$12:$A$202,0))=0,"",INDEX('Annex 4 LDNO charges'!$B$12:$B$202,MATCH($A91,'Annex 4 LDNO charges'!$A$12:$A$202,0)))) -> J31 | C91: =IFERROR(INDEX('Annex 1 LV, HV and UMS charges'!$C$13:$C$44,MATCH($A91,'Annex 1 LV, HV and UMS charges'!$A$13:$A$44,0)),INDEX('Annex 4 LDNO charges'!$C$12:$C$202,MATCH($A91,'Annex 4 LDNO charges'!$A$12:$A$202,0))) -> 0 | E91: 0
... A99: LDNO EHV: HV Site Specific Band 4 | B99: =IFERROR(INDEX('Annex 1 LV, HV and UMS charges'!$B$13:$B$44,MATCH($A99,'Annex 1 LV, HV and UMS charges'!$A$13:$A$44,0)),IF(INDEX('Annex 4 LDNO charges'!$B$12:$B$202,MATCH($A99,'Annex 4 LDNO charges'!$A$12:$A$202,0))=0,"",INDEX('Annex 4 LDNO charges'!$B$12:$B$202,MATCH($A99,'Annex 4 LDNO charges'!$A$12:$A$202,0)))) -> K34 | C99: =IFERROR(INDEX('Annex 1 LV, HV and UMS charges'!$C$13:$C$44,MATCH($A99,'Annex 1 LV, HV and UMS charges'!$A$13:$A$44,0)),INDEX('Annex 4 LDNO charges'!$C$12:$C$202,MATCH($A99,'Annex 4 LDNO charges'!$A$12:$A$202,0))) -> 0 | E99: 0
A100: LDNO 132kV/EHV: Domestic Aggregated or CT with Residual | B100: =IFERROR(INDEX('Annex 1 LV, HV and UMS charges'!$B$13:$B$44,MATCH($A100,'Annex 1 LV, HV and UMS charges'!$A$13:$A$44,0)),IF(INDEX('Annex 4 LDNO charges'!$B$12:$B$202,MATCH($A100,'Annex 4 LDNO charges'!$A$12:$A$202,0))=0,"",INDEX('Annex 4 LDNO charges'!$B$12:$B$202,MATCH($A100,'Annex 4 LDNO charges'!$A$12:$A$202,0)))) -> A40 | C100: =IFERROR(INDEX('Annex 1 LV, HV and UMS charges'!$C$13:$C$44,MATCH($A100,'Annex 1 LV, HV and UMS charges'!$A$13:$A$44,0)),INDEX('Annex 4 LDNO charges'!$C$12:$C$202,MATCH($A100,'Annex 4 LDNO charges'!$A$12:$A$202,0))) -> 0, 1, 2 | D100: 0 | E100: 0
A101: LDNO 132kV/EHV: Non-Domestic Aggregated or CT No Residual | B101: =IFERROR(INDEX('Annex 1 LV, HV and UMS charges'!$B$13:$B$44,MATCH($A101,'Annex 1 LV, HV and UMS charges'!$A$13:$A$44,0)),IF(INDEX('Annex 4 LDNO charges'!$B$12:$B$202,MATCH($A101,'Annex 4 LDNO charges'!$A$12:$A$202,0))=0,"",INDEX('Annex 4 LDNO charges'!$B$12:$B$202,MATCH($A101,'Annex 4 LDNO charges'!$A$12:$A$202,0)))) -> C40 | C101: =IFERROR(INDEX('Annex 1 LV, HV and UMS charges'!$C$13:$C$44,MATCH($A101,'Annex 1 LV, HV and UMS charges'!$A$13:$A$44,0)),INDEX('Annex 4 LDNO charges'!$C$12:$C$202,MATCH($A101,'Annex 4 LDNO charges'!$A$12:$A$202,0))) -> 0, 3, 4, 5-8 | E101: 0
A102: LDNO 132kV/EHV: Non-Domestic Aggregated or CT Band 1 | B102: =IFERROR(INDEX('Annex 1 LV, HV and UMS charges'!$B$13:$B$44,MATCH($A102,'Annex 1 LV, HV and UMS charges'!$A$13:$A$44,0)),IF(INDEX('Annex 4 LDNO charges'!$B$12:$B$202,MATCH($A102,'Annex 4 LDNO charges'!$A$12:$A$202,0))=0,"",INDEX('Annex 4 LDNO charges'!$B$12:$B$202,MATCH($A102,'Annex 4 LDNO charges'!$A$12:$A$202,0)))) -> C41 | C102: =IFERROR(INDEX('Annex 1 LV, HV and UMS charges'!$C$13:$C$44,MATCH($A102,'Annex 1 LV, HV and UMS charges'!$A$13:$A$44,0)),INDEX('Annex 4 LDNO charges'!$C$12:$C$202,MATCH($A102,'Annex 4 LDNO charges'!$A$12:$A$202,0))) -> 0, 3, 4, 5-8 | E102: 0
A103: LDNO 132kV/EHV: Non-Domestic Aggregated or CT Band 2 | B103: =IFERROR(INDEX('Annex 1 LV, HV and UMS charges'!$B$13:$B$44,MATCH($A103,'Annex 1 LV, HV and UMS charges'!$A$13:$A$44,0)),IF(INDEX('Annex 4 LDNO charges'!$B$12:$B$202,MATCH($A103,'Annex 4 LDNO charges'!$A$12:$A$202,0))=0,"",INDEX('Annex 4 LDNO charges'!$B$12:$B$202,MATCH($A103,'Annex 4 LDNO charges'!$A$12:$A$202,0)))) -> C42 | C103: =IFERROR(INDEX('Annex 1 LV, HV and UMS charges'!$C$13:$C$44,MATCH($A103,'Annex 1 LV, HV and UMS charges'!$A$13:$A$44,0)),INDEX('Annex 4 LDNO charges'!$C$12:$C$202,MATCH($A103,'Annex 4 LDNO charges'!$A$12:$A$202,0))) -> 0, 3, 4, 5-8 | E103: 0
A104: LDNO 132kV/EHV: Non-Domestic Aggregated or CT Band 3 | B104: =IFERROR(INDEX('Annex 1 LV, HV and UMS charges'!$B$13:$B$44,MATCH($A104,'Annex 1 LV, HV and UMS charges'!$A$13:$A$44,0)),IF(INDEX('Annex 4 LDNO charges'!$B$12:$B$202,MATCH($A104,'Annex 4 LDNO charges'!$A$12:$A$202,0))=0,"",INDEX('Annex 4 LDNO charges'!$B$12:$B$202,MATCH($A104,'Annex 4 LDNO charges'!$A$12:$A$202,0)))) -> C43 | C104: =IFERROR(INDEX('Annex 1 LV, HV and UMS charges'!$C$13:$C$44,MATCH($A104,'Annex 1 LV, HV and UMS charges'!$A$13:$A$44,0)),INDEX('Annex 4 LDNO charges'!$C$12:$C$202,MATCH($A104,'Annex 4 LDNO charges'!$A$12:$A$202,0))) -> 0, 3, 4, 5-8 | E104: 0
A105: LDNO 132kV/EHV: Non-Domestic Aggregated or CT Band 4 | B105: =IFERROR(INDEX('Annex 1 LV, HV and UMS charges'!$B$13:$B$44,MATCH($A105,'Annex 1 LV, HV and UMS charges'!$A$13:$A$44,0)),IF(INDEX('Annex 4 LDNO charges'!$B$12:$B$202,MATCH($A105,'Annex 4 LDNO charges'!$A$12:$A$202,0))=0,"",INDEX('Annex 4 LDNO charges'!$B$12:$B$202,MATCH($A105,'Annex 4 LDNO charges'!$A$12:$A$202,0)))) -> C44 | C105: =IFERROR(INDEX('Annex 1 LV, HV and UMS charges'!$C$13:$C$44,MATCH($A105,'Annex 1 LV, HV and UMS charges'!$A$13:$A$44,0)),INDEX('Annex 4 LDNO charges'!$C$12:$C$202,MATCH($A105,'Annex 4 LDNO charges'!$A$12:$A$202,0))) -> 0, 3, 4, 5-8 | E105: 0
A106: LDNO 132kV/EHV: LV Site Specific No Residual | B106: =IFERROR(INDEX('Annex 1 LV, HV and UMS charges'!$B$13:$B$44,MATCH($A106,'Annex 1 LV, HV and UMS charges'!$A$13:$A$44,0)),IF(INDEX('Annex 4 LDNO charges'!$B$12:$B$202,MATCH($A106,'Annex 4 LDNO charges'!$A$12:$A$202,0))=0,"",INDEX('Annex 4 LDNO charges'!$B$12:$B$202,MATCH($A106,'Annex 4 LDNO charges'!$A$12:$A$202,0)))) -> E40 | C106: =IFERROR(INDEX('Annex 1 LV, HV and UMS charges'!$C$13:$C$44,MATCH($A106,'Annex 1 LV, HV and UMS charges'!$A$13:$A$44,0)),INDEX('Annex 4 LDNO charges'!$C$12:$C$202,MATCH($A106,'Annex 4 LDNO charges'!$A$12:$A$202,0))) -> 0 | E106: 0
A107: LDNO 132kV/EHV: LV Site Specific Band 1 | B107: =IFERROR(INDEX('Annex 1 LV, HV and UMS charges'!$B$13:$B$44,MATCH($A107,'Annex 1 LV, HV and UMS charges'!$A$13:$A$44,0)),IF(INDEX('Annex 4 LDNO charges'!$B$12:$B$202,MATCH($A107,'Annex 4 LDNO charges'!$A$12:$A$202,0))=0,"",INDEX('Annex 4 LDNO charges'!$B$12:$B$202,MATCH($A107,'Annex 4 LDNO charges'!$A$12:$A$202,0)))) -> E41 | C107: =IFERROR(INDEX('Annex 1 LV, HV and UMS charges'!$C$13:$C$44,MATCH($A107,'Annex 1 LV, HV and UMS charges'!$A$13:$A$44,0)),INDEX('Annex 4 LDNO charges'!$C$12:$C$202,MATCH($A107,'Annex 4 LDNO charges'!$A$12:$A$202,0))) -> 0 | E107: 0
A108: LDNO 132kV/EHV: LV Site Specific Band 2 | B108: =IFERROR(INDEX('Annex 1 LV, HV and UMS charges'!$B$13:$B$44,MATCH($A108,'Annex 1 LV, HV and UMS charges'!$A$13:$A$44,0)),IF(INDEX('Annex 4 LDNO charges'!$B$12:$B$202,MATCH($A108,'Annex 4 LDNO charges'!$A$12:$A$202,0))=0,"",INDEX('Annex 4 LDNO charges'!$B$12:$B$202,MATCH($A108,'Annex 4 LDNO charges'!$A$12:$A$202,0)))) -> E42 | C108: =IFERROR(INDEX('Annex 1 LV, HV and UMS charges'!$C$13:$C$44,MATCH($A108,'Annex 1 LV, HV and UMS charges'!$A$13:$A$44,0)),INDEX('Annex 4 LDNO charges'!$C$12:$C$202,MATCH($A108,'Annex 4 LDNO charges'!$A$12:$A$202,0))) -> 0 | E108: 0
A109: LDNO 132kV/EHV: LV Site Specific Band 3 | B109: =IFERROR(INDEX('Annex 1 LV, HV and UMS charges'!$B$13:$B$44,MATCH($A109,'Annex 1 LV, HV and UMS charges'!$A$13:$A$44,0)),IF(INDEX('Annex 4 LDNO charges'!$B$12:$B$202,MATCH($A109,'Annex 4 LDNO charges'!$A$12:$A$202,0))=0,"",INDEX('Annex 4 LDNO charges'!$B$12:$B$202,MATCH($A109,'Annex 4 LDNO charges'!$A$12:$A$202,0)))) -> E43 | C109: =IFERROR(INDEX('Annex 1 LV, HV and UMS charges'!$C$13:$C$44,MATCH($A109,'Annex 1 LV, HV and UMS charges'!$A$13:$A$44,0)),INDEX('Annex 4 LDNO charges'!$C$12:$C$202,MATCH($A109,'Annex 4 LDNO charges'!$A$12:$A$202,0))) -> 0 | E109: 0
A110: LDNO 132kV/EHV: LV Site Specific Band 4 | B110: =IFERROR(INDEX('Annex 1 LV, HV and UMS charges'!$B$13:$B$44,MATCH($A110,'Annex 1 LV, HV and UMS charges'!$A$13:$A$44,0)),IF(INDEX('Annex 4 LDNO charges'!$B$12:$B$202,MATCH($A110,'Annex 4 LDNO charges'!$A$12:$A$202,0))=0,"",INDEX('Annex 4 LDNO charges'!$B$12:$B$202,MATCH($A110,'Annex 4 LDNO charges'!$A$12:$A$202,0)))) -> E44 | C110: =IFERROR(INDEX('Annex 1 LV, HV and UMS charges'!$C$13:$C$44,MATCH($A110,'Annex 1 LV, HV and UMS charges'!$A$13:$A$44,0)),INDEX('Annex 4 LDNO charges'!$C$12:$C$202,MATCH($A110,'Annex 4 LDNO charges'!$A$12:$A$202,0))) -> 0 | E110: 0
A111: LDNO 132kV/EHV: LV Sub Site Specific No Residual | B111: =IFERROR(INDEX('Annex 1 LV, HV and UMS charges'!$B$13:$B$44,MATCH($A111,'Annex 1 LV, HV and UMS charges'!$A$13:$A$44,0)),IF(INDEX('Annex 4 LDNO charges'!$B$12:$B$202,MATCH($A111,'Annex 4 LDNO charges'!$A$12:$A$202,0))=0,"",INDEX('Annex 4 LDNO charges'!$B$12:$B$202,MATCH($A111,'Annex 4 LDNO charges'!$A$12:$A$202,0)))) -> J40 | C111: =IFERROR(INDEX('Annex 1 LV, HV and UMS charges'!$C$13:$C$44,MATCH($A111,'Annex 1 LV, HV and UMS charges'!$A$13:$A$44,0)),INDEX('Annex 4 LDNO charges'!$C$12:$C$202,MATCH($A111,'Annex 4 LDNO charges'!$A$12:$A$202,0))) -> 0 | E111: 0
A112: LDNO 132kV/EHV: LV Sub Site Specific Band 1 | B112: =IFERROR(INDEX('Annex 1 LV, HV and UMS charges'!$B$13:$B$44,MATCH($A112,'Annex 1 LV, HV and UMS charges'!$A$13:$A$44,0)),IF(INDEX('Annex 4 LDNO charges'!$B$12:$B$202,MATCH($A112,'Annex 4 LDNO charges'!$A$12:$A$202,0))=0,"",INDEX('Annex 4 LDNO charges'!$B$12:$B$202,MATCH($A112,'Annex 4 LDNO charges'!$A$12:$A$202,0)))) -> J41 | C112: =IFERROR(INDEX('Annex 1 LV, HV and UMS charges'!$C$13:$C$44,MATCH($A112,'Annex 1 LV, HV and UMS charges'!$A$13:$A$44,0)),INDEX('Annex 4 LDNO charges'!$C$12:$C$202,MATCH($A112,'Annex 4 LDNO charges'!$A$12:$A$202,0))) -> 0 | E112: 0
... A120: LDNO 132kV/EHV: HV Site Specific Band 4 | B120: =IFERROR(INDEX('Annex 1 LV, HV and UMS charges'!$B$13:$B$44,MATCH($A120,'Annex 1 LV, HV and UMS charges'!$A$13:$A$44,0)),IF(INDEX('Annex 4 LDNO charges'!$B$12:$B$202,MATCH($A120,'Annex 4 LDNO charges'!$A$12:$A$202,0))=0,"",INDEX('Annex 4 LDNO charges'!$B$12:$B$202,MATCH($A120,'Annex 4 LDNO charges'!$A$12:$A$202,0)))) -> K44 | C120: =IFERROR(INDEX('Annex 1 LV, HV and UMS charges'!$C$13:$C$44,MATCH($A120,'Annex 1 LV, HV and UMS charges'!$A$13:$A$44,0)),INDEX('Annex 4 LDNO charges'!$C$12:$C$202,MATCH($A120,'Annex 4 LDNO charges'!$A$12:$A$202,0))) -> 0 | E120: 0
A121: LDNO 132kV: Domestic Aggregated or CT with Residual | B121: =IFERROR(INDEX('Annex 1 LV, HV and UMS charges'!$B$13:$B$44,MATCH($A121,'Annex 1 LV, HV and UMS charges'!$A$13:$A$44,0)),IF(INDEX('Annex 4 LDNO charges'!$B$12:$B$202,MATCH($A121,'Annex 4 LDNO charges'!$A$12:$A$202,0))=0,"",INDEX('Annex 4 LDNO charges'!$B$12:$B$202,MATCH($A121,'Annex 4 LDNO charges'!$A$12:$A$202,0)))) -> A50 | C121: =IFERROR(INDEX('Annex 1 LV, HV and UMS charges'!$C$13:$C$44,MATCH($A121,'Annex 1 LV, HV and UMS charges'!$A$13:$A$44,0)),INDEX('Annex 4 LDNO charges'!$C$12:$C$202,MATCH($A121,'Annex 4 LDNO charges'!$A$12:$A$202,0))) -> 0, 1, 2 | D121: 0 | E121: 0
A122: LDNO 132kV: Non-Domestic Aggregated or CT No Residual | B122: =IFERROR(INDEX('Annex 1 LV, HV and UMS charges'!$B$13:$B$44,MATCH($A122,'Annex 1 LV, HV and UMS charges'!$A$13:$A$44,0)),IF(INDEX('Annex 4 LDNO charges'!$B$12:$B$202,MATCH($A122,'Annex 4 LDNO charges'!$A$12:$A$202,0))=0,"",INDEX('Annex 4 LDNO charges'!$B$12:$B$202,MATCH($A122,'Annex 4 LDNO charges'!$A$12:$A$202,0)))) -> C50 | C122: =IFERROR(INDEX('Annex 1 LV, HV and UMS charges'!$C$13:$C$44,MATCH($A122,'Annex 1 LV, HV and UMS charges'!$A$13:$A$44,0)),INDEX('Annex 4 LDNO charges'!$C$12:$C$202,MATCH($A122,'Annex 4 LDNO charges'!$A$12:$A$202,0))) -> 0, 3, 4, 5-8 | E122: 0
A123: LDNO 132kV: Non-Domestic Aggregated or CT Band 1 | B123: =IFERROR(INDEX('Annex 1 LV, HV and UMS charges'!$B$13:$B$44,MATCH($A123,'Annex 1 LV, HV and UMS charges'!$A$13:$A$44,0)),IF(INDEX('Annex 4 LDNO charges'!$B$12:$B$202,MATCH($A123,'Annex 4 LDNO charges'!$A$12:$A$202,0))=0,"",INDEX('Annex 4 LDNO charges'!$B$12:$B$202,MATCH($A123,'Annex 4 LDNO charges'!$A$12:$A$202,0)))) -> C51 | C123: =IFERROR(INDEX('Annex 1 LV, HV and UMS charges'!$C$13:$C$44,MATCH($A123,'Annex 1 LV, HV and UMS charges'!$A$13:$A$44,0)),INDEX('Annex 4 LDNO charges'!$C$12:$C$202,MATCH($A123,'Annex 4 LDNO charges'!$A$12:$A$202,0))) -> 0, 3, 4, 5-8 | E123: 0
A124: LDNO 132kV: Non-Domestic Aggregated or CT Band 2 | B124: =IFERROR(INDEX('Annex 1 LV, HV and UMS charges'!$B$13:$B$44,MATCH($A124,'Annex 1 LV, HV and UMS charges'!$A$13:$A$44,0)),IF(INDEX('Annex 4 LDNO charges'!$B$12:$B$202,MATCH($A124,'Annex 4 LDNO charges'!$A$12:$A$202,0))=0,"",INDEX('Annex 4 LDNO charges'!$B$12:$B$202,MATCH($A124,'Annex 4 LDNO charges'!$A$12:$A$202,0)))) -> C52 | C124: =IFERROR(INDEX('Annex 1 LV, HV and UMS charges'!$C$13:$C$44,MATCH($A124,'Annex 1 LV, HV and UMS charges'!$A$13:$A$44,0)),INDEX('Annex 4 LDNO charges'!$C$12:$C$202,MATCH($A124,'Annex 4 LDNO charges'!$A$12:$A$202,0))) -> 0, 3, 4, 5-8 | E124: 0
A125: LDNO 132kV: Non-Domestic Aggregated or CT Band 3 | B125: =IFERROR(INDEX('Annex 1 LV, HV and UMS charges'!$B$13:$B$44,MATCH($A125,'Annex 1 LV, HV and UMS charges'!$A$13:$A$44,0)),IF(INDEX('Annex 4 LDNO charges'!$B$12:$B$202,MATCH($A125,'Annex 4 LDNO charges'!$A$12:$A$202,0))=0,"",INDEX('Annex 4 LDNO charges'!$B$12:$B$202,MATCH($A125,'Annex 4 LDNO charges'!$A$12:$A$202,0)))) -> C53 | C125: =IFERROR(INDEX('Annex 1 LV, HV and UMS charges'!$C$13:$C$44,MATCH($A125,'Annex 1 LV, HV and UMS charges'!$A$13:$A$44,0)),INDEX('Annex 4 LDNO charges'!$C$12:$C$202,MATCH($A125,'Annex 4 LDNO charges'!$A$12:$A$202,0))) -> 0, 3, 4, 5-8 | E125: 0
A126: LDNO 132kV: Non-Domestic Aggregated or CT Band 4 | B126: =IFERROR(INDEX('Annex 1 LV, HV and UMS charges'!$B$13:$B$44,MATCH($A126,'Annex 1 LV, HV and UMS charges'!$A$13:$A$44,0)),IF(INDEX('Annex 4 LDNO charges'!$B$12:$B$202,MATCH($A126,'Annex 4 LDNO charges'!$A$12:$A$202,0))=0,"",INDEX('Annex 4 LDNO charges'!$B$12:$B$202,MATCH($A126,'Annex 4 LDNO charges'!$A$12:$A$202,0)))) -> C54 | C126: =IFERROR(INDEX('Annex 1 LV, HV and UMS charges'!$C$13:$C$44,MATCH($A126,'Annex 1 LV, HV and UMS charges'!$A$13:$A$44,0)),INDEX('Annex 4 LDNO charges'!$C$12:$C$202,MATCH($A126,'Annex 4 LDNO charges'!$A$12:$A$202,0))) -> 0, 3, 4, 5-8 | E126: 0
A127: LDNO 132kV: LV Site Specific No Residual | B127: =IFERROR(INDEX('Annex 1 LV, HV and UMS charges'!$B$13:$B$44,MATCH($A127,'Annex 1 LV, HV and UMS charges'!$A$13:$A$44,0)),IF(INDEX('Annex 4 LDNO charges'!$B$12:$B$202,MATCH($A127,'Annex 4 LDNO charges'!$A$12:$A$202,0))=0,"",INDEX('Annex 4 LDNO charges'!$B$12:$B$202,MATCH($A127,'Annex 4 LDNO charges'!$A$12:$A$202,0)))) -> E50 | C127: =IFERROR(INDEX('Annex 1 LV, HV and UMS charges'!$C$13:$C$44,MATCH($A127,'Annex 1 LV, HV and UMS charges'!$A$13:$A$44,0)),INDEX('Annex 4 LDNO charges'!$C$12:$C$202,MATCH($A127,'Annex 4 LDNO charges'!$A$12:$A$202,0))) -> 0 | E127: 0
A128: LDNO 132kV: LV Site Specific Band 1 | B128: =IFERROR(INDEX('Annex 1 LV, HV and UMS charges'!$B$13:$B$44,MATCH($A128,'Annex 1 LV, HV and UMS charges'!$A$13:$A$44,0)),IF(INDEX('Annex 4 LDNO charges'!$B$12:$B$202,MATCH($A128,'Annex 4 LDNO charges'!$A$12:$A$202,0))=0,"",INDEX('Annex 4 LDNO charges'!$B$12:$B$202,MATCH($A128,'Annex 4 LDNO charges'!$A$12:$A$202,0)))) -> E51 | C128: =IFERROR(INDEX('Annex 1 LV, HV and UMS charges'!$C$13:$C$44,MATCH($A128,'Annex 1 LV, HV and UMS charges'!$A$13:$A$44,0)),INDEX('Annex 4 LDNO charges'!$C$12:$C$202,MATCH($A128,'Annex 4 LDNO charges'!$A$12:$A$202,0))) -> 0 | E128: 0
A129: LDNO 132kV: LV Site Specific Band 2 | B129: =IFERROR(INDEX('Annex 1 LV, HV and UMS charges'!$B$13:$B$44,MATCH($A129,'Annex 1 LV, HV and UMS charges'!$A$13:$A$44,0)),IF(INDEX('Annex 4 LDNO charges'!$B$12:$B$202,MATCH($A129,'Annex 4 LDNO charges'!$A$12:$A$202,0))=0,"",INDEX('Annex 4 LDNO charges'!$B$12:$B$202,MATCH($A129,'Annex 4 LDNO charges'!$A$12:$A$202,0)))) -> E52 | C129: =IFERROR(INDEX('Annex 1 LV, HV and UMS charges'!$C$13:$C$44,MATCH($A129,'Annex 1 LV, HV and UMS charges'!$A$13:$A$44,0)),INDEX('Annex 4 LDNO charges'!$C$12:$C$202,MATCH($A129,'Annex 4 LDNO charges'!$A$12:$A$202,0))) -> 0 | E129: 0
A130: LDNO 132kV: LV Site Specific Band 3 | B130: =IFERROR(INDEX('Annex 1 LV, HV and UMS charges'!$B$13:$B$44,MATCH($A130,'Annex 1 LV, HV and UMS charges'!$A$13:$A$44,0)),IF(INDEX('Annex 4 LDNO charges'!$B$12:$B$202,MATCH($A130,'Annex 4 LDNO charges'!$A$12:$A$202,0))=0,"",INDEX('Annex 4 LDNO charges'!$B$12:$B$202,MATCH($A130,'Annex 4 LDNO charges'!$A$12:$A$202,0)))) -> E53 | C130: =IFERROR(INDEX('Annex 1 LV, HV and UMS charges'!$C$13:$C$44,MATCH($A130,'Annex 1 LV, HV and UMS charges'!$A$13:$A$44,0)),INDEX('Annex 4 LDNO charges'!$C$12:$C$202,MATCH($A130,'Annex 4 LDNO charges'!$A$12:$A$202,0))) -> 0 | E130: 0
A131: LDNO 132kV: LV Site Specific Band 4 | B131: =IFERROR(INDEX('Annex 1 LV, HV and UMS charges'!$B$13:$B$44,MATCH($A131,'Annex 1 LV, HV and UMS charges'!$A$13:$A$44,0)),IF(INDEX('Annex 4 LDNO charges'!$B$12:$B$202,MATCH($A131,'Annex 4 LDNO charges'!$A$12:$A$202,0))=0,"",INDEX('Annex 4 LDNO charges'!$B$12:$B$202,MATCH($A131,'Annex 4 LDNO charges'!$A$12:$A$202,0)))) -> E54 | C131: =IFERROR(INDEX('Annex 1 LV, HV and UMS charges'!$C$13:$C$44,MATCH($A131,'Annex 1 LV, HV and UMS charges'!$A$13:$A$44,0)),INDEX('Annex 4 LDNO charges'!$C$12:$C$202,MATCH($A131,'Annex 4 LDNO charges'!$A$12:$A$202,0))) -> 0 | E131: 0
A132: LDNO 132kV: LV Sub Site Specific No Residual | B132: =IFERROR(INDEX('Annex 1 LV, HV and UMS charges'!$B$13:$B$44,MATCH($A132,'Annex 1 LV, HV and UMS charges'!$A$13:$A$44,0)),IF(INDEX('Annex 4 LDNO charges'!$B$12:$B$202,MATCH($A132,'Annex 4 LDNO charges'!$A$12:$A$202,0))=0,"",INDEX('Annex 4 LDNO charges'!$B$12:$B$202,MATCH($A132,'Annex 4 LDNO charges'!$A$12:$A$202,0)))) -> J50 | C132: =IFERROR(INDEX('Annex 1 LV, HV and UMS charges'!$C$13:$C$44,MATCH($A132,'Annex 1 LV, HV and UMS charges'!$A$13:$A$44,0)),INDEX('Annex 4 LDNO charges'!$C$12:$C$202,MATCH($A132,'Annex 4 LDNO charges'!$A$12:$A$202,0))) -> 0 | E132: 0
A133: LDNO 132kV: LV Sub Site Specific Band 1 | B133: =IFERROR(INDEX('Annex 1 LV, HV and UMS charges'!$B$13:$B$44,MATCH($A133,'Annex 1 LV, HV and UMS charges'!$A$13:$A$44,0)),IF(INDEX('Annex 4 LDNO charges'!$B$12:$B$202,MATCH($A133,'Annex 4 LDNO charges'!$A$12:$A$202,0))=0,"",INDEX('Annex 4 LDNO charges'!$B$12:$B$202,MATCH($A133,'Annex 4 LDNO charges'!$A$12:$A$202,0)))) -> J51 | C133: =IFERROR(INDEX('Annex 1 LV, HV and UMS charges'!$C$13:$C$44,MATCH($A133,'Annex 1 LV, HV and UMS charges'!$A$13:$A$44,0)),INDEX('Annex 4 LDNO charges'!$C$12:$C$202,MATCH($A133,'Annex 4 LDNO charges'!$A$12:$A$202,0))) -> 0 | E133: 0
... A141: LDNO 132kV: HV Site Specific Band 4 | B141: =IFERROR(INDEX('Annex 1 LV, HV and UMS charges'!$B$13:$B$44,MATCH($A141,'Annex 1 LV, HV and UMS charges'!$A$13:$A$44,0)),IF(INDEX('Annex 4 LDNO charges'!$B$12:$B$202,MATCH($A141,'Annex 4 LDNO charges'!$A$12:$A$202,0))=0,"",INDEX('Annex 4 LDNO charges'!$B$12:$B$202,MATCH($A141,'Annex 4 LDNO charges'!$A$12:$A$202,0)))) -> K54 | C141: =IFERROR(INDEX('Annex 1 LV, HV and UMS charges'!$C$13:$C$44,MATCH($A141,'Annex 1 LV, HV and UMS charges'!$A$13:$A$44,0)),INDEX('Annex 4 LDNO charges'!$C$12:$C$202,MATCH($A141,'Annex 4 LDNO charges'!$A$12:$A$202,0))) -> 0 | E141: 0
A142: LDNO 0000: Domestic Aggregated or CT with Residual | B142: =IFERROR(INDEX('Annex 1 LV, HV and UMS charges'!$B$13:$B$44,MATCH($A142,'Annex 1 LV, HV and UMS charges'!$A$13:$A$44,0)),IF(INDEX('Annex 4 LDNO charges'!$B$12:$B$202,MATCH($A142,'Annex 4 LDNO charges'!$A$12:$A$202,0))=0,"",INDEX('Annex 4 LDNO charges'!$B$12:$B$202,MATCH($A142,'Annex 4 LDNO charges'!$A$12:$A$202,0)))) -> A60 | C142: =IFERROR(INDEX('Annex 1 LV, HV and UMS charges'!$C$13:$C$44,MATCH($A142,'Annex 1 LV, HV and UMS charges'!$A$13:$A$44,0)),INDEX('Annex 4 LDNO charges'!$C$12:$C$202,MATCH($A142,'Annex 4 LDNO charges'!$A$12:$A$202,0))) -> 0, 1, 2 | D142: 0 | E142: 0
A143: LDNO 0000: Non-Domestic Aggregated or CT No Residual | B143: =IFERROR(INDEX('Annex 1 LV, HV and UMS charges'!$B$13:$B$44,MATCH($A143,'Annex 1 LV, HV and UMS charges'!$A$13:$A$44,0)),IF(INDEX('Annex 4 LDNO charges'!$B$12:$B$202,MATCH($A143,'Annex 4 LDNO charges'!$A$12:$A$202,0))=0,"",INDEX('Annex 4 LDNO charges'!$B$12:$B$202,MATCH($A143,'Annex 4 LDNO charges'!$A$12:$A$202,0)))) -> C60 | C143: =IFERROR(INDEX('Annex 1 LV, HV and UMS charges'!$C$13:$C$44,MATCH($A143,'Annex 1 LV, HV and UMS charges'!$A$13:$A$44,0)),INDEX('Annex 4 LDNO charges'!$C$12:$C$202,MATCH($A143,'Annex 4 LDNO charges'!$A$12:$A$202,0))) -> 0, 3, 4, 5-8 | E143: 0
...

Sheet Nodal prices
A1: Back to Overview
A2: =Overview!B4& " - Effective from "&Overview!D4&" - "&Overview!E4&" Nodal/Zonal charges" -> London Power Networks - Effective from 1 April 2027 - Final Nodal/Zonal charges
A4: Node/Zone ID | B4: Geographical name | C4: Local charge 1 £/kVA | D4: Remote charge 1 £/kVA
A5: ABPA51 | B5: Aberdeen Pl A 11kV | C5: 5.2100263 | D5: 0.0032557065
A6: ABPA52 | B6: Aberdeen Pl A 11kV | C6: 0.34981578 | D6: -0.00029295903
A7: ABPB51 | B7: Aberdeen Pl B 11kV | C7: 2.3838268 | D7: -0.00018123474
A8: ACTL81 | B8: Acton Lane 22kV | C8: 0 | D8: 0
A9: AMBL51 | B9: Amberley Rd 11kV | C9: 0 | D9: 0.0097971283
A10: AMBL52 | B10: Amberley Rd 11kV | C10: 0 | D10: 0.0058944888
A11: AXES51 | B11: Axe St 11kV | C11: 3.0752415 | D11: 11.289296
A12: AXES52 | B12: Axe St 11kV | C12: 3.0933138 | D12: 8.8409186
A13: BACA51 | B13: Back Hill A 11kV | C13: 0.063057713 | D13: 0.17993939
A14: BACA52 | B14: Back Hill A 11kV | C14: 1.470067 | D14: 0.47188811
A15: BANC51 | B15: Bankside C 11kV | C15: 0 | D15: 1.1701686
A16: BANC52 | B16: Bankside C 11kV | C16: 0 | D16: 1.1688223
... A313: WDGR51 | B313: Woodgrange Park 11kV | C313: 1.7612816 | D313: 8.1442196

Sheet SSC unit rate lookup
A1: Back to Overview
A28: Standard Settlement Configuration Id | B28: Standard Settlement Configuration Desc | C28: Common Decode | F28: Change implemented | G28: Date | H28: Comments
A29: 3 | B29: 10-hour OP | C29: A/R | F29: Notes updated | G29: 43626 | H29: Updated to reflect DCP 268 which delinks all tariffs from the TPR bands
A30: 4 | B30: 10-hour OP | C30: A/R | F30: Code 1 & 2 changed to A | G30: 43626 | H30: Updated to reflect DCP 268 which delinks all tariffs from the TPR bands
A31: 5 | B31: 10-hour OP + w/e | C31: A/R | F31: Code O changed to A/R | G31: 43626 | H31: Updated to reflect DCP 268 which delinks all tariffs from the TPR bands
A32: 6 | B32: 10.5-hour OP | C32: A/R | F32: Removed TPR | G32: 43626 | H32: Removed TPR lookup element as this no longer effects which rate to apply
A33: 7 | B33: 10.5-hour OP | C33: A/R
A34: 8 | B34: 10.5-hour OP | C34: A/R
A35: 9 | B35: 10.5-hour OP | C35: A/R
A36: 10 | B36: 10.5-hour OP | C36: A/R
A37: 11 | B37: 10.5-hour OP | C37: A/R
A38: 12 | B38: 10.5-hour OP | C38: A/R
A39: 13 | B39: 11 Hour OP | C39: A/R
A40: 15 | B40: 11 Hour OP | C40: A/R
A41: 16 | B41: 11.5-hour OP | C41: A/R
A42: 17 | B42: 11.5-hour OP | C42: A/R
A43: 18 | B43: 11.5-hour OP | C43: A/R
A44: 19 | B44: 11.5-hour OP | C44: A/R
... A764: 997 | B764: Evening/Weekend - BST | C764: A

Sheet Residual Charging Bands
A1: Back to Overview
A2: =Overview!B4& " - Effective from "&Overview!C4&" - "&Overview!E4&" Residual Charging Bands" -> London Power Networks - Effective from 2027/28 - Final Residual Charging Bands
A4: Voltage of Connection | B4: Band | C4: Units | D4: Lower Threshold* | E4: Upper Threshold* | F4: Residual Charge per Fixed Charge** (p/day) | G4: Residual Charge per Unit rate 1** (p/kWh) | H4: Residual Charge per Unit rate 2** (p/kWh) | I4: Residual Charge per Unit rate 3** (p/kWh)
A5: Domestic Aggregated | B5: Single band | C5: - | F5: -5.4849222 | G5: -0.21746675 | H5: -0.21746675 | I5: -0.10781044
A6: Designated Properties connected at LV, billing with no MIC | B6: 1 | C6: kWh | D6: 0 | E6: 3986 | F6: -5.9094115 | G6: -0.11999497 | H6: -0.11999497 | I6: -0.083462426
B7: 2 | C7: kWh | D7: 3986 | E7: 13677 | F7: -5.9094115 | G7: -0.96622523 | H7: -0.96622523 | I7: -0.083462426
B8: 3 | C8: kWh | D8: 13677 | E8: 27543 | F8: -5.9094115 | G8: -1.2769282 | H8: -1.130445 | I8: -0.083462426
B9: 4 | C9: kWh | D9: 27543 | E9: ∞ | F9: -5.9094115 | G9: -1.6787005 | H9: -1.130445 | I9: -0.083462426
A10: Designated Properties connected at LV, billing with MIC | B10: 1 | C10: kVA | D10: 0 | E10: 90 | F10: -12.207098 | G10: -2.7532511 | H10: -0.59937426 | I10: -0.03257764
B11: 2 | C11: kVA | D11: 90 | E11: 150 | F11: -12.207098 | G11: -2.8179092 | H11: -0.59937426 | I11: -0.03257764
B12: 3 | C12: kVA | D12: 150 | E12: 250 | F12: -12.207098 | G12: -2.8759502 | H12: -0.59937426 | I12: -0.03257764
B13: 4 | C13: kVA | D13: 250 | E13: ∞ | F13: -12.207098 | G13: -2.9477089 | H13: -0.59937426 | I13: -0.03257764
A14: Designated Properties connected at HV | B14: 1 | C14: kVA | D14: 0 | E14: 500 | F14: -129.42482 | G14: -3.0674115 | H14: -0.44576703 | I14: -0.025715095
B15: 2 | C15: kVA | D15: 500 | E15: 1100 | F15: -129.42482 | G15: -3.2643898 | H15: -0.44576703 | I15: -0.025715095
B16: 3 | C16: kVA | D16: 1100 | E16: 2000 | F16: -129.42482 | G16: -3.1831089 | H16: -0.44576703 | I16: -0.025715095
B17: 4 | C17: kVA | D17: 2000 | E17: ∞ | F17: -129.42482 | G17: -3.2478135 | H17: -0.44576703 | I17: -0.025715095
A18: Designated EHV Properties | B18: 1 | C18: kVA | D18: 0 | E18: 3500 | F18: 975.6701
B19: 2 | C19: kVA | D19: 3500 | E19: 11000 | F19: 10677.011
B20: 3 | C20: kVA | D20: 11000 | E20: 20000 | F20: 28207.127
B21: 4 | C21: kVA | D21: 20000 | E21: ∞ | F21: 68626.324
A22: * All boundaries are inclusive of the upper threshold and exclusive of the lower threshold i.e. Lower < x ≤ Upper.
A23: **Residual charge element in London Power Networks CDCM model is negative and therefore the application of the residual reduces the calculated fixed charge. If the fixed charge reaches zero then the remaining reduction is applied to the unit rates.

Sheet TNUoS Mapping
A1: Back to Overview
A2: =Overview!C4&" - Effective from "&Overview!D4&" - "&Overview!F4&" TNUoS Mapping" -> 2027/28 - Effective from 1 April 2027 - TNUoS Mapping
A4: DUoS Tariff name | B4: TNUoS Site Charging Band
A5: Domestic Aggregated or CT with Residual | B5: Domestic
A6: Domestic Aggregated (Related MPAN) | B6: n/a (Non-Final Demand Site)
A7: Non-Domestic Aggregated or CT No Residual | B7: =$B$6 -> n/a (Non-Final Demand Site)
A8: Non-Domestic Aggregated or CT Band 1 | B8: LV_NoMIC_1
A9: Non-Domestic Aggregated or CT Band 2 | B9: LV_NoMIC_2
A10: Non-Domestic Aggregated or CT Band 3 | B10: LV_NoMIC_3
A11: Non-Domestic Aggregated or CT Band 4 | B11: LV_NoMIC_4
A12: Non-Domestic Aggregated (related MPAN) | B12: =$B$6 -> n/a (Non-Final Demand Site)
A13: LV Site Specific No Residual | B13: =$B$6 -> n/a (Non-Final Demand Site)
A14: LV Site Specific Band 1 | B14: LV1
A15: LV Site Specific Band 2 | B15: LV2
A16: LV Site Specific Band 3 | B16: LV3
A17: LV Site Specific Band 4 | B17: LV4
A18: LV Sub Site Specific No Residual | B18: =$B$6 -> n/a (Non-Final Demand Site)
A19: LV Sub Site Specific Band 1 | B19: LV1
A20: LV Sub Site Specific Band 2 | B20: LV2
A21: LV Sub Site Specific Band 3 | B21: LV3
A22: LV Sub Site Specific Band 4 | B22: LV4
A23: HV Site Specific No Residual | B23: =$B$6 -> n/a (Non-Final Demand Site)
A24: HV Site Specific Band 1 | B24: HV1
A25: HV Site Specific Band 2 | B25: HV2
A26: HV Site Specific Band 3 | B26: HV3
A27: HV Site Specific Band 4 | B27: HV4
A28: Unmetered Supplies | B28: n/a (p/kWh charge)
A29: LV Generation Aggregated | B29: =$B$6 -> n/a (Non-Final Demand Site)
A30: LV Sub Generation Aggregated | B30: =$B$6 -> n/a (Non-Final Demand Site)
A31: LV Generation Site Specific | B31: =$B$6 -> n/a (Non-Final Demand Site)
A32: LV Generation Site Specific no RP charge | B32: =$B$6 -> n/a (Non-Final Demand Site)
A33: LV Sub Generation Site Specific | B33: =$B$6 -> n/a (Non-Final Demand Site)
A34: LV Sub Generation Site Specific no RP charge | B34: =$B$6 -> n/a (Non-Final Demand Site)
A35: HV Generation Site Specific | B35: =$B$6 -> n/a (Non-Final Demand Site)
A36: HV Generation Site Specific no RP charge | B36: =$B$6 -> n/a (Non-Final Demand Site)
A37: Designated EHV Site Specific No Residual | B37: =$B$6 -> n/a (Non-Final Demand Site)
A38: Designated EHV Site Specific Band 1 | B38: EHV1
A39: Designated EHV Site Specific Band 2 | B39: EHV2
A40: Designated EHV Site Specific Band 3 | B40: EHV3
A41: Designated EHV Site Specific Band 4 | B41: EHV4

Sheet Charge Calculator
B1: Back to Overview
B2: =Overview!B4& " - Effective from "&Overview!D4&" - "&Overview!E4 -> London Power Networks - Effective from 1 April 2027 - Final | AC2: Tariff name | AD2: Red/black unit charge p/kWh | AE2: Amber/yellow unit charge p/kWh | AF2: Green unit charge p/kWh | AG2: Fixed charge p/MPAN/day | AH2: Capacity charge p/kVA/day | AI2: Exceeded capacity charge p/kVA/day | AJ2: Reactive power charge p/kVArh
AC3: Domestic Aggregated or CT with Residual | AD3: Red unit charge p/kWh | AE3: Amber unit charge p/kWh | AF3: Green unit charge p/kWh | AG3: Fixed charge p/MPAN/day | AH3: n/a | AI3: n/a | AJ3: n/a
B4: LV and HV designated properties and Unmetered Supplies tariff calculator | L4: EHV designated property calculator | AC4: Domestic Aggregated (Related MPAN) | AD4: Red unit charge p/kWh | AE4: Amber unit charge p/kWh | AF4: Green unit charge p/kWh | AG4: n/a | AH4: n/a | AI4: n/a | AJ4: n/a
B5: Step 1, Choose your tariff using the drop down list in cell B10 | L5: Step 1, Choose your tariff using the drop down list in cell L10. Please note, this calculator returns tariffs from Annex 2 only. If your site has a new or amended tariff in Annex 6 this will need to be entered manually. | AC5: Non-Domestic Aggregated or CT No Residual | AD5: Red unit charge p/kWh | AE5: Amber unit charge p/kWh | AF5: Green unit charge p/kWh | AG5: Fixed charge p/MPAN/day | AH5: n/a | AI5: n/a | AJ5: n/a
B6: Step 2, After selecting a tariff in step 1, Cells C12-I12 will generate headings, please enter your consumption in cells C13:I13 underneath each heading generated (if no heading leave cell blank) | L6: Step 2, After selecting a tariff in step 1, Cells M12-T12 will generate headings, please enter your consumption in cells M13:T13 underneath each heading generated (if no heading leave cell blank) | AC6: Non-Domestic Aggregated or CT Band 1 | AD6: Red unit charge p/kWh | AE6: Amber unit charge p/kWh | AF6: Green unit charge p/kWh | AG6: Fixed charge p/MPAN/day | AH6: n/a | AI6: n/a | AJ6: n/a
B7: Step 3, Enter a forecast of consumption if required in cells C14:I14 | L7: Step 3, Enter a forecast of consumption if required in cells M14:T14 | AC7: Non-Domestic Aggregated or CT Band 2 | AD7: Red unit charge p/kWh | AE7: Amber unit charge p/kWh | AF7: Green unit charge p/kWh | AG7: Fixed charge p/MPAN/day | AH7: n/a | AI7: n/a | AJ7: n/a
AC8: Non-Domestic Aggregated or CT Band 3 | AD8: Red unit charge p/kWh | AE8: Amber unit charge p/kWh | AF8: Green unit charge p/kWh | AG8: Fixed charge p/MPAN/day | AH8: n/a | AI8: n/a | AJ8: n/a
B9: Tariff details Choose tariff name from drop down box below | C9: =IFERROR(_xlfn.XLOOKUP($B$10,$AC$2:$AC$34,AD$2:AD$34),AD2) -> Red/black unit charge p/kWh | D9: =IFERROR(_xlfn.XLOOKUP($B$10,$AC$2:$AC$34,AE$2:AE$34),AE2) -> Amber/yellow unit charge p/kWh | E9: =IFERROR(_xlfn.XLOOKUP($B$10,$AC$2:$AC$34,AF$2:AF$34),AF2) -> Green unit charge p/kWh | F9: =IFERROR(_xlfn.XLOOKUP($B$10,$AC$2:$AC$34,AG$2:AG$34),AG2) -> Fixed charge p/MPAN/day | G9: =IFERROR(_xlfn.XLOOKUP($B$10,$AC$2:$AC$34,AH$2:AH$34),AH2) -> Capacity charge p/kVA/day | H9: =IFERROR(_xlfn.XLOOKUP($B$10,$AC$2:$AC$34,AI$2:AI$34),AI2) -> Exceeded capacity charge p/kVA/day | I9: =IFERROR(_xlfn.XLOOKUP($B$10,$AC$2:$AC$34,AJ$2:AJ$34),AJ2) -> Reactive power charge p/kVArh | L9: Site details Choose the site name from the drop down box below | M9: ='Annex 2 Designated EHV charges'!I10 -> Import Super Red unit charge (p/kWh) | N9: ='Annex 2 Designated EHV charges'!J10 -> Import fixed charge (p/day) | O9: ='Annex 2 Designated EHV charges'!K10 -> Import capacity charge (p/kVA/day) | P9: ='Annex 2 Designated EHV charges'!L10 -> Import exceeded capacity charge (p/kVA/day) | Q9: ='Annex 2 Designated EHV charges'!M10 -> Export Super Red unit charge (p/kWh) | R9: ='Annex 2 Designated EHV charges'!N10 -> Export fixed charge (p/day) | S9: ='Annex 2 Designated EHV charges'!O10 -> Export capacity charge (p/kVA/day) | T9: ='Annex 2 Designated EHV charges'!P10 -> Export exceeded capacity charge (p/kVA/day) | AC9: Non-Domestic Aggregated or CT Band 4 | AD9: Red unit charge p/kWh | AE9: Amber unit charge p/kWh | AF9: Green unit charge p/kWh | AG9: Fixed charge p/MPAN/day | AH9: n/a | AI9: n/a | AJ9: n/a
C10: =IFERROR(VLOOKUP($B$10,'Annex 1 LV, HV and UMS charges'!$A:$K,4,FALSE),"") | D10: =IFERROR(VLOOKUP($B$10,'Annex 1 LV, HV and UMS charges'!$A:$K,5,FALSE),"") | E10: =IFERROR(VLOOKUP($B$10,'Annex 1 LV, HV and UMS charges'!$A:$K,6,FALSE),"") | F10: =IFERROR(VLOOKUP($B$10,'Annex 1 LV, HV and UMS charges'!$A:$K,7,FALSE),"") | G10: =IFERROR(VLOOKUP($B$10,'Annex 1 LV, HV and UMS charges'!$A:$K,8,FALSE),"") | H10: =IFERROR(VLOOKUP($B$10,'Annex 1 LV, HV and UMS charges'!$A:$K,9,FALSE),"") | I10: =IFERROR(VLOOKUP($B$10,'Annex 1 LV, HV and UMS charges'!$A:$K,10,FALSE),"") | M10: =IFERROR(_xlfn.XLOOKUP($L$10,'Annex 2 Designated EHV charges'!$G:$G,'Annex 2 Designated EHV charges'!I:I),"") -> 0 | N10: =IFERROR(_xlfn.XLOOKUP($L$10,'Annex 2 Designated EHV charges'!$G:$G,'Annex 2 Designated EHV charges'!J:J),"") -> 0 | O10: =IFERROR(_xlfn.XLOOKUP($L$10,'Annex 2 Designated EHV charges'!$G:$G,'Annex 2 Designated EHV charges'!K:K),"") -> 0 | P10: =IFERROR(_xlfn.XLOOKUP($L$10,'Annex 2 Designated EHV charges'!$G:$G,'Annex 2 Designated EHV charges'!L:L),"") -> 0 | Q10: =IFERROR(_xlfn.XLOOKUP($L$10,'Annex 2 Designated EHV charges'!$G:$G,'Annex 2 Designated EHV charges'!M:M),"") -> 0 | R10: =IFERROR(_xlfn.XLOOKUP($L$10,'Annex 2 Designated EHV charges'!$G:$G,'Annex 2 Designated EHV charges'!N:N),"") -> 0 | S10: =IFERROR(_xlfn.XLOOKUP($L$10,'Annex 2 Designated EHV charges'!$G:$G,'Annex 2 Designated EHV charges'!O:O),"") -> 0 | T10: =IFERROR(_xlfn.XLOOKUP($L$10,'Annex 2 Designated EHV charges'!$G:$G,'Annex 2 Designated EHV charges'!P:P),"") -> 0 | AC10: Non-Domestic Aggregated (related MPAN) | AD10: Red unit charge p/kWh | AE10: Amber unit charge p/kWh | AF10: Green unit charge p/kWh | AG10: n/a | AH10: n/a | AI10: n/a | AJ10: n/a
AC11: LV Site Specific No Residual | AD11: Red unit charge p/kWh | AE11: Amber unit charge p/kWh | AF11: Green unit charge p/kWh | AG11: Fixed charge p/MPAN/day | AH11: Capacity charge p/kVA/day | AI11: Exceeded Capacity charge p/kVA/day | AJ11: Reactive power charge p/kVArh
B12: Tariff components | C12: =C9 -> Red/black unit charge p/kWh | D12: =D9 -> Amber/yellow unit charge p/kWh | E12: =E9 -> Green unit charge p/kWh | F12: Number of days in consumption period i.e. 365 if one year | G12: Maximum import or export capacity kVA | H12: Average daily exceeded capacity kVA | I12: Excess reactive units kVArh | L12: Tariff components | M12: Import super red kWh | N12: Number of days in consumption period i.e. 365 if one year | O12: Maximum import capacity kVA | P12: Average daily exceeded capacity kVA | Q12: Export Super Red kWh | R12: Number of days in consumption period i.e. 365 if one year | S12: Maximum export capacity kVA | T12: Average daily exceeded capacity kVA | AC12: LV Site Specific Band 1 | AD12: Red unit charge p/kWh | AE12: Amber unit charge p/kWh | AF12: Green unit charge p/kWh | AG12: Fixed charge p/MPAN/day | AH12: Capacity charge p/kVA/day | AI12: Exceeded Capacity charge p/kVA/day | AJ12: Reactive power charge p/kVArh
B13: Enter current consumption details | L13: Enter current consumption details | R13: =N13 -> 0 | AC13: LV Site Specific Band 2 | AD13: Red unit charge p/kWh | AE13: Amber unit charge p/kWh | AF13: Green unit charge p/kWh | AG13: Fixed charge p/MPAN/day | AH13: Capacity charge p/kVA/day | AI13: Exceeded Capacity charge p/kVA/day | AJ13: Reactive power charge p/kVArh
B14: Enter forecast consumption details (if different) | C14: =C13 -> 0 | D14: =D13 -> 0 | E14: =E13 -> 0 | F14: =F13 -> 0 | G14: =G13 -> 0 | H14: =H13 -> 0 | I14: =I13 -> 0 | L14: Enter forecast consumption details (if different) | M14: =M13 -> 0 | N14: =N13 -> 0 | O14: =O13 -> 0 | P14: =P13 -> 0 | Q14: =Q13 -> 0 | R14: =R13 -> 0 | S14: =S13 -> 0 | T14: =T13 -> 0 | AC14: LV Site Specific Band 3 | AD14: Red unit charge p/kWh | AE14: Amber unit charge p/kWh | AF14: Green unit charge p/kWh | AG14: Fixed charge p/MPAN/day | AH14: Capacity charge p/kVA/day | AI14: Exceeded Capacity charge p/kVA/day | AJ14: Reactive power charge p/kVArh
AC15: LV Site Specific Band 4 | AD15: Red unit charge p/kWh | AE15: Amber unit charge p/kWh | AF15: Green unit charge p/kWh | AG15: Fixed charge p/MPAN/day | AH15: Capacity charge p/kVA/day | AI15: Exceeded Capacity charge p/kVA/day | AJ15: Reactive power charge p/kVArh
B16: Charge components | C16: Unit 1 £ | D16: Unit 2 £ | E16: Unit 3 £ | F16: Fixed charge £ | G16: Capacity charge £ | H16: Exceeded capacity charge £ | I16: Reactive power charge £ | L16: Charge components | M16: Import super red charge £ | N16: Import fixed charge £ | O16: Import capacity charge £ | P16: Import exceeded capacity charge £ | Q16: Export super red charge £ | R16: Export fixed charge £ | S16: Export capacity charge £ | T16: Export exceeded capacity charge £ | AC16: LV Sub Site Specific No Residual | AD16: Red unit charge p/kWh | AE16: Amber unit charge p/kWh | AF16: Green unit charge p/kWh | AG16: Fixed charge p/MPAN/day | AH16: Capacity charge p/kVA/day | AI16: Exceeded Capacity charge p/kVA/day | AJ16: Reactive power charge p/kVArh
B17: Current consumption period charges | C17: =IFERROR(C10*C13/100,"") | D17: =IFERROR(D10*D13/100,"") | E17: =IFERROR(E10*E13/100,"") | F17: =IFERROR(F10*F13/100,"") | G17: =IFERROR(G10*G13*F13/100,"") | H17: =IFERROR(H10*H13*F13/100,"") | I17: =IFERROR(I10*I13/100,"") | L17: Current consumption period charges | M17: =IFERROR(M10*M13/100,"") -> 0 | N17: =IFERROR(N10*N13/100,"") -> 0 | O17: =IFERROR(O10*O13*N13/100,"") -> 0 | P17: =IFERROR(P10*P13*N13/100,"") -> 0 | Q17: =IFERROR(Q10*Q13/100,"") -> 0 | R17: =IFERROR(R10*R13/100,"") -> 0 | S17: =IFERROR(S10*S13*R13/100,"") -> 0 | T17: =IFERROR(T10*T13*R13/100,"") -> 0 | AC17: LV Sub Site Specific Band 1 | AD17: Red unit charge p/kWh | AE17: Amber unit charge p/kWh | AF17: Green unit charge p/kWh | AG17: Fixed charge p/MPAN/day | AH17: Capacity charge p/kVA/day | AI17: Exceeded Capacity charge p/kVA/day | AJ17: Reactive power charge p/kVArh
B18: Forecast consumption period charges | C18: =IFERROR(C10*C14/100,"") | D18: =IFERROR(D10*D14/100,"") | E18: =IFERROR(E10*E14/100,"") | F18: =IFERROR(F10*F14/100,"") | G18: =IFERROR(G10*G14*F14/100,"") | H18: =IFERROR(H10*H14*F14/100,"") | I18: =IFERROR(I10*I14/100,"") | L18: Forecast consumption period charges | M18: =IFERROR(M10*M14/100,"") -> 0 | N18: =IFERROR(N10*N14/100,"") -> 0 | O18: =IFERROR(O10*O14*N14/100,"") -> 0 | P18: =IFERROR(P10*P14*N14/100,"") -> 0 | Q18: =IFERROR(Q10*Q14/100,"") -> 0 | R18: =IFERROR(R10*R14/100,"") -> 0 | S18: =IFERROR(S10*S14*R14/100,"") -> 0 | T18: =IFERROR(T10*T14*R14/100,"") -> 0 | AC18: LV Sub Site Specific Band 2 | AD18: Red unit charge p/kWh | AE18: Amber unit charge p/kWh | AF18: Green unit charge p/kWh | AG18: Fixed charge p/MPAN/day | AH18: Capacity charge p/kVA/day | AI18: Exceeded Capacity charge p/kVA/day | AJ18: Reactive power charge p/kVArh
AC19: LV Sub Site Specific Band 3 | AD19: Red unit charge p/kWh | AE19: Amber unit charge p/kWh | AF19: Green unit charge p/kWh | AG19: Fixed charge p/MPAN/day | AH19: Capacity charge p/kVA/day | AI19: Exceeded Capacity charge p/kVA/day | AJ19: Reactive power charge p/kVArh
C20: Total charge £ | M20: Import total charge £ | N20: Export total charge £ | AC20: LV Sub Site Specific Band 4 | AD20: Red unit charge p/kWh | AE20: Amber unit charge p/kWh | AF20: Green unit charge p/kWh | AG20: Fixed charge p/MPAN/day | AH20: Capacity charge p/kVA/day | AI20: Exceeded Capacity charge p/kVA/day | AJ20: Reactive power charge p/kVArh
B21: Current consumption period charges | C21: =SUM(C17:I17) -> 0 | L21: Current consumption period charges | M21: =SUM(M17:P17) -> 0 | N21: =SUM(Q17:T17) -> 0 | AC21: HV Site Specific No Residual | AD21: Red unit charge p/kWh | AE21: Amber unit charge p/kWh | AF21: Green unit charge p/kWh | AG21: Fixed charge p/MPAN/day | AH21: Capacity charge p/kVA/day | AI21: Exceeded Capacity charge p/kVA/day | AJ21: Reactive power charge p/kVArh
B22: Forecast consumption period charges | C22: =SUM(C18:I18) -> 0 | L22: Forecast consumption period charges | M22: =SUM(M18:P18) -> 0 | N22: =SUM(Q18:T18) -> 0 | AC22: HV Site Specific Band 1 | AD22: Red unit charge p/kWh | AE22: Amber unit charge p/kWh | AF22: Green unit charge p/kWh | AG22: Fixed charge p/MPAN/day | AH22: Capacity charge p/kVA/day | AI22: Exceeded Capacity charge p/kVA/day | AJ22: Reactive power charge p/kVArh
AC23: HV Site Specific Band 2 | AD23: Red unit charge p/kWh | AE23: Amber unit charge p/kWh | AF23: Green unit charge p/kWh | AG23: Fixed charge p/MPAN/day | AH23: Capacity charge p/kVA/day | AI23: Exceeded Capacity charge p/kVA/day | AJ23: Reactive power charge p/kVArh
B24: These charges are estimates based on tariff selected and consumption values entered. | L24: These charges are estimates based on site selected and consumption values entered. | AC24: HV Site Specific Band 3 | AD24: Red unit charge p/kWh | AE24: Amber unit charge p/kWh | AF24: Green unit charge p/kWh | AG24: Fixed charge p/MPAN/day | AH24: Capacity charge p/kVA/day | AI24: Exceeded Capacity charge p/kVA/day | AJ24: Reactive power charge p/kVArh
AC25: HV Site Specific Band 4 | AD25: Red unit charge p/kWh | AE25: Amber unit charge p/kWh | AF25: Green unit charge p/kWh | AG25: Fixed charge p/MPAN/day | AH25: Capacity charge p/kVA/day | AI25: Exceeded Capacity charge p/kVA/day | AJ25: Reactive power charge p/kVArh
AC26: Unmetered Supplies | AD26: Black unit charge p/kWh | AE26: Yellow unit charge p/kWh | AF26: Green unit charge p/kWh | AG26: n/a | AH26: n/a | AI26: n/a | AJ26: n/a
AC27: LV Generation Aggregated | AD27: Red unit charge p/kWh | AE27: Amber unit charge p/kWh | AF27: Green unit charge p/kWh | AG27: Fixed charge p/MPAN/day | AH27: n/a | AI27: n/a | AJ27: n/a
AC28: LV Sub Generation Aggregated | AD28: Red unit charge p/kWh | AE28: Amber unit charge p/kWh | AF28: Green unit charge p/kWh | AG28: Fixed charge p/MPAN/day | AH28: n/a | AI28: n/a | AJ28: n/a
AC29: LV Generation Site Specific | AD29: Red unit charge p/kWh | AE29: Amber unit charge p/kWh | AF29: Green unit charge p/kWh | AG29: Fixed charge p/MPAN/day | AH29: n/a | AI29: n/a | AJ29: Reactive power charge p/kVArh
AC30: LV Generation Site Specific no RP charge | AD30: Red unit charge p/kWh | AE30: Amber unit charge p/kWh | AF30: Green unit charge p/kWh | AG30: Fixed charge p/MPAN/day | AH30: n/a | AI30: n/a | AJ30: n/a
AC31: LV Sub Generation Site Specific | AD31: Red unit charge p/kWh | AE31: Amber unit charge p/kWh | AF31: Green unit charge p/kWh | AG31: Fixed charge p/MPAN/day | AH31: n/a | AI31: n/a | AJ31: Reactive power charge p/kVArh
AC32: LV Sub Generation Site Specific no RP charge | AD32: Red unit charge p/kWh | AE32: Amber unit charge p/kWh | AF32: Green unit charge p/kWh | AG32: Fixed charge p/MPAN/day | AH32: n/a | AI32: n/a | AJ32: n/a
AC33: HV Generation Site Specific | AD33: Red unit charge p/kWh | AE33: Amber unit charge p/kWh | AF33: Green unit charge p/kWh | AG33: Fixed charge p/MPAN/day | AH33: n/a | AI33: n/a | AJ33: Reactive power charge p/kVArh
AC34: HV Generation Site Specific no RP charge | AD34: Red unit charge p/kWh | AE34: Amber unit charge p/kWh | AF34: Green unit charge p/kWh | AG34: Fixed charge p/MPAN/day | AH34: n/a | AI34: n/a | AJ34: n/a
